Workbook

Sheet All Charters Unified
A1: Charter_Source Ticket # | B1: Charter Month | C1: Source_File | D1: NYSSIS ID | E1: Student ID | F1: Last Name | G1: First Name | H1: Grade Level | I1: DOB | J1: School Name | K1: Enroll Date | L1: Withdraw Date | M1: SCSD FTE | N1: Student Status | O1: Notes for Patrick | P1: SPED_Flag
A2: Southside 291462 | B2: 46174 | C2: southside_291462_unified-roster.xlsx | D2: 1630725543 | E2: 210010695 | F2: Thomas | G2: Aaleiyah | H2: 2 | I2: 43094 | J2: Southside Academy Charter School | K2: 45904 | M2: 1 | N2: No Good | O2: ST states: student enrolled at Southside Academy Charter School 8/2/255 - 9/1/25 . Entry date is 3> discrepancy. Need charter attendance record to change in ST. | P2: Gen Ed
A3: Southside 291462 | B3: 46174 | C3: southside_291462_unified-roster.xlsx | D3: 7417895120 | E3: 210022348 | F3: East | G3: Abel | H3: K | I3: 43993 | J3: Southside Academy Charter School | K3: 45903 | L3: 45940 | M3: 0.15 | N3: No Good | O3: ST states: student started Southside Academy Charter School 9/3/25 . Entry date is 3> discrepancy. Need charter attendance record to change in ST. | P3: Gen Ed
A4: Southside 291462 | B4: 46174 | C4: southside_291462_unified-roster.xlsx | D4: 6114934235 | E4: 200036757 | F4: Smith | G4: Adorre | H4: 4 | I4: 42225 | J4: Southside Academy Charter School | K4: 45904 | M4: 0.975 | N4: No Good | O4: ST states: student started McKiunley Brighton ES 4/8/26-current. Need charter attendance record to change in ST. | P4: SPED
A5: Southside 291462 | B5: 46174 | C5: southside_291462_unified-roster.xlsx | D5: 8894205962 | E5: 200032672 | F5: Maloof | G5: Aiden | H5: 8 | I5: 41220 | J5: Southside Academy Charter School | K5: 45903 | L5: 46077 | M5: 0.575 | N5: No Good | O5: ST states: Enrolled at Southside Academy 7/1/25-2/9/26. Enrolled at Lincoln MS 2/10/26-current. Exit date 3> discrepancy. Need charter attendance record to change in ST. | P5: Gen Ed
A6: Southside 291462 | B6: 46174 | C6: southside_291462_unified-roster.xlsx | D6: 9715356981 | E6: 210019407 | F6: McClain | G6: Ali | H6: K | I6: 44190 | J6: Southside Academy Charter School | K6: 45904 | M6: 0.975 | N6: No Good | O6: ST states: student enrolled at Southside Academy Charter 1/15/26-current. Entry date is 3> day discrepancy. Need charter attendance record to change in ST. | P6: Gen Ed
A7: Southside 291462 | B7: 46174 | C7: southside_291462_unified-roster.xlsx | D7: 7916282794 | E7: 210003054 | F7: Rufus | G7: Amir | H7: 4 | I7: 42677 | J7: Southside Academy Charter School | K7: 45909 | M7: 0.975 | N7: No Good | O7: ST states: student enrolled at Southside Academny 9/29/25. Entry date 3> day discrepancy. Need charter attendance record to change in ST. | P7: Gen Ed
A8: Southside 291462 | B8: 46174 | C8: southside_291462_unified-roster.xlsx | D8: 5016968523 | F8: Felder | G8: Anessa | H8: 1 | I8: 43675 | J8: Southside Academy Charter School | K8: 45904 | L8: 45917 | M8: 0.05 | N8: No Good | O8: ST states: No charter 25-26 enrollment in ST.Bellevue ES / ES enrollment 7/1/25 - 9/15/25. Enrolled at Van Duyn ES Van Duyn ES / ES - current. Need charter school attendance record to change in ST. | P8: Gen Ed
A9: Southside 291462 | B9: 46174 | C9: southside_291462_unified-roster.xlsx | D9: 1567036743 | E9: 210022223 | F9: Tindley | G9: Annalisse | H9: 2 | I9: 43334 | J9: Southside Academy Charter School | K9: 45915 | M9: 0.95 | N9: No Good | O9: ST states: student enrolled at Southside Academny 9/26/25. Entry date 3> day discrepancy. Need charter attendance record to change in ST. | P9: Gen Ed
A10: Southside 291462 | B10: 46174 | C10: southside_291462_unified-roster.xlsx | D10: 9622581930 | E10: 210014483 | F10: Dennis | G10: Arhianna | H10: 1 | I10: 43699 | J10: Southside Academy Charter School | K10: 45904 | L10: 45994 | M10: 0.3 | N10: No Good | O10: ST states: student enrolled at Southside Academy Charter School 8/16/25.25 11/25/25. Enrolled at HW Smith PK-8 12/1/25 - current. Entry date 3> day discrepancy. Need charter attendance record to change in ST. | P10: Gen Ed
A11: Southside 291462 | B11: 46174 | C11: southside_291462_unified-roster.xlsx | D11: 8381796603 | F11: Loper | G11: Bobby | H11: K | I11: 44194 | J11: Southside Academy Charter School | K11: 45903 | M11: 1 | N11: No Good | O11: ST states:No 25-26 charter shool enrollment entry in ST student enrolled at Bellevue ES 7/1/25-9/10/25. | P11: Gen Ed
A12: Southside 291462 | B12: 46174 | C12: southside_291462_unified-roster.xlsx | D12: 8993227873 | E12: 210019759 | F12: Reome | G12: Caylyn | H12: 1 | I12: 43543 | J12: Southside Academy Charter School | K12: 45903 | L12: 45915 | M12: 0.05 | N12: No Good | O12: ST states: student enrolled at Southside Academy 7/1/25 - 9/11/25. Exit date 3> day discrepancy. Need charter attendance record to change in ST. Enrolled at Syracuse Academy of Science Elementary at St James 9/12/25 | P12: Gen Ed
A13: Southside 291462 | B13: 46174 | C13: southside_291462_unified-roster.xlsx | D13: 5531469482 | E13: 210003314 | F13: Reome Jr. | G13: Christopher | H13: 3 | I13: 42876 | J13: Southside Academy Charter School | K13: 45903 | L13: 45915 | M13: 0.05 | N13: No Good | O13: ST states: student enrolled at Southside Academy 7/1/25 - 9/11/25. Exit date 3> day discrepancy. Need charter attendance record to change in ST. Enrolled at Syracuse Academy of Science Elementary at St James 9/12/25 | P13: Gen Ed
A14: Southside 291462 | B14: 46174 | C14: southside_291462_unified-roster.xlsx | D14: 7205350121 | E14: 210018482 | F14: Davis | G14: Cyh'Mora | H14: 1 | I14: 43826 | J14: Southside Academy Charter School | K14: 45903 | M14: 1 | N14: No Good | O14: ST states: student enrolled at Southside Academy Charter School9/25/25 - current. Entry date 3> day discrepancy. Need charter attendance record to change in ST. | P14: Gen Ed
A15: Southside 291462 | B15: 46174 | C15: southside_291462_unified-roster.xlsx | D15: 4427385530 | F15: 0 | G15: Donald | H15: K | I15: 44172 | J15: Southside Academy Charter School | K15: 45903 | M15: 1 | N15: Not in ST System | O15: Not pulling up in ST. Need more student information. NYSSIS ID, Last name,grade,parent info, gender, race, etc. | P15: Gen Ed
A16: Southside 291462 | B16: 46174 | C16: southside_291462_unified-roster.xlsx | D16: 5481567902 | E16: 210022691 | F16: Hatfield | G16: Draylan | H16: K | I16: 43853 | J16: Southside Academy Charter School | K16: 45905 | M16: 0.975 | N16: No Good | O16: ST states: student enrolled at Southside Academy Charter School 10/28/25 - current. Entry date 3> day discrepancy. Need charter attendance record to change in ST. | P16: SPED
A17: Southside 291462 | B17: 46174 | C17: southside_291462_unified-roster.xlsx | D17: 9345645621 | F17: 0 | G17: Edward | H17: K | I17: 43910 | J17: Southside Academy Charter School | K17: 45918 | M17: 0.925 | N17: Not in ST System | O17: Not pulling up in ST. Need more student information. NYSSIS ID, Last name,grade,parent info, gender, race, etc. | P17: Gen Ed
A18: Southside 291462 | B18: 46174 | C18: southside_291462_unified-roster.xlsx | D18: 3226816591 | E18: 210018247 | F18: Giddings | G18: Gracie | H18: K | I18: 44192 | J18: Southside Academy Charter School | K18: 45904 | M18: 0.975 | N18: No Good | O18: ST states: student enrolled at Southside Academy Charter School 1/7/25- current. Entry date 3> day discrepancy. Need charter attendance record to change in ST. | P18: Gen Ed
A19: Southside 291462 | B19: 46174 | C19: southside_291462_unified-roster.xlsx | D19: 8891043605 | E19: 210011263 | F19: Maldonado | G19: INessa | H19: 2 | I19: 43358 | J19: Southside Academy Charter School | K19: 45910 | M19: 0.975 | N19: No Good | O19: ST states: student enrolled at Southside Academy Charter School 11/5/25- current. Entry date 3> day discrepancy. Need charter attendance record to change in ST. | P19: SPED
A20: Southside 291462 | B20: 46174 | C20: southside_291462_unified-roster.xlsx | D20: 6207168494 | E20: 200038985 | F20: Sallard | G20: Jaliyah | H20: 4 | I20: 42561 | J20: Southside Academy Charter School | K20: 45915 | M20: 0.95 | N20: No Good | O20: ST states: student enrolled at Southside Academy Charter School 9/24/25- current. Entry date 3> day discrepancy. Need charter attendance record to change in ST. | P20: Gen Ed
A21: Southside 291462 | B21: 46174 | C21: southside_291462_unified-roster.xlsx | D21: 7360992380 | E21: 210022689 | F21: Vaughns | G21: Jayceon | H21: 2 | I21: 43318 | J21: Southside Academy Charter School | K21: 45905 | M21: 0.975 | N21: No Good | O21: ST states: student enrolled at Southside Academy Charter School 10/28/25- current. Entry date 3> day discrepancy. Need charter attendance record to change in ST. | P21: SPED
A22: Southside 291462 | B22: 46174 | C22: southside_291462_unified-roster.xlsx | D22: 9316354706 | E22: 210014757 | F22: Jackson | G22: Jordyn | H22: K | I22: 44128 | J22: Southside Academy Charter School | K22: 45903 | M22: 1 | N22: No Good | O22: ST states: student enrolled at Syracuse Academy of Science Elementary at St James 8/15/25 - 9/14/25. Enrolled at Southside Academy 9/15/25 - current. Entry 3> day discrepancy. Need charter attendance record to change in ST. | P22: Gen Ed
A23: Southside 291462 | B23: 46174 | C23: southside_291462_unified-roster.xlsx | F23: 0 | G23: Josiah | H23: 7 | I23: 41450 | J23: Southside Academy Charter School | K23: 45903 | M23: 1 | N23: Not in ST System | O23: Not pulling up in ST. | P23: Gen Ed
A24: Southside 291462 | B24: 46174 | C24: southside_291462_unified-roster.xlsx | D24: 4148681903 | E24: 210019004 | F24: Robertson | G24: Jovanni | H24: 1 | I24: 43725 | J24: Citizenship & Science Academy of Syracuse Charter | K24: 45903 | M24: 1 | N24: No Good | O24: ST states: student enrolled at Citizenship & Science Academy of Syracuse Charter 7/1/25 - 9/10/25.. Enrolled at Southside Academy 9/24/25 - current. Entry 3> day discrepancy. Need charter attendance record to change in ST. | P24: Gen Ed
A25: Southside 291462 | B25: 46174 | C25: southside_291462_unified-roster.xlsx | D25: 3321809294 | E25: 200033900 | F25: Anderson | G25: Juelez | H25: 5 | I25: 41625 | J25: Southside Academy Charter School | K25: 45903 | L25: 45995 | M25: 0.325 | N25: No Good | O25: ST states: student enrolled at Southside Academy Charter School 7/1/25- 11/24/25. Enrolled at STEAM @ Dr King / ES 11/25/25- current. Entry date 3> day discrepancy. Need charter attendance record to change in ST. | P25: SPED
A26: Southside 291462 | B26: 46174 | C26: southside_291462_unified-roster.xlsx | D26: 2807672461 | E26: 200024256 | F26: Cenzalli JR | G26: Justin | H26: 8 | I26: 41042 | J26: Southside Academy Charter School | K26: 45903 | L26: 45919 | M26: 0.075 | N26: No Good | O26: ST states: student enrolled at Southside Academy Charter School 9/6/25 - 9/11/25. Enrolled at Ed Smith PK-8 / MS 9/18/25- 2/6/25. Entry date 3> day discrepancy. Need charter attendance record to change in ST. | P26: SPED
A27: Southside 291462 | B27: 46174 | C27: southside_291462_unified-roster.xlsx | D27: 3908940154 | E27: 210002244 | F27: Lobban | G27: Kahwi | H27: 5 | I27: 41841 | J27: Southside Academy Charter School | K27: 45904 | L27: 45923 | M27: 0.05 | N27: No Good | O27: ST states: student enrolled at Southside Academy Charter School 7/1/25 - 9/8/25. Enrolled at STEAM @ Dr King / ES 9/18/25 - current. Entry date 3> day discrepancy. Need charter attendance record to change in ST. | P27: SPED
A28: Southside 291462 | B28: 46174 | C28: southside_291462_unified-roster.xlsx | D28: 4658757613 | F28: Titus | G28: Kaiden | H28: K | I28: 44196 | J28: Southside Academy Charter School | K28: 45903 | M28: 1 | N28: No Good | O28: ST states: enrolled at McKinley Brighton ES 7/3/25-9/8/25. With note that parent reported child will attend Southside. Need charter attendance report to change in ST. | P28: Gen Ed
A29: Southside 291462 | B29: 46174 | C29: southside_291462_unified-roster.xlsx | D29: 2808195416 | E29: 210017791 | F29: Maddox | G29: Kelani | H29: K | I29: 44152 | J29: Southside Academy Charter School | K29: 45917 | M29: 0.95 | N29: No Good | O29: ST states: student enrolled at Southside Academy Charter School 11/12/25- current. Entry date 3> day discrepancy. Need charter attendance record to change in ST. | P29: Gen Ed
A30: Southside 291462 | B30: 46174 | C30: southside_291462_unified-roster.xlsx | D30: 8014067546 | E30: 210022082 | F30: Suressi | G30: Kilani | H30: K | I30: 43979 | J30: Southside Academy Charter School | K30: 45905 | L30: 46010 | M30: 0.35 | N30: No Good | O30: ST states: student enrolled at Southside Academy Charter School 12/10/2025 - 12/21/2025. Entry date 3> day discrepancy. Need charter attendance record to change in ST. | P30: Gen Ed
A31: Southside 291462 | B31: 46174 | C31: southside_291462_unified-roster.xlsx | F31: 0 | G31: Kisean | H31: 0 | J31: Southside Academy Charter School | K31: 46097 | M31: 0.35 | N31: Not in ST System | O31: Not pulling up in ST. Need more student information. NYSSIS ID, Last name,grade,parent info, gender, race, etc. | P31: Gen Ed
A32: Southside 291462 | B32: 46174 | C32: southside_291462_unified-roster.xlsx | D32: 8110682342 | E32: 210006494 | F32: Matthews | G32: LaMonte | H32: 2 | I32: 43322 | J32: Southside Academy Charter School | K32: 45903 | L32: 46079 | M32: 0.6 | N32: No Good | O32: ST states: student enrolled at Southside Academy Charter School 8/25/2025 - 2/18/2026. Enrolled at Van Duyn ES / ES 2/19/26- current Entry date 3> day discrepancy. Need charter attendance record to change in ST. | P32: SPED
A33: Southside 291462 | B33: 46174 | C33: southside_291462_unified-roster.xlsx | D33: 2125386561 | F33: Brynien | G33: Liliana | H33: 4 | I33: 42384 | J33: Southside Academy Charter School | K33: 45964 | M33: 0.8 | N33: No Good | O33: No 25-26 enrollment in ST. Need charter attendance record to make change in ST. | P33: Gen Ed
A34: Southside 291462 | B34: 46174 | C34: southside_291462_unified-roster.xlsx | D34: 5279781642 | E34: 210017699 | F34: James-Haygood | G34: Llmanuel | H34: K | I34: 44110 | J34: Southside Academy Charter School | K34: 45908 | M34: 0.975 | N34: No Good | O34: ST states: Enrolled at Southside Academy Charter School 7/1/25 - 3/3/26. Need charter school attendance record to change in ST. | P34: Gen Ed
A35: Southside 291462 | B35: 46174 | C35: southside_291462_unified-roster.xlsx | D35: 6748943165 | E35: 210016382 | F35: Warde | G35: Malachi | H35: 6 | I35: 41501 | J35: Southside Academy Charter School | K35: 45903 | M35: 1 | N35: No Good | O35: ST states: student enrolled at Grant MS / MS 7/1/25 - 9/15/25. Enrolled at Southside Academy Charter School 9/16/25 - current. Entry date 3> day discrepancy. Need charter attendance record to change in ST. | P35: Gen Ed
A36: Southside 291462 | B36: 46174 | C36: southside_291462_unified-roster.xlsx | D36: 4302512531 | E36: 210002246 | F36: Lobban | G36: Mehki | H36: 5 | I36: 41841 | J36: Southside Academy Charter School | K36: 45904 | L36: 45919 | M36: 0.05 | N36: No Good | O36: ST states: student enrolled at Southside Academy Charter School 7/1/2025 - 9/8/2025. Enrolled at STEAM @ Dr King / ES 9/18/25 - current. Entry date 3> day discrepancy. Need charter attendance record to change in ST. | P36: SPED
A37: Southside 291462 | B37: 46174 | C37: southside_291462_unified-roster.xlsx | D37: 8460982760 | E37: 210022815 | F37: Lindsey | G37: Nadir | H37: K | I37: 44033 | J37: Southside Academy Charter School | K37: 45964 | L37: 46010 | M37: 0.175 | N37: No Good | O37: ST states: Enrolled at Southside Academy Charter School 11/12/25-current. Entry date 3> day discrepancy. Need charter school attendance record to change in ST. | P37: Gen Ed
A38: Southside 291462 | B38: 46174 | C38: southside_291462_unified-roster.xlsx | D38: 2981769541 | E38: 210009975 | F38: Smith | G38: Natalia | H38: 1 | I38: 43468 | J38: Southside Academy Charter School | K38: 45968 | M38: 0.775 | N38: No Good | O38: ST states: student enrolled at Southside Academy Charter School 12/10/2025 - current. Entry date 3> day discrepancy. Need charter attendance record to change in ST. | P38: Gen Ed
A39: Southside 291462 | B39: 46174 | C39: southside_291462_unified-roster.xlsx | D39: 6994835771 | F39: Morris | G39: Rahmier | H39: K | I39: 44148 | J39: Southside Academy Charter School | K39: 45903 | L39: 45923 | M39: 0.075 | N39: No Good | O39: No enrollment record in ST. Need charter school attendance to create enrollment entry in ST. | P39: Gen Ed
A40: Southside 291462 | B40: 46174 | C40: southside_291462_unified-roster.xlsx | D40: 1565701023 | E40: 210022225 | F40: Tarrats | G40: Ruben | H40: 7 | I40: 41464 | J40: Southside Academy Charter School | K40: 45915 | M40: 0.95 | N40: No Good | O40: ST states: student enrolled at Southside Academy Charter School 10/15/2025 - current. Entry date 3> day discrepancy. Need charter attendance record to change in ST. | P40: Gen Ed
A41: Southside 291462 | B41: 46174 | C41: southside_291462_unified-roster.xlsx | D41: 1348451822 | E41: 210022690 | F41: Moore | G41: Samya | H41: 4 | I41: 42401 | J41: Southside Academy Charter School | K41: 45905 | M41: 0.975 | N41: No Good | O41: ST states: Enrolled at Southside Academy Charter School 10/27/25-current. Entry date 3> day discrepancy. Need charter school attendance record to change in ST. | P41: Gen Ed
A42: Southside 291462 | B42: 46174 | C42: southside_291462_unified-roster.xlsx | D42: 6885359396 | F42: Thurman | G42: Xavier | H42: 1 | I42: 43656 | J42: Southside Academy Charter School | K42: 45903 | L42: 45981 | M42: 0.275 | N42: No Good | O42: No charter enrollment for current year 25-26 in ST. Only Projected Enrollment for Southside Academy for 7/1/26. Need charter attendance record to change in ST. | P42: Gen Ed
A43: Southside 291462 | B43: 46174 | C43: southside_291462_unified-roster.xlsx | D43: 9391717043 | E43: 210022224 | F43: Tarrats | G43: Zailashay | H43: 6 | I43: 41897 | J43: Southside Academy Charter School | K43: 45930 | M43: 0.9 | N43: No Good | O43: ST states: student enrolled at Southside Academy Charter School 10/15/2025 - current. Entry date 3> day discrepancy. Need charter attendance record to change in ST. | P43: Gen Ed
A44: Southside 291462 | B44: 46174 | C44: southside_291462_unified-roster.xlsx | D44: 3015231426 | E44: 210023269 | F44: Walker | G44: Zayvian | H44: K | I44: 43861 | J44: Southside Academy Charter School | K44: 45903 | M44: 1 | N44: No Good | O44: ST states: student enrolled at Southside Academy on 4/9/26- current. 3> day discrepancy. Need charter attendance record to change in ST. | P44: Gen Ed
A45: Southside 291462 | B45: 46174 | C45: southside_291462_unified-roster.xlsx | D45: 5714663321 | E45: 200036826 | F45: Parrilla | G45: Aaminah | H45: 6 | I45: 41964 | J45: Southside Academy Charter School | K45: 45903 | M45: 1 | N45: Good | O45: 0 | P45: SPED
A46: Southside 291462 | B46: 46174 | C46: southside_291462_unified-roster.xlsx | D46: 9977865516 | E46: 210018968 | F46: Lynch | G46: Aaron | H46: 1 | I46: 43557 | J46: Southside Academy Charter School | K46: 45915 | M46: 0.95 | N46: Good | O46: 0 | P46: Gen Ed
A47: Southside 291462 | B47: 46174 | C47: southside_291462_unified-roster.xlsx | D47: 4986713632 | E47: 210003070 | F47: Smith | G47: Aaron | H47: 5 | I47: 41842 | J47: Southside Academy Charter School | K47: 45903 | M47: 1 | N47: Good | O47: 0 | P47: Gen Ed
A48: Southside 291462 | B48: 46174 | C48: southside_291462_unified-roster.xlsx | D48: 9323458081 | E48: 210014696 | F48: Anderson | G48: Aayden | H48: 1 | I48: 43550 | J48: Southside Academy Charter School | K48: 45903 | L48: 46085 | M48: 0.625 | N48: Good | O48: 0 | P48: SPED
A49: Southside 291462 | B49: 46174 | C49: southside_291462_unified-roster.xlsx | D49: 1983806742 | E49: 210018426 | F49: Durham | G49: Adam | H49: 1 | I49: 43605 | J49: Southside Academy Charter School | K49: 45903 | M49: 1 | N49: Good | O49: 0 | P49: Gen Ed
A50: Southside 291462 | B50: 46174 | C50: southside_291462_unified-roster.xlsx | D50: 9265754471 | E50: 200031166 | F50: Perdomo | G50: Adelina | H50: 7 | I50: 41281 | J50: Southside Academy Charter School | K50: 45903 | M50: 1 | N50: Good | O50: 0 | P50: Gen Ed
A51: Southside 291462 | B51: 46174 | C51: southside_291462_unified-roster.xlsx | D51: 2349311626 | E51: 200026850 | F51: Mann | G51: Adonis | H51: 8 | I51: 40622 | J51: Southside Academy Charter School | K51: 45903 | M51: 1 | N51: Good | O51: 0 | P51: SPED
A52: Southside 291462 | B52: 46174 | C52: southside_291462_unified-roster.xlsx | D52: 6920438320 | E52: 210005255 | F52: Smith | G52: Adoriannah | H52: 6 | I52: 41864 | J52: Southside Academy Charter School | K52: 45908 | M52: 0.975 | N52: Good | O52: 0 | P52: Gen Ed
A53: Southside 291462 | B53: 46174 | C53: southside_291462_unified-roster.xlsx | D53: 2859324671 | E53: 200030533 | F53: Harris | G53: Adrayla | H53: 8 | I53: 41151 | J53: Southside Academy Charter School | K53: 45903 | M53: 1 | N53: Good | O53: 0 | P53: Gen Ed
A54: Southside 291462 | B54: 46174 | C54: southside_291462_unified-roster.xlsx | D54: 9004836816 | E54: 210007545 | F54: Rowland | G54: Adrianna | H54: 8 | I54: 40934 | J54: Southside Academy Charter School | K54: 45903 | M54: 1 | N54: Good | O54: 0 | P54: Gen Ed
A55: Southside 291462 | B55: 46174 | C55: southside_291462_unified-roster.xlsx | D55: 4798198643 | E55: 210011819 | F55: Davis | G55: A-Drianna | H55: 1 | I55: 43589 | J55: Southside Academy Charter School | K55: 45903 | M55: 1 | N55: Good | O55: 0 | P55: Gen Ed
A56: Southside 291462 | B56: 46174 | C56: southside_291462_unified-roster.xlsx | D56: 5716749290 | E56: 200038876 | F56: Green-Hayward | G56: AdriElla | H56: 6 | I56: 41861 | J56: Southside Academy Charter School | K56: 45903 | M56: 1 | N56: Good | O56: 0 | P56: Gen Ed
A57: Southside 291462 | B57: 46174 | C57: southside_291462_unified-roster.xlsx | D57: 9816245530 | E57: 210016421 | F57: Timori | G57: Ahmad | H57: 5 | I57: 41917 | J57: Southside Academy Charter School | K57: 45903 | M57: 1 | N57: Good | O57: 0 | P57: Gen Ed
A58: Southside 291462 | B58: 46174 | C58: southside_291462_unified-roster.xlsx | D58: 9112250374 | E58: 210004384 | F58: Capers | G58: Aiden | H58: 4 | I58: 42418 | J58: Southside Academy Charter School | K58: 45903 | M58: 1 | N58: Good | O58: 0 | P58: Gen Ed
A59: Southside 291462 | B59: 46174 | C59: southside_291462_unified-roster.xlsx | D59: 5308675136 | E59: 210017359 | F59: Akot | G59: Akot | H59: K | I59: 44049 | J59: Southside Academy Charter School | K59: 45903 | L59: 46052 | M59: 0.5 | N59: Good | O59: 0 | P59: Gen Ed
A60: Southside 291462 | B60: 46174 | C60: southside_291462_unified-roster.xlsx | D60: 6862971750 | E60: 200030599 | F60: Kodet | G60: Alana | H60: 7 | I60: 41500 | J60: Southside Academy Charter School | K60: 45903 | M60: 1 | N60: Good | O60: 0 | P60: Gen Ed
A61: Southside 291462 | B61: 46174 | C61: southside_291462_unified-roster.xlsx | D61: 1012369440 | E61: 210004998 | F61: Salem | G61: Alanna | H61: 4 | I61: 42475 | J61: Southside Academy Charter School | K61: 45903 | M61: 1 | N61: Good | O61: 0 | P61: Gen Ed
A62: Southside 291462 | B62: 46174 | C62: southside_291462_unified-roster.xlsx | D62: 4003684191 | E62: 200038430 | F62: Tillie | G62: Alayiah | H62: 4 | I62: 42281 | J62: Southside Academy Charter School | K62: 45903 | M62: 1 | N62: Good | O62: 0 | P62: SPED
A63: Southside 291462 | B63: 46174 | C63: southside_291462_unified-roster.xlsx | D63: 8037443260 | E63: 210012357 | F63: Allan Jr | G63: Alexander | H63: 3 | I63: 42781 | J63: Southside Academy Charter School | K63: 45918 | M63: 0.925 | N63: Good | O63: 0 | P63: SPED
A64: Southside 291462 | B64: 46174 | C64: southside_291462_unified-roster.xlsx | D64: 1757340380 | E64: 210005851 | F64: May | G64: Alina | H64: 2 | I64: 43109 | J64: Southside Academy Charter School | K64: 45903 | M64: 1 | N64: Good | O64: 0 | P64: SPED
A65: Southside 291462 | B65: 46174 | C65: southside_291462_unified-roster.xlsx | D65: 9247943203 | E65: 200032807 | F65: Aiken | G65: Aliya | H65: 8 | I65: 41174 | J65: Southside Academy Charter School | K65: 45903 | M65: 1 | N65: Good | O65: 0 | P65: Gen Ed
A66: Southside 291462 | B66: 46174 | C66: southside_291462_unified-roster.xlsx | D66: 2018797941 | E66: 200037650 | F66: Blunt | G66: Aliyah | H66: 5 | I66: 42094 | J66: Southside Academy Charter School | K66: 45903 | M66: 1 | N66: Good | O66: 0 | P66: Gen Ed
A67: Southside 291462 | B67: 46174 | C67: southside_291462_unified-roster.xlsx | D67: 7271659280 | E67: 200038218 | F67: Smith | G67: Allanna | H67: 6 | I67: 41726 | J67: Southside Academy Charter School | K67: 45903 | L67: 46059 | M67: 0.525 | N67: Good | O67: 0 | P67: Gen Ed
A68: Southside 291462 | B68: 46174 | C68: southside_291462_unified-roster.xlsx | D68: 200029382 | E68: 200029382 | F68: Colon | G68: Alyani | H68: 8 | I68: 40559 | J68: Southside Academy Charter School | K68: 45903 | M68: 1 | N68: Good | O68: 0 | P68: Gen Ed
A69: Southside 291462 | B69: 46174 | C69: southside_291462_unified-roster.xlsx | D69: 2799458756 | E69: 210004202 | F69: Jacobs | G69: Amara | H69: 3 | I69: 42788 | J69: Southside Academy Charter School | K69: 45909 | M69: 0.975 | N69: Good | O69: 0 | P69: Gen Ed
A70: Southside 291462 | B70: 46174 | C70: southside_291462_unified-roster.xlsx | D70: 3948567923 | E70: 200029630 | F70: Coston | G70: Amare | H70: 6 | I70: 41522 | J70: Southside Academy Charter School | K70: 45903 | M70: 1 | N70: Good | O70: 0 | P70: Gen Ed
A71: Southside 291462 | B71: 46174 | C71: southside_291462_unified-roster.xlsx | D71: 2365285906 | E71: 210004781 | F71: McFadden | G71: Amari | H71: 2 | I71: 43026 | J71: Southside Academy Charter School | K71: 45903 | M71: 1 | N71: Good | O71: 0 | P71: SPED
A72: Southside 291462 | B72: 46174 | C72: southside_291462_unified-roster.xlsx | D72: 5003227753 | E72: 200037678 | F72: Vega Davila | G72: Amarilys | H72: 5 | I72: 41985 | J72: Southside Academy Charter School | K72: 45903 | M72: 1 | N72: Good | O72: 0 | P72: Gen Ed
A73: Southside 291462 | B73: 46174 | C73: southside_291462_unified-roster.xlsx | D73: 1647851873 | E73: 210004236 | F73: Morales | G73: Amaya | H73: 5 | I73: 41740 | J73: Southside Academy Charter School | K73: 45903 | M73: 1 | N73: Good | O73: 0 | P73: Gen Ed
A74: Southside 291462 | B74: 46174 | C74: southside_291462_unified-roster.xlsx | D74: 1635879015 | E74: 210004000 | F74: Ruiz-Mclain | G74: Ameliah | H74: 4 | I74: 42388 | J74: Southside Academy Charter School | K74: 45903 | M74: 1 | N74: Good | O74: 0 | P74: Gen Ed
A75: Southside 291462 | B75: 46174 | C75: southside_291462_unified-roster.xlsx | D75: 2567760593 | E75: 200030543 | F75: Chandler | G75: Amerie | H75: 7 | I75: 41095 | J75: Southside Academy Charter School | K75: 45903 | M75: 1 | N75: Good | O75: 0 | P75: Gen Ed
A76: Southside 291462 | B76: 46174 | C76: southside_291462_unified-roster.xlsx | D76: 8535798744 | E76: 210017318 | F76: Clifton | G76: Amias | H76: K | I76: 43817 | J76: Southside Academy Charter School | K76: 45903 | M76: 1 | N76: Good | O76: 0 | P76: Gen Ed
A77: Southside 291462 | B77: 46174 | C77: southside_291462_unified-roster.xlsx | D77: 6124086535 | E77: 210007964 | F77: Cirino | G77: Amir | H77: 3 | I77: 42940 | J77: Southside Academy Charter School | K77: 45904 | M77: 0.975 | N77: Good | O77: 0 | P77: Gen Ed
A78: Southside 291462 | B78: 46174 | C78: southside_291462_unified-roster.xlsx | D78: 2741058673 | E78: 210011629 | F78: Johnson | G78: Amir | H78: 2 | I78: 43132 | J78: Southside Academy Charter School | K78: 45904 | M78: 0.975 | N78: Good | O78: 0 | P78: Gen Ed
A79: Southside 291462 | B79: 46174 | C79: southside_291462_unified-roster.xlsx | D79: 3898545173 | E79: 200037239 | F79: Aiken | G79: Amira | H79: 6 | I79: 41632 | J79: Southside Academy Charter School | K79: 45903 | M79: 1 | N79: Good | O79: 0 | P79: Gen Ed
... A95: Southside 291462 | B95: 46174 | C95: southside_291462_unified-roster.xlsx | D95: 8775651313 | E95: 210013145 | F95: Stroman | G95: Anthony | H95: 3 | I95: 42916 | J95: Southside Academy Charter School | K95: 45903 | M95: 1 | N95: Good | O95: 0 | P95: Gen Ed
A96: Southside 291462 | B96: 46174 | C96: southside_291462_unified-roster.xlsx | D96: 9394640522 | E96: 210010093 | F96: Davis-El | G96: Anubis | H96: 2 | I96: 43011 | J96: Southside Academy Charter School | K96: 45903 | L96: 45940 | M96: 0.15 | N96: Good | O96: 0 | P96: Gen Ed
A97: Southside 291462 | B97: 46174 | C97: southside_291462_unified-roster.xlsx | D97: 9394640522 | E97: 210010093 | F97: Davis-El | G97: Anubis | H97: 2 | I97: 43011 | J97: Southside Academy Charter School | K97: 46042 | M97: 0.55 | N97: Good | O97: 0 | P97: Gen Ed
A98: Southside 291462 | B98: 46174 | C98: southside_291462_unified-roster.xlsx | D98: 7329456485 | E98: 210008329 | F98: Billingsley | G98: Anyia | H98: 2 | I98: 43389 | J98: Southside Academy Charter School | K98: 45903 | M98: 1 | N98: Good | O98: 0 | P98: Gen Ed
A99: Southside 291462 | B99: 46174 | C99: southside_291462_unified-roster.xlsx | D99: 3550907634 | E99: 210011269 | F99: Titus | G99: Anyla | H99: 2 | I99: 43453 | J99: Southside Academy Charter School | K99: 45903 | M99: 1 | N99: Good | O99: 0 | P99: Gen Ed
A100: Southside 291462 | B100: 46174 | C100: southside_291462_unified-roster.xlsx | D100: 1580562481 | E100: 210014023 | F100: Works | G100: ARayvia | H100: 2 | I100: 43126 | J100: Southside Academy Charter School | K100: 45904 | M100: 0.975 | N100: Good | O100: 0 | P100: Gen Ed
A101: Southside 291462 | B101: 46174 | C101: southside_291462_unified-roster.xlsx | D101: 8769895202 | E101: 200029205 | F101: Luter | G101: Aria | H101: 7 | I101: 41324 | J101: Southside Academy Charter School | K101: 45903 | M101: 1 | N101: Good | O101: 0 | P101: Gen Ed
A102: Southside 291462 | B102: 46174 | C102: southside_291462_unified-roster.xlsx | D102: 5516246433 | E102: 210007891 | F102: Colon | G102: Ariel | H102: 3 | I102: 42835 | J102: Southside Academy Charter School | K102: 45903 | M102: 1 | N102: Good | O102: 0 | P102: Gen Ed
A103: Southside 291462 | B103: 46174 | C103: southside_291462_unified-roster.xlsx | D103: 6887336141 | E103: 210007601 | F103: Price | G103: Ariel | H103: 2 | I103: 42947 | J103: Southside Academy Charter School | K103: 45903 | M103: 1 | N103: Good | O103: 0 | P103: Gen Ed
A104: Southside 291462 | B104: 46174 | C104: southside_291462_unified-roster.xlsx | D104: 4006453581 | E104: 210009775 | F104: Flowers | G104: Aries | H104: 3 | I104: 42816 | J104: Southside Academy Charter School | K104: 45915 | M104: 0.95 | N104: Good | O104: 0 | P104: Gen Ed
A105: Southside 291462 | B105: 46174 | C105: southside_291462_unified-roster.xlsx | D105: 1781894942 | E105: 200038707 | F105: Williams | G105: Ariya | H105: 5 | I105: 42329 | J105: Southside Academy Charter School | K105: 45903 | M105: 1 | N105: Good | O105: 0 | P105: Gen Ed
A106: Southside 291462 | B106: 46174 | C106: southside_291462_unified-roster.xlsx | D106: 4699043762 | E106: 210007108 | F106: Cirino | G106: Armani | H106: 4 | I106: 42559 | J106: Southside Academy Charter School | K106: 45904 | M106: 0.975 | N106: Good | O106: 0 | P106: Gen Ed
A107: Southside 291462 | B107: 46174 | C107: southside_291462_unified-roster.xlsx | D107: 5975014716 | E107: 210013616 | F107: Murray | G107: Armarni | H107: K | I107: 43945 | J107: Southside Academy Charter School | K107: 45903 | M107: 1 | N107: Good | O107: 0 | P107: Gen Ed
A108: Southside 291462 | B108: 46174 | C108: southside_291462_unified-roster.xlsx | D108: 1761288976 | E108: 210005225 | F108: Colon | G108: Armauni | H108: 2 | I108: 43161 | J108: Southside Academy Charter School | K108: 45903 | M108: 1 | N108: Good | O108: 0 | P108: SPED
... A158: Southside 291462 | B158: 46174 | C158: southside_291462_unified-roster.xlsx | D158: 7690309653 | E158: 200037763 | F158: Donai | G158: Daniel | H158: 8 | I158: 41007 | J158: Southside Academy Charter School | K158: 45903 | M158: 1 | N158: Good | O158: 0 | P158: Gen Ed
A159: Southside 291462 | B159: 46174 | C159: southside_291462_unified-roster.xlsx | D159: 6229109670 | E159: 210021510 | F159: Rivera Filomeno | G159: Dariel | H159: 7 | I159: 41116 | J159: Southside Academy Charter School | K159: 45904 | L159: 45957 | M159: 0.2 | N159: Good | O159: 0 | P159: SPED
A160: Southside 291462 | B160: 46174 | C160: southside_291462_unified-roster.xlsx | D160: 200032748 | E160: 200032748 | F160: Rucker | G160: Daryaun | H160: 5 | I160: 41999 | J160: Southside Academy Charter School | K160: 45915 | M160: 0.95 | N160: Good | O160: 0 | P160: Gen Ed
A161: Southside 291462 | B161: 46174 | C161: southside_291462_unified-roster.xlsx | D161: 6015998781 | E161: 210002243 | F161: St. Louis | G161: Davion | H161: 5 | I161: 42073 | J161: Southside Academy Charter School | K161: 45903 | M161: 1 | N161: Good | O161: 0 | P161: Gen Ed
A162: Southside 291462 | B162: 46174 | C162: southside_291462_unified-roster.xlsx | D162: 8655911084 | E162: 200030088 | F162: Knight | G162: DaVore | H162: 7 | I162: 41481 | J162: Southside Academy Charter School | K162: 45903 | L162: 46066 | M162: 0.55 | N162: Good | O162: 0 | P162: Gen Ed
A163: Southside 291462 | B163: 46174 | C163: southside_291462_unified-roster.xlsx | D163: 5594297206 | E163: 200039236 | F163: Harper | G163: Dawuan | H163: 4 | I163: 42607 | J163: Southside Academy Charter School | K163: 45903 | M163: 1 | N163: Good | O163: 0 | P163: SPED
A164: Southside 291462 | B164: 46174 | C164: southside_291462_unified-roster.xlsx | D164: 7290173314 | E164: 210011342 | F164: Smiley Delee | G164: Deanni | H164: 2 | I164: 42715 | J164: Southside Academy Charter School | K164: 45904 | M164: 0.975 | N164: Good | O164: 0 | P164: Gen Ed
...

Sheet Formula Version
A1: Charter_Source Ticket # | B1: Charter Month | C1: Source_File | D1: NYSSIS ID | E1: Student ID | F1: Last Name | G1: First Name | H1: Grade Level | I1: DOB | J1: School Name | K1: Enroll Date | L1: Withdraw Date | M1: SCSD FTE | N1: Student Status | O1: Notes for Patrick | P1: SPED_Flag | Q1: ST_NYSSIS_Lookup | R1: ST_School_Lookup | S1: ST_SID_Lookup | T1: Match_Source | U1: SPED_Disability_Lookup
A2: Southside 291462 | B2: 46174 | C2: southside_291462_unified-roster.xlsx | D2: 1630725543 | E2: 210010695 | F2: Thomas | G2: Aaleiyah | H2: 2 | I2: 43094 | J2: Southside Academy Charter School | K2: 45904 | M2: 1 | N2: No Good | O2: ST states: student enrolled at Southside Academy Charter School 8/2/255 - 9/1/25 . Entry date is 3> discrepancy. Need charter attendance record to change in ST. | P2: Gen Ed | Q2: =IFERROR(INDEX('ST Enroll Export'!$A$2:$A$3230,MATCH($D2,'ST Enroll Export'!$A$2:$A$3230,0)),IFERROR(IF(INDEX('ST Enroll Export'!$A$2:$A$3230,MATCH($E2,'ST Enroll Export'!$B$2:$B$3230,0))="","",INDEX('ST Enroll Export'!$A$2:$A$3230,MATCH($E2,'ST Enroll Export'!$B$2:$B$3230,0))),"Not Found")) -> 1630725543 | R2: =IFERROR(INDEX('ST Enroll Export'!$G$2:$G$3230,MATCH($D2,'ST Enroll Export'!$A$2:$A$3230,0)),IFERROR(INDEX('ST Enroll Export'!$G$2:$G$3230,MATCH($E2,'ST Enroll Export'!$B$2:$B$3230,0)),"Not Found")) -> Southside Academy Charter School | S2: =IFERROR(INDEX('ST Enroll Export'!$B$2:$B$3230,MATCH($D2,'ST Enroll Export'!$A$2:$A$3230,0)),IFERROR(INDEX('ST Enroll Export'!$B$2:$B$3230,MATCH($E2,'ST Enroll Export'!$B$2:$B$3230,0)),"Not Found")) -> 210010695 | T2: =IF(ISNUMBER(MATCH($D2,'ST Enroll Export'!$A$2:$A$3230,0)),"NYSSIS Match",IF(ISNUMBER(MATCH($E2,'ST Enroll Export'!$B$2:$B$3230,0)),"SID Match","No ST Match")) -> NYSSIS Match | U2: =IF(ISNUMBER(MATCH($D2,Disability!$B$2:$B$5962,0)),"SPED","Gen Ed") -> Gen Ed
A3: Southside 291462 | B3: 46174 | C3: southside_291462_unified-roster.xlsx | D3: 7417895120 | E3: 210022348 | F3: East | G3: Abel | H3: K | I3: 43993 | J3: Southside Academy Charter School | K3: 45903 | L3: 45940 | M3: 0.15 | N3: No Good | O3: ST states: student started Southside Academy Charter School 9/3/25 . Entry date is 3> discrepancy. Need charter attendance record to change in ST. | P3: Gen Ed | Q3: =IFERROR(INDEX('ST Enroll Export'!$A$2:$A$3230,MATCH($D3,'ST Enroll Export'!$A$2:$A$3230,0)),IFERROR(IF(INDEX('ST Enroll Export'!$A$2:$A$3230,MATCH($E3,'ST Enroll Export'!$B$2:$B$3230,0))="","",INDEX('ST Enroll Export'!$A$2:$A$3230,MATCH($E3,'ST Enroll Export'!$B$2:$B$3230,0))),"Not Found")) | R3: =IFERROR(INDEX('ST Enroll Export'!$G$2:$G$3230,MATCH($D3,'ST Enroll Export'!$A$2:$A$3230,0)),IFERROR(INDEX('ST Enroll Export'!$G$2:$G$3230,MATCH($E3,'ST Enroll Export'!$B$2:$B$3230,0)),"Not Found")) -> Southside Academy Charter School | S3: =IFERROR(INDEX('ST Enroll Export'!$B$2:$B$3230,MATCH($D3,'ST Enroll Export'!$A$2:$A$3230,0)),IFERROR(INDEX('ST Enroll Export'!$B$2:$B$3230,MATCH($E3,'ST Enroll Export'!$B$2:$B$3230,0)),"Not Found")) -> 210022348 | T3: =IF(ISNUMBER(MATCH($D3,'ST Enroll Export'!$A$2:$A$3230,0)),"NYSSIS Match",IF(ISNUMBER(MATCH($E3,'ST Enroll Export'!$B$2:$B$3230,0)),"SID Match","No ST Match")) -> SID Match | U3: =IF(ISNUMBER(MATCH($D3,Disability!$B$2:$B$5962,0)),"SPED","Gen Ed") -> Gen Ed
A4: Southside 291462 | B4: 46174 | C4: southside_291462_unified-roster.xlsx | D4: 6114934235 | E4: 200036757 | F4: Smith | G4: Adorre | H4: 4 | I4: 42225 | J4: Southside Academy Charter School | K4: 45904 | M4: 0.975 | N4: No Good | O4: ST states: student started McKiunley Brighton ES 4/8/26-current. Need charter attendance record to change in ST. | P4: SPED | Q4: =IFERROR(INDEX('ST Enroll Export'!$A$2:$A$3230,MATCH($D4,'ST Enroll Export'!$A$2:$A$3230,0)),IFERROR(IF(INDEX('ST Enroll Export'!$A$2:$A$3230,MATCH($E4,'ST Enroll Export'!$B$2:$B$3230,0))="","",INDEX('ST Enroll Export'!$A$2:$A$3230,MATCH($E4,'ST Enroll Export'!$B$2:$B$3230,0))),"Not Found")) -> 6114934235 | R4: =IFERROR(INDEX('ST Enroll Export'!$G$2:$G$3230,MATCH($D4,'ST Enroll Export'!$A$2:$A$3230,0)),IFERROR(INDEX('ST Enroll Export'!$G$2:$G$3230,MATCH($E4,'ST Enroll Export'!$B$2:$B$3230,0)),"Not Found")) -> Southside Academy Charter School | S4: =IFERROR(INDEX('ST Enroll Export'!$B$2:$B$3230,MATCH($D4,'ST Enroll Export'!$A$2:$A$3230,0)),IFERROR(INDEX('ST Enroll Export'!$B$2:$B$3230,MATCH($E4,'ST Enroll Export'!$B$2:$B$3230,0)),"Not Found")) -> 200036757 | T4: =IF(ISNUMBER(MATCH($D4,'ST Enroll Export'!$A$2:$A$3230,0)),"NYSSIS Match",IF(ISNUMBER(MATCH($E4,'ST Enroll Export'!$B$2:$B$3230,0)),"SID Match","No ST Match")) -> NYSSIS Match | U4: =IF(ISNUMBER(MATCH($D4,Disability!$B$2:$B$5962,0)),"SPED","Gen Ed") -> SPED
A5: Southside 291462 | B5: 46174 | C5: southside_291462_unified-roster.xlsx | D5: 8894205962 | E5: 200032672 | F5: Maloof | G5: Aiden | H5: 8 | I5: 41220 | J5: Southside Academy Charter School | K5: 45903 | L5: 46077 | M5: 0.575 | N5: No Good | O5: ST states: Enrolled at Southside Academy 7/1/25-2/9/26. Enrolled at Lincoln MS 2/10/26-current. Exit date 3> discrepancy. Need charter attendance record to change in ST. | P5: Gen Ed | Q5: =IFERROR(INDEX('ST Enroll Export'!$A$2:$A$3230,MATCH($D5,'ST Enroll Export'!$A$2:$A$3230,0)),IFERROR(IF(INDEX('ST Enroll Export'!$A$2:$A$3230,MATCH($E5,'ST Enroll Export'!$B$2:$B$3230,0))="","",INDEX('ST Enroll Export'!$A$2:$A$3230,MATCH($E5,'ST Enroll Export'!$B$2:$B$3230,0))),"Not Found")) -> 8894205962 | R5: =IFERROR(INDEX('ST Enroll Export'!$G$2:$G$3230,MATCH($D5,'ST Enroll Export'!$A$2:$A$3230,0)),IFERROR(INDEX('ST Enroll Export'!$G$2:$G$3230,MATCH($E5,'ST Enroll Export'!$B$2:$B$3230,0)),"Not Found")) -> Southside Academy Charter School | S5: =IFERROR(INDEX('ST Enroll Export'!$B$2:$B$3230,MATCH($D5,'ST Enroll Export'!$A$2:$A$3230,0)),IFERROR(INDEX('ST Enroll Export'!$B$2:$B$3230,MATCH($E5,'ST Enroll Export'!$B$2:$B$3230,0)),"Not Found")) -> 200032672 | T5: =IF(ISNUMBER(MATCH($D5,'ST Enroll Export'!$A$2:$A$3230,0)),"NYSSIS Match",IF(ISNUMBER(MATCH($E5,'ST Enroll Export'!$B$2:$B$3230,0)),"SID Match","No ST Match")) -> NYSSIS Match | U5: =IF(ISNUMBER(MATCH($D5,Disability!$B$2:$B$5962,0)),"SPED","Gen Ed") -> SPED
A6: Southside 291462 | B6: 46174 | C6: southside_291462_unified-roster.xlsx | D6: 9715356981 | E6: 210019407 | F6: McClain | G6: Ali | H6: K | I6: 44190 | J6: Southside Academy Charter School | K6: 45904 | M6: 0.975 | N6: No Good | O6: ST states: student enrolled at Southside Academy Charter 1/15/26-current. Entry date is 3> day discrepancy. Need charter attendance record to change in ST. | P6: Gen Ed | Q6: =IFERROR(INDEX('ST Enroll Export'!$A$2:$A$3230,MATCH($D6,'ST Enroll Export'!$A$2:$A$3230,0)),IFERROR(IF(INDEX('ST Enroll Export'!$A$2:$A$3230,MATCH($E6,'ST Enroll Export'!$B$2:$B$3230,0))="","",INDEX('ST Enroll Export'!$A$2:$A$3230,MATCH($E6,'ST Enroll Export'!$B$2:$B$3230,0))),"Not Found")) -> 9715356981 | R6: =IFERROR(INDEX('ST Enroll Export'!$G$2:$G$3230,MATCH($D6,'ST Enroll Export'!$A$2:$A$3230,0)),IFERROR(INDEX('ST Enroll Export'!$G$2:$G$3230,MATCH($E6,'ST Enroll Export'!$B$2:$B$3230,0)),"Not Found")) -> Southside Academy Charter School | S6: =IFERROR(INDEX('ST Enroll Export'!$B$2:$B$3230,MATCH($D6,'ST Enroll Export'!$A$2:$A$3230,0)),IFERROR(INDEX('ST Enroll Export'!$B$2:$B$3230,MATCH($E6,'ST Enroll Export'!$B$2:$B$3230,0)),"Not Found")) -> 210019407 | T6: =IF(ISNUMBER(MATCH($D6,'ST Enroll Export'!$A$2:$A$3230,0)),"NYSSIS Match",IF(ISNUMBER(MATCH($E6,'ST Enroll Export'!$B$2:$B$3230,0)),"SID Match","No ST Match")) -> NYSSIS Match | U6: =IF(ISNUMBER(MATCH($D6,Disability!$B$2:$B$5962,0)),"SPED","Gen Ed") -> Gen Ed
A7: Southside 291462 | B7: 46174 | C7: southside_291462_unified-roster.xlsx | D7: 7916282794 | E7: 210003054 | F7: Rufus | G7: Amir | H7: 4 | I7: 42677 | J7: Southside Academy Charter School | K7: 45909 | M7: 0.975 | N7: No Good | O7: ST states: student enrolled at Southside Academny 9/29/25. Entry date 3> day discrepancy. Need charter attendance record to change in ST. | P7: Gen Ed | Q7: =IFERROR(INDEX('ST Enroll Export'!$A$2:$A$3230,MATCH($D7,'ST Enroll Export'!$A$2:$A$3230,0)),IFERROR(IF(INDEX('ST Enroll Export'!$A$2:$A$3230,MATCH($E7,'ST Enroll Export'!$B$2:$B$3230,0))="","",INDEX('ST Enroll Export'!$A$2:$A$3230,MATCH($E7,'ST Enroll Export'!$B$2:$B$3230,0))),"Not Found")) -> 7916282794 | R7: =IFERROR(INDEX('ST Enroll Export'!$G$2:$G$3230,MATCH($D7,'ST Enroll Export'!$A$2:$A$3230,0)),IFERROR(INDEX('ST Enroll Export'!$G$2:$G$3230,MATCH($E7,'ST Enroll Export'!$B$2:$B$3230,0)),"Not Found")) -> Southside Academy Charter School | S7: =IFERROR(INDEX('ST Enroll Export'!$B$2:$B$3230,MATCH($D7,'ST Enroll Export'!$A$2:$A$3230,0)),IFERROR(INDEX('ST Enroll Export'!$B$2:$B$3230,MATCH($E7,'ST Enroll Export'!$B$2:$B$3230,0)),"Not Found")) -> 210003054 | T7: =IF(ISNUMBER(MATCH($D7,'ST Enroll Export'!$A$2:$A$3230,0)),"NYSSIS Match",IF(ISNUMBER(MATCH($E7,'ST Enroll Export'!$B$2:$B$3230,0)),"SID Match","No ST Match")) -> NYSSIS Match | U7: =IF(ISNUMBER(MATCH($D7,Disability!$B$2:$B$5962,0)),"SPED","Gen Ed") -> Gen Ed
A8: Southside 291462 | B8: 46174 | C8: southside_291462_unified-roster.xlsx | D8: 5016968523 | F8: Felder | G8: Anessa | H8: 1 | I8: 43675 | J8: Southside Academy Charter School | K8: 45904 | L8: 45917 | M8: 0.05 | N8: No Good | O8: ST states: No charter 25-26 enrollment in ST.Bellevue ES / ES enrollment 7/1/25 - 9/15/25. Enrolled at Van Duyn ES Van Duyn ES / ES - current. Need charter school attendance record to change in ST. | P8: Gen Ed | Q8: =IFERROR(INDEX('ST Enroll Export'!$A$2:$A$3230,MATCH($D8,'ST Enroll Export'!$A$2:$A$3230,0)),IFERROR(IF(INDEX('ST Enroll Export'!$A$2:$A$3230,MATCH($E8,'ST Enroll Export'!$B$2:$B$3230,0))="","",INDEX('ST Enroll Export'!$A$2:$A$3230,MATCH($E8,'ST Enroll Export'!$B$2:$B$3230,0))),"Not Found")) -> Not Found | R8: =IFERROR(INDEX('ST Enroll Export'!$G$2:$G$3230,MATCH($D8,'ST Enroll Export'!$A$2:$A$3230,0)),IFERROR(INDEX('ST Enroll Export'!$G$2:$G$3230,MATCH($E8,'ST Enroll Export'!$B$2:$B$3230,0)),"Not Found")) -> Not Found | S8: =IFERROR(INDEX('ST Enroll Export'!$B$2:$B$3230,MATCH($D8,'ST Enroll Export'!$A$2:$A$3230,0)),IFERROR(INDEX('ST Enroll Export'!$B$2:$B$3230,MATCH($E8,'ST Enroll Export'!$B$2:$B$3230,0)),"Not Found")) -> Not Found | T8: =IF(ISNUMBER(MATCH($D8,'ST Enroll Export'!$A$2:$A$3230,0)),"NYSSIS Match",IF(ISNUMBER(MATCH($E8,'ST Enroll Export'!$B$2:$B$3230,0)),"SID Match","No ST Match")) -> No ST Match | U8: =IF(ISNUMBER(MATCH($D8,Disability!$B$2:$B$5962,0)),"SPED","Gen Ed") -> Gen Ed
A9: Southside 291462 | B9: 46174 | C9: southside_291462_unified-roster.xlsx | D9: 1567036743 | E9: 210022223 | F9: Tindley | G9: Annalisse | H9: 2 | I9: 43334 | J9: Southside Academy Charter School | K9: 45915 | M9: 0.95 | N9: No Good | O9: ST states: student enrolled at Southside Academny 9/26/25. Entry date 3> day discrepancy. Need charter attendance record to change in ST. | P9: Gen Ed | Q9: =IFERROR(INDEX('ST Enroll Export'!$A$2:$A$3230,MATCH($D9,'ST Enroll Export'!$A$2:$A$3230,0)),IFERROR(IF(INDEX('ST Enroll Export'!$A$2:$A$3230,MATCH($E9,'ST Enroll Export'!$B$2:$B$3230,0))="","",INDEX('ST Enroll Export'!$A$2:$A$3230,MATCH($E9,'ST Enroll Export'!$B$2:$B$3230,0))),"Not Found")) -> 1567036743 | R9: =IFERROR(INDEX('ST Enroll Export'!$G$2:$G$3230,MATCH($D9,'ST Enroll Export'!$A$2:$A$3230,0)),IFERROR(INDEX('ST Enroll Export'!$G$2:$G$3230,MATCH($E9,'ST Enroll Export'!$B$2:$B$3230,0)),"Not Found")) -> Southside Academy Charter School | S9: =IFERROR(INDEX('ST Enroll Export'!$B$2:$B$3230,MATCH($D9,'ST Enroll Export'!$A$2:$A$3230,0)),IFERROR(INDEX('ST Enroll Export'!$B$2:$B$3230,MATCH($E9,'ST Enroll Export'!$B$2:$B$3230,0)),"Not Found")) -> 210022223 | T9: =IF(ISNUMBER(MATCH($D9,'ST Enroll Export'!$A$2:$A$3230,0)),"NYSSIS Match",IF(ISNUMBER(MATCH($E9,'ST Enroll Export'!$B$2:$B$3230,0)),"SID Match","No ST Match")) -> NYSSIS Match | U9: =IF(ISNUMBER(MATCH($D9,Disability!$B$2:$B$5962,0)),"SPED","Gen Ed") -> Gen Ed
A10: Southside 291462 | B10: 46174 | C10: southside_291462_unified-roster.xlsx | D10: 9622581930 | E10: 210014483 | F10: Dennis | G10: Arhianna | H10: 1 | I10: 43699 | J10: Southside Academy Charter School | K10: 45904 | L10: 45994 | M10: 0.3 | N10: No Good | O10: ST states: student enrolled at Southside Academy Charter School 8/16/25.25 11/25/25. Enrolled at HW Smith PK-8 12/1/25 - current. Entry date 3> day discrepancy. Need charter attendance record to change in ST. | P10: Gen Ed | Q10: =IFERROR(INDEX('ST Enroll Export'!$A$2:$A$3230,MATCH($D10,'ST Enroll Export'!$A$2:$A$3230,0)),IFERROR(IF(INDEX('ST Enroll Export'!$A$2:$A$3230,MATCH($E10,'ST Enroll Export'!$B$2:$B$3230,0))="","",INDEX('ST Enroll Export'!$A$2:$A$3230,MATCH($E10,'ST Enroll Export'!$B$2:$B$3230,0))),"Not Found")) -> 9622581930 | R10: =IFERROR(INDEX('ST Enroll Export'!$G$2:$G$3230,MATCH($D10,'ST Enroll Export'!$A$2:$A$3230,0)),IFERROR(INDEX('ST Enroll Export'!$G$2:$G$3230,MATCH($E10,'ST Enroll Export'!$B$2:$B$3230,0)),"Not Found")) -> Southside Academy Charter School | S10: =IFERROR(INDEX('ST Enroll Export'!$B$2:$B$3230,MATCH($D10,'ST Enroll Export'!$A$2:$A$3230,0)),IFERROR(INDEX('ST Enroll Export'!$B$2:$B$3230,MATCH($E10,'ST Enroll Export'!$B$2:$B$3230,0)),"Not Found")) -> 210014483 | T10: =IF(ISNUMBER(MATCH($D10,'ST Enroll Export'!$A$2:$A$3230,0)),"NYSSIS Match",IF(ISNUMBER(MATCH($E10,'ST Enroll Export'!$B$2:$B$3230,0)),"SID Match","No ST Match")) -> NYSSIS Match | U10: =IF(ISNUMBER(MATCH($D10,Disability!$B$2:$B$5962,0)),"SPED","Gen Ed") -> Gen Ed
A11: Southside 291462 | B11: 46174 | C11: southside_291462_unified-roster.xlsx | D11: 8381796603 | F11: Loper | G11: Bobby | H11: K | I11: 44194 | J11: Southside Academy Charter School | K11: 45903 | M11: 1 | N11: No Good | O11: ST states:No 25-26 charter shool enrollment entry in ST student enrolled at Bellevue ES 7/1/25-9/10/25. | P11: Gen Ed | Q11: =IFERROR(INDEX('ST Enroll Export'!$A$2:$A$3230,MATCH($D11,'ST Enroll Export'!$A$2:$A$3230,0)),IFERROR(IF(INDEX('ST Enroll Export'!$A$2:$A$3230,MATCH($E11,'ST Enroll Export'!$B$2:$B$3230,0))="","",INDEX('ST Enroll Export'!$A$2:$A$3230,MATCH($E11,'ST Enroll Export'!$B$2:$B$3230,0))),"Not Found")) -> Not Found | R11: =IFERROR(INDEX('ST Enroll Export'!$G$2:$G$3230,MATCH($D11,'ST Enroll Export'!$A$2:$A$3230,0)),IFERROR(INDEX('ST Enroll Export'!$G$2:$G$3230,MATCH($E11,'ST Enroll Export'!$B$2:$B$3230,0)),"Not Found")) -> Not Found | S11: =IFERROR(INDEX('ST Enroll Export'!$B$2:$B$3230,MATCH($D11,'ST Enroll Export'!$A$2:$A$3230,0)),IFERROR(INDEX('ST Enroll Export'!$B$2:$B$3230,MATCH($E11,'ST Enroll Export'!$B$2:$B$3230,0)),"Not Found")) -> Not Found | T11: =IF(ISNUMBER(MATCH($D11,'ST Enroll Export'!$A$2:$A$3230,0)),"NYSSIS Match",IF(ISNUMBER(MATCH($E11,'ST Enroll Export'!$B$2:$B$3230,0)),"SID Match","No ST Match")) -> No ST Match | U11: =IF(ISNUMBER(MATCH($D11,Disability!$B$2:$B$5962,0)),"SPED","Gen Ed") -> Gen Ed
A12: Southside 291462 | B12: 46174 | C12: southside_291462_unified-roster.xlsx | D12: 8993227873 | E12: 210019759 | F12: Reome | G12: Caylyn | H12: 1 | I12: 43543 | J12: Southside Academy Charter School | K12: 45903 | L12: 45915 | M12: 0.05 | N12: No Good | O12: ST states: student enrolled at Southside Academy 7/1/25 - 9/11/25. Exit date 3> day discrepancy. Need charter attendance record to change in ST. Enrolled at Syracuse Academy of Science Elementary at St James 9/12/25 | P12: Gen Ed | Q12: =IFERROR(INDEX('ST Enroll Export'!$A$2:$A$3230,MATCH($D12,'ST Enroll Export'!$A$2:$A$3230,0)),IFERROR(IF(INDEX('ST Enroll Export'!$A$2:$A$3230,MATCH($E12,'ST Enroll Export'!$B$2:$B$3230,0))="","",INDEX('ST Enroll Export'!$A$2:$A$3230,MATCH($E12,'ST Enroll Export'!$B$2:$B$3230,0))),"Not Found")) -> 8993227873 | R12: =IFERROR(INDEX('ST Enroll Export'!$G$2:$G$3230,MATCH($D12,'ST Enroll Export'!$A$2:$A$3230,0)),IFERROR(INDEX('ST Enroll Export'!$G$2:$G$3230,MATCH($E12,'ST Enroll Export'!$B$2:$B$3230,0)),"Not Found")) -> Southside Academy Charter School | S12: =IFERROR(INDEX('ST Enroll Export'!$B$2:$B$3230,MATCH($D12,'ST Enroll Export'!$A$2:$A$3230,0)),IFERROR(INDEX('ST Enroll Export'!$B$2:$B$3230,MATCH($E12,'ST Enroll Export'!$B$2:$B$3230,0)),"Not Found")) -> 210019759 | T12: =IF(ISNUMBER(MATCH($D12,'ST Enroll Export'!$A$2:$A$3230,0)),"NYSSIS Match",IF(ISNUMBER(MATCH($E12,'ST Enroll Export'!$B$2:$B$3230,0)),"SID Match","No ST Match")) -> NYSSIS Match | U12: =IF(ISNUMBER(MATCH($D12,Disability!$B$2:$B$5962,0)),"SPED","Gen Ed") -> Gen Ed
A13: Southside 291462 | B13: 46174 | C13: southside_291462_unified-roster.xlsx | D13: 5531469482 | E13: 210003314 | F13: Reome Jr. | G13: Christopher | H13: 3 | I13: 42876 | J13: Southside Academy Charter School | K13: 45903 | L13: 45915 | M13: 0.05 | N13: No Good | O13: ST states: student enrolled at Southside Academy 7/1/25 - 9/11/25. Exit date 3> day discrepancy. Need charter attendance record to change in ST. Enrolled at Syracuse Academy of Science Elementary at St James 9/12/25 | P13: Gen Ed | Q13: =IFERROR(INDEX('ST Enroll Export'!$A$2:$A$3230,MATCH($D13,'ST Enroll Export'!$A$2:$A$3230,0)),IFERROR(IF(INDEX('ST Enroll Export'!$A$2:$A$3230,MATCH($E13,'ST Enroll Export'!$B$2:$B$3230,0))="","",INDEX('ST Enroll Export'!$A$2:$A$3230,MATCH($E13,'ST Enroll Export'!$B$2:$B$3230,0))),"Not Found")) -> 5531469482 | R13: =IFERROR(INDEX('ST Enroll Export'!$G$2:$G$3230,MATCH($D13,'ST Enroll Export'!$A$2:$A$3230,0)),IFERROR(INDEX('ST Enroll Export'!$G$2:$G$3230,MATCH($E13,'ST Enroll Export'!$B$2:$B$3230,0)),"Not Found")) -> Southside Academy Charter School | S13: =IFERROR(INDEX('ST Enroll Export'!$B$2:$B$3230,MATCH($D13,'ST Enroll Export'!$A$2:$A$3230,0)),IFERROR(INDEX('ST Enroll Export'!$B$2:$B$3230,MATCH($E13,'ST Enroll Export'!$B$2:$B$3230,0)),"Not Found")) -> 210003314 | T13: =IF(ISNUMBER(MATCH($D13,'ST Enroll Export'!$A$2:$A$3230,0)),"NYSSIS Match",IF(ISNUMBER(MATCH($E13,'ST Enroll Export'!$B$2:$B$3230,0)),"SID Match","No ST Match")) -> NYSSIS Match | U13: =IF(ISNUMBER(MATCH($D13,Disability!$B$2:$B$5962,0)),"SPED","Gen Ed") -> Gen Ed
A14: Southside 291462 | B14: 46174 | C14: southside_291462_unified-roster.xlsx | D14: 7205350121 | E14: 210018482 | F14: Davis | G14: Cyh'Mora | H14: 1 | I14: 43826 | J14: Southside Academy Charter School | K14: 45903 | M14: 1 | N14: No Good | O14: ST states: student enrolled at Southside Academy Charter School9/25/25 - current. Entry date 3> day discrepancy. Need charter attendance record to change in ST. | P14: Gen Ed | Q14: =IFERROR(INDEX('ST Enroll Export'!$A$2:$A$3230,MATCH($D14,'ST Enroll Export'!$A$2:$A$3230,0)),IFERROR(IF(INDEX('ST Enroll Export'!$A$2:$A$3230,MATCH($E14,'ST Enroll Export'!$B$2:$B$3230,0))="","",INDEX('ST Enroll Export'!$A$2:$A$3230,MATCH($E14,'ST Enroll Export'!$B$2:$B$3230,0))),"Not Found")) -> 7205350121 | R14: =IFERROR(INDEX('ST Enroll Export'!$G$2:$G$3230,MATCH($D14,'ST Enroll Export'!$A$2:$A$3230,0)),IFERROR(INDEX('ST Enroll Export'!$G$2:$G$3230,MATCH($E14,'ST Enroll Export'!$B$2:$B$3230,0)),"Not Found")) -> Southside Academy Charter School | S14: =IFERROR(INDEX('ST Enroll Export'!$B$2:$B$3230,MATCH($D14,'ST Enroll Export'!$A$2:$A$3230,0)),IFERROR(INDEX('ST Enroll Export'!$B$2:$B$3230,MATCH($E14,'ST Enroll Export'!$B$2:$B$3230,0)),"Not Found")) -> 210018482 | T14: =IF(ISNUMBER(MATCH($D14,'ST Enroll Export'!$A$2:$A$3230,0)),"NYSSIS Match",IF(ISNUMBER(MATCH($E14,'ST Enroll Export'!$B$2:$B$3230,0)),"SID Match","No ST Match")) -> NYSSIS Match | U14: =IF(ISNUMBER(MATCH($D14,Disability!$B$2:$B$5962,0)),"SPED","Gen Ed") -> Gen Ed
A15: Southside 291462 | B15: 46174 | C15: southside_291462_unified-roster.xlsx | D15: 4427385530 | F15: 0 | G15: Donald | H15: K | I15: 44172 | J15: Southside Academy Charter School | K15: 45903 | M15: 1 | N15: Not in ST System | O15: Not pulling up in ST. Need more student information. NYSSIS ID, Last name,grade,parent info, gender, race, etc. | P15: Gen Ed | Q15: =IFERROR(INDEX('ST Enroll Export'!$A$2:$A$3230,MATCH($D15,'ST Enroll Export'!$A$2:$A$3230,0)),IFERROR(IF(INDEX('ST Enroll Export'!$A$2:$A$3230,MATCH($E15,'ST Enroll Export'!$B$2:$B$3230,0))="","",INDEX('ST Enroll Export'!$A$2:$A$3230,MATCH($E15,'ST Enroll Export'!$B$2:$B$3230,0))),"Not Found")) -> Not Found | R15: =IFERROR(INDEX('ST Enroll Export'!$G$2:$G$3230,MATCH($D15,'ST Enroll Export'!$A$2:$A$3230,0)),IFERROR(INDEX('ST Enroll Export'!$G$2:$G$3230,MATCH($E15,'ST Enroll Export'!$B$2:$B$3230,0)),"Not Found")) -> Not Found | S15: =IFERROR(INDEX('ST Enroll Export'!$B$2:$B$3230,MATCH($D15,'ST Enroll Export'!$A$2:$A$3230,0)),IFERROR(INDEX('ST Enroll Export'!$B$2:$B$3230,MATCH($E15,'ST Enroll Export'!$B$2:$B$3230,0)),"Not Found")) -> Not Found | T15: =IF(ISNUMBER(MATCH($D15,'ST Enroll Export'!$A$2:$A$3230,0)),"NYSSIS Match",IF(ISNUMBER(MATCH($E15,'ST Enroll Export'!$B$2:$B$3230,0)),"SID Match","No ST Match")) -> No ST Match | U15: =IF(ISNUMBER(MATCH($D15,Disability!$B$2:$B$5962,0)),"SPED","Gen Ed") -> Gen Ed
A16: Southside 291462 | B16: 46174 | C16: southside_291462_unified-roster.xlsx | D16: 5481567902 | E16: 210022691 | F16: Hatfield | G16: Draylan | H16: K | I16: 43853 | J16: Southside Academy Charter School | K16: 45905 | M16: 0.975 | N16: No Good | O16: ST states: student enrolled at Southside Academy Charter School 10/28/25 - current. Entry date 3> day discrepancy. Need charter attendance record to change in ST. | P16: SPED | Q16: =IFERROR(INDEX('ST Enroll Export'!$A$2:$A$3230,MATCH($D16,'ST Enroll Export'!$A$2:$A$3230,0)),IFERROR(IF(INDEX('ST Enroll Export'!$A$2:$A$3230,MATCH($E16,'ST Enroll Export'!$B$2:$B$3230,0))="","",INDEX('ST Enroll Export'!$A$2:$A$3230,MATCH($E16,'ST Enroll Export'!$B$2:$B$3230,0))),"Not Found")) -> 5481567902 | R16: =IFERROR(INDEX('ST Enroll Export'!$G$2:$G$3230,MATCH($D16,'ST Enroll Export'!$A$2:$A$3230,0)),IFERROR(INDEX('ST Enroll Export'!$G$2:$G$3230,MATCH($E16,'ST Enroll Export'!$B$2:$B$3230,0)),"Not Found")) -> Southside Academy Charter School | S16: =IFERROR(INDEX('ST Enroll Export'!$B$2:$B$3230,MATCH($D16,'ST Enroll Export'!$A$2:$A$3230,0)),IFERROR(INDEX('ST Enroll Export'!$B$2:$B$3230,MATCH($E16,'ST Enroll Export'!$B$2:$B$3230,0)),"Not Found")) -> 210022691 | T16: =IF(ISNUMBER(MATCH($D16,'ST Enroll Export'!$A$2:$A$3230,0)),"NYSSIS Match",IF(ISNUMBER(MATCH($E16,'ST Enroll Export'!$B$2:$B$3230,0)),"SID Match","No ST Match")) -> NYSSIS Match | U16: =IF(ISNUMBER(MATCH($D16,Disability!$B$2:$B$5962,0)),"SPED","Gen Ed") -> SPED
A17: Southside 291462 | B17: 46174 | C17: southside_291462_unified-roster.xlsx | D17: 9345645621 | F17: 0 | G17: Edward | H17: K | I17: 43910 | J17: Southside Academy Charter School | K17: 45918 | M17: 0.925 | N17: Not in ST System | O17: Not pulling up in ST. Need more student information. NYSSIS ID, Last name,grade,parent info, gender, race, etc. | P17: Gen Ed | Q17: =IFERROR(INDEX('ST Enroll Export'!$A$2:$A$3230,MATCH($D17,'ST Enroll Export'!$A$2:$A$3230,0)),IFERROR(IF(INDEX('ST Enroll Export'!$A$2:$A$3230,MATCH($E17,'ST Enroll Export'!$B$2:$B$3230,0))="","",INDEX('ST Enroll Export'!$A$2:$A$3230,MATCH($E17,'ST Enroll Export'!$B$2:$B$3230,0))),"Not Found")) -> Not Found | R17: =IFERROR(INDEX('ST Enroll Export'!$G$2:$G$3230,MATCH($D17,'ST Enroll Export'!$A$2:$A$3230,0)),IFERROR(INDEX('ST Enroll Export'!$G$2:$G$3230,MATCH($E17,'ST Enroll Export'!$B$2:$B$3230,0)),"Not Found")) -> Not Found | S17: =IFERROR(INDEX('ST Enroll Export'!$B$2:$B$3230,MATCH($D17,'ST Enroll Export'!$A$2:$A$3230,0)),IFERROR(INDEX('ST Enroll Export'!$B$2:$B$3230,MATCH($E17,'ST Enroll Export'!$B$2:$B$3230,0)),"Not Found")) -> Not Found | T17: =IF(ISNUMBER(MATCH($D17,'ST Enroll Export'!$A$2:$A$3230,0)),"NYSSIS Match",IF(ISNUMBER(MATCH($E17,'ST Enroll Export'!$B$2:$B$3230,0)),"SID Match","No ST Match")) -> No ST Match | U17: =IF(ISNUMBER(MATCH($D17,Disability!$B$2:$B$5962,0)),"SPED","Gen Ed") -> Gen Ed
A18: Southside 291462 | B18: 46174 | C18: southside_291462_unified-roster.xlsx | D18: 3226816591 | E18: 210018247 | F18: Giddings | G18: Gracie | H18: K | I18: 44192 | J18: Southside Academy Charter School | K18: 45904 | M18: 0.975 | N18: No Good | O18: ST states: student enrolled at Southside Academy Charter School 1/7/25- current. Entry date 3> day discrepancy. Need charter attendance record to change in ST. | P18: Gen Ed | Q18: =IFERROR(INDEX('ST Enroll Export'!$A$2:$A$3230,MATCH($D18,'ST Enroll Export'!$A$2:$A$3230,0)),IFERROR(IF(INDEX('ST Enroll Export'!$A$2:$A$3230,MATCH($E18,'ST Enroll Export'!$B$2:$B$3230,0))="","",INDEX('ST Enroll Export'!$A$2:$A$3230,MATCH($E18,'ST Enroll Export'!$B$2:$B$3230,0))),"Not Found")) -> 3226816591 | R18: =IFERROR(INDEX('ST Enroll Export'!$G$2:$G$3230,MATCH($D18,'ST Enroll Export'!$A$2:$A$3230,0)),IFERROR(INDEX('ST Enroll Export'!$G$2:$G$3230,MATCH($E18,'ST Enroll Export'!$B$2:$B$3230,0)),"Not Found")) -> Southside Academy Charter School | S18: =IFERROR(INDEX('ST Enroll Export'!$B$2:$B$3230,MATCH($D18,'ST Enroll Export'!$A$2:$A$3230,0)),IFERROR(INDEX('ST Enroll Export'!$B$2:$B$3230,MATCH($E18,'ST Enroll Export'!$B$2:$B$3230,0)),"Not Found")) -> 210018247 | T18: =IF(ISNUMBER(MATCH($D18,'ST Enroll Export'!$A$2:$A$3230,0)),"NYSSIS Match",IF(ISNUMBER(MATCH($E18,'ST Enroll Export'!$B$2:$B$3230,0)),"SID Match","No ST Match")) -> NYSSIS Match | U18: =IF(ISNUMBER(MATCH($D18,Disability!$B$2:$B$5962,0)),"SPED","Gen Ed") -> Gen Ed
A19: Southside 291462 | B19: 46174 | C19: southside_291462_unified-roster.xlsx | D19: 8891043605 | E19: 210011263 | F19: Maldonado | G19: INessa | H19: 2 | I19: 43358 | J19: Southside Academy Charter School | K19: 45910 | M19: 0.975 | N19: No Good | O19: ST states: student enrolled at Southside Academy Charter School 11/5/25- current. Entry date 3> day discrepancy. Need charter attendance record to change in ST. | P19: SPED | Q19: =IFERROR(INDEX('ST Enroll Export'!$A$2:$A$3230,MATCH($D19,'ST Enroll Export'!$A$2:$A$3230,0)),IFERROR(IF(INDEX('ST Enroll Export'!$A$2:$A$3230,MATCH($E19,'ST Enroll Export'!$B$2:$B$3230,0))="","",INDEX('ST Enroll Export'!$A$2:$A$3230,MATCH($E19,'ST Enroll Export'!$B$2:$B$3230,0))),"Not Found")) -> 8891043605 | R19: =IFERROR(INDEX('ST Enroll Export'!$G$2:$G$3230,MATCH($D19,'ST Enroll Export'!$A$2:$A$3230,0)),IFERROR(INDEX('ST Enroll Export'!$G$2:$G$3230,MATCH($E19,'ST Enroll Export'!$B$2:$B$3230,0)),"Not Found")) -> Southside Academy Charter School | S19: =IFERROR(INDEX('ST Enroll Export'!$B$2:$B$3230,MATCH($D19,'ST Enroll Export'!$A$2:$A$3230,0)),IFERROR(INDEX('ST Enroll Export'!$B$2:$B$3230,MATCH($E19,'ST Enroll Export'!$B$2:$B$3230,0)),"Not Found")) -> 210011263 | T19: =IF(ISNUMBER(MATCH($D19,'ST Enroll Export'!$A$2:$A$3230,0)),"NYSSIS Match",IF(ISNUMBER(MATCH($E19,'ST Enroll Export'!$B$2:$B$3230,0)),"SID Match","No ST Match")) -> NYSSIS Match | U19: =IF(ISNUMBER(MATCH($D19,Disability!$B$2:$B$5962,0)),"SPED","Gen Ed") -> SPED
A20: Southside 291462 | B20: 46174 | C20: southside_291462_unified-roster.xlsx | D20: 6207168494 | E20: 200038985 | F20: Sallard | G20: Jaliyah | H20: 4 | I20: 42561 | J20: Southside Academy Charter School | K20: 45915 | M20: 0.95 | N20: No Good | O20: ST states: student enrolled at Southside Academy Charter School 9/24/25- current. Entry date 3> day discrepancy. Need charter attendance record to change in ST. | P20: Gen Ed | Q20: =IFERROR(INDEX('ST Enroll Export'!$A$2:$A$3230,MATCH($D20,'ST Enroll Export'!$A$2:$A$3230,0)),IFERROR(IF(INDEX('ST Enroll Export'!$A$2:$A$3230,MATCH($E20,'ST Enroll Export'!$B$2:$B$3230,0))="","",INDEX('ST Enroll Export'!$A$2:$A$3230,MATCH($E20,'ST Enroll Export'!$B$2:$B$3230,0))),"Not Found")) -> 6207168494 | R20: =IFERROR(INDEX('ST Enroll Export'!$G$2:$G$3230,MATCH($D20,'ST Enroll Export'!$A$2:$A$3230,0)),IFERROR(INDEX('ST Enroll Export'!$G$2:$G$3230,MATCH($E20,'ST Enroll Export'!$B$2:$B$3230,0)),"Not Found")) -> Southside Academy Charter School | S20: =IFERROR(INDEX('ST Enroll Export'!$B$2:$B$3230,MATCH($D20,'ST Enroll Export'!$A$2:$A$3230,0)),IFERROR(INDEX('ST Enroll Export'!$B$2:$B$3230,MATCH($E20,'ST Enroll Export'!$B$2:$B$3230,0)),"Not Found")) -> 200038985 | T20: =IF(ISNUMBER(MATCH($D20,'ST Enroll Export'!$A$2:$A$3230,0)),"NYSSIS Match",IF(ISNUMBER(MATCH($E20,'ST Enroll Export'!$B$2:$B$3230,0)),"SID Match","No ST Match")) -> NYSSIS Match | U20: =IF(ISNUMBER(MATCH($D20,Disability!$B$2:$B$5962,0)),"SPED","Gen Ed") -> Gen Ed
A21: Southside 291462 | B21: 46174 | C21: southside_291462_unified-roster.xlsx | D21: 7360992380 | E21: 210022689 | F21: Vaughns | G21: Jayceon | H21: 2 | I21: 43318 | J21: Southside Academy Charter School | K21: 45905 | M21: 0.975 | N21: No Good | O21: ST states: student enrolled at Southside Academy Charter School 10/28/25- current. Entry date 3> day discrepancy. Need charter attendance record to change in ST. | P21: SPED | Q21: =IFERROR(INDEX('ST Enroll Export'!$A$2:$A$3230,MATCH($D21,'ST Enroll Export'!$A$2:$A$3230,0)),IFERROR(IF(INDEX('ST Enroll Export'!$A$2:$A$3230,MATCH($E21,'ST Enroll Export'!$B$2:$B$3230,0))="","",INDEX('ST Enroll Export'!$A$2:$A$3230,MATCH($E21,'ST Enroll Export'!$B$2:$B$3230,0))),"Not Found")) -> 7360992380 | R21: =IFERROR(INDEX('ST Enroll Export'!$G$2:$G$3230,MATCH($D21,'ST Enroll Export'!$A$2:$A$3230,0)),IFERROR(INDEX('ST Enroll Export'!$G$2:$G$3230,MATCH($E21,'ST Enroll Export'!$B$2:$B$3230,0)),"Not Found")) -> Southside Academy Charter School | S21: =IFERROR(INDEX('ST Enroll Export'!$B$2:$B$3230,MATCH($D21,'ST Enroll Export'!$A$2:$A$3230,0)),IFERROR(INDEX('ST Enroll Export'!$B$2:$B$3230,MATCH($E21,'ST Enroll Export'!$B$2:$B$3230,0)),"Not Found")) -> 210022689 | T21: =IF(ISNUMBER(MATCH($D21,'ST Enroll Export'!$A$2:$A$3230,0)),"NYSSIS Match",IF(ISNUMBER(MATCH($E21,'ST Enroll Export'!$B$2:$B$3230,0)),"SID Match","No ST Match")) -> NYSSIS Match | U21: =IF(ISNUMBER(MATCH($D21,Disability!$B$2:$B$5962,0)),"SPED","Gen Ed") -> SPED
A22: Southside 291462 | B22: 46174 | C22: southside_291462_unified-roster.xlsx | D22: 9316354706 | E22: 210014757 | F22: Jackson | G22: Jordyn | H22: K | I22: 44128 | J22: Southside Academy Charter School | K22: 45903 | M22: 1 | N22: No Good | O22: ST states: student enrolled at Syracuse Academy of Science Elementary at St James 8/15/25 - 9/14/25. Enrolled at Southside Academy 9/15/25 - current. Entry 3> day discrepancy. Need charter attendance record to change in ST. | P22: Gen Ed | Q22: =IFERROR(INDEX('ST Enroll Export'!$A$2:$A$3230,MATCH($D22,'ST Enroll Export'!$A$2:$A$3230,0)),IFERROR(IF(INDEX('ST Enroll Export'!$A$2:$A$3230,MATCH($E22,'ST Enroll Export'!$B$2:$B$3230,0))="","",INDEX('ST Enroll Export'!$A$2:$A$3230,MATCH($E22,'ST Enroll Export'!$B$2:$B$3230,0))),"Not Found")) -> 9316354706 | R22: =IFERROR(INDEX('ST Enroll Export'!$G$2:$G$3230,MATCH($D22,'ST Enroll Export'!$A$2:$A$3230,0)),IFERROR(INDEX('ST Enroll Export'!$G$2:$G$3230,MATCH($E22,'ST Enroll Export'!$B$2:$B$3230,0)),"Not Found")) -> Southside Academy Charter School | S22: =IFERROR(INDEX('ST Enroll Export'!$B$2:$B$3230,MATCH($D22,'ST Enroll Export'!$A$2:$A$3230,0)),IFERROR(INDEX('ST Enroll Export'!$B$2:$B$3230,MATCH($E22,'ST Enroll Export'!$B$2:$B$3230,0)),"Not Found")) -> 210014757 | T22: =IF(ISNUMBER(MATCH($D22,'ST Enroll Export'!$A$2:$A$3230,0)),"NYSSIS Match",IF(ISNUMBER(MATCH($E22,'ST Enroll Export'!$B$2:$B$3230,0)),"SID Match","No ST Match")) -> NYSSIS Match | U22: =IF(ISNUMBER(MATCH($D22,Disability!$B$2:$B$5962,0)),"SPED","Gen Ed") -> Gen Ed
A23: Southside 291462 | B23: 46174 | C23: southside_291462_unified-roster.xlsx | F23: 0 | G23: Josiah | H23: 7 | I23: 41450 | J23: Southside Academy Charter School | K23: 45903 | M23: 1 | N23: Not in ST System | O23: Not pulling up in ST. | P23: Gen Ed | Q23: =IFERROR(INDEX('ST Enroll Export'!$A$2:$A$3230,MATCH($D23,'ST Enroll Export'!$A$2:$A$3230,0)),IFERROR(IF(INDEX('ST Enroll Export'!$A$2:$A$3230,MATCH($E23,'ST Enroll Export'!$B$2:$B$3230,0))="","",INDEX('ST Enroll Export'!$A$2:$A$3230,MATCH($E23,'ST Enroll Export'!$B$2:$B$3230,0))),"Not Found")) -> Not Found | R23: =IFERROR(INDEX('ST Enroll Export'!$G$2:$G$3230,MATCH($D23,'ST Enroll Export'!$A$2:$A$3230,0)),IFERROR(INDEX('ST Enroll Export'!$G$2:$G$3230,MATCH($E23,'ST Enroll Export'!$B$2:$B$3230,0)),"Not Found")) -> Not Found | S23: =IFERROR(INDEX('ST Enroll Export'!$B$2:$B$3230,MATCH($D23,'ST Enroll Export'!$A$2:$A$3230,0)),IFERROR(INDEX('ST Enroll Export'!$B$2:$B$3230,MATCH($E23,'ST Enroll Export'!$B$2:$B$3230,0)),"Not Found")) -> Not Found | T23: =IF(ISNUMBER(MATCH($D23,'ST Enroll Export'!$A$2:$A$3230,0)),"NYSSIS Match",IF(ISNUMBER(MATCH($E23,'ST Enroll Export'!$B$2:$B$3230,0)),"SID Match","No ST Match")) -> No ST Match | U23: =IF(ISNUMBER(MATCH($D23,Disability!$B$2:$B$5962,0)),"SPED","Gen Ed") -> Gen Ed
A24: Southside 291462 | B24: 46174 | C24: southside_291462_unified-roster.xlsx | D24: 4148681903 | E24: 210019004 | F24: Robertson | G24: Jovanni | H24: 1 | I24: 43725 | J24: Citizenship & Science Academy of Syracuse Charter | K24: 45903 | M24: 1 | N24: No Good | O24: ST states: student enrolled at Citizenship & Science Academy of Syracuse Charter 7/1/25 - 9/10/25.. Enrolled at Southside Academy 9/24/25 - current. Entry 3> day discrepancy. Need charter attendance record to change in ST. | P24: Gen Ed | Q24: =IFERROR(INDEX('ST Enroll Export'!$A$2:$A$3230,MATCH($D24,'ST Enroll Export'!$A$2:$A$3230,0)),IFERROR(IF(INDEX('ST Enroll Export'!$A$2:$A$3230,MATCH($E24,'ST Enroll Export'!$B$2:$B$3230,0))="","",INDEX('ST Enroll Export'!$A$2:$A$3230,MATCH($E24,'ST Enroll Export'!$B$2:$B$3230,0))),"Not Found")) -> 4148681903 | R24: =IFERROR(INDEX('ST Enroll Export'!$G$2:$G$3230,MATCH($D24,'ST Enroll Export'!$A$2:$A$3230,0)),IFERROR(INDEX('ST Enroll Export'!$G$2:$G$3230,MATCH($E24,'ST Enroll Export'!$B$2:$B$3230,0)),"Not Found")) -> Citizenship & Science Academy of Syracuse Charter | S24: =IFERROR(INDEX('ST Enroll Export'!$B$2:$B$3230,MATCH($D24,'ST Enroll Export'!$A$2:$A$3230,0)),IFERROR(INDEX('ST Enroll Export'!$B$2:$B$3230,MATCH($E24,'ST Enroll Export'!$B$2:$B$3230,0)),"Not Found")) -> 210019004 | T24: =IF(ISNUMBER(MATCH($D24,'ST Enroll Export'!$A$2:$A$3230,0)),"NYSSIS Match",IF(ISNUMBER(MATCH($E24,'ST Enroll Export'!$B$2:$B$3230,0)),"SID Match","No ST Match")) -> NYSSIS Match | U24: =IF(ISNUMBER(MATCH($D24,Disability!$B$2:$B$5962,0)),"SPED","Gen Ed") -> Gen Ed
A25: Southside 291462 | B25: 46174 | C25: southside_291462_unified-roster.xlsx | D25: 3321809294 | E25: 200033900 | F25: Anderson | G25: Juelez | H25: 5 | I25: 41625 | J25: Southside Academy Charter School | K25: 45903 | L25: 45995 | M25: 0.325 | N25: No Good | O25: ST states: student enrolled at Southside Academy Charter School 7/1/25- 11/24/25. Enrolled at STEAM @ Dr King / ES 11/25/25- current. Entry date 3> day discrepancy. Need charter attendance record to change in ST. | P25: SPED | Q25: =IFERROR(INDEX('ST Enroll Export'!$A$2:$A$3230,MATCH($D25,'ST Enroll Export'!$A$2:$A$3230,0)),IFERROR(IF(INDEX('ST Enroll Export'!$A$2:$A$3230,MATCH($E25,'ST Enroll Export'!$B$2:$B$3230,0))="","",INDEX('ST Enroll Export'!$A$2:$A$3230,MATCH($E25,'ST Enroll Export'!$B$2:$B$3230,0))),"Not Found")) -> 3321809294 | R25: =IFERROR(INDEX('ST Enroll Export'!$G$2:$G$3230,MATCH($D25,'ST Enroll Export'!$A$2:$A$3230,0)),IFERROR(INDEX('ST Enroll Export'!$G$2:$G$3230,MATCH($E25,'ST Enroll Export'!$B$2:$B$3230,0)),"Not Found")) -> Southside Academy Charter School | S25: =IFERROR(INDEX('ST Enroll Export'!$B$2:$B$3230,MATCH($D25,'ST Enroll Export'!$A$2:$A$3230,0)),IFERROR(INDEX('ST Enroll Export'!$B$2:$B$3230,MATCH($E25,'ST Enroll Export'!$B$2:$B$3230,0)),"Not Found")) -> 200033900 | T25: =IF(ISNUMBER(MATCH($D25,'ST Enroll Export'!$A$2:$A$3230,0)),"NYSSIS Match",IF(ISNUMBER(MATCH($E25,'ST Enroll Export'!$B$2:$B$3230,0)),"SID Match","No ST Match")) -> NYSSIS Match | U25: =IF(ISNUMBER(MATCH($D25,Disability!$B$2:$B$5962,0)),"SPED","Gen Ed") -> SPED
A26: Southside 291462 | B26: 46174 | C26: southside_291462_unified-roster.xlsx | D26: 2807672461 | E26: 200024256 | F26: Cenzalli JR | G26: Justin | H26: 8 | I26: 41042 | J26: Southside Academy Charter School | K26: 45903 | L26: 45919 | M26: 0.075 | N26: No Good | O26: ST states: student enrolled at Southside Academy Charter School 9/6/25 - 9/11/25. Enrolled at Ed Smith PK-8 / MS 9/18/25- 2/6/25. Entry date 3> day discrepancy. Need charter attendance record to change in ST. | P26: SPED | Q26: =IFERROR(INDEX('ST Enroll Export'!$A$2:$A$3230,MATCH($D26,'ST Enroll Export'!$A$2:$A$3230,0)),IFERROR(IF(INDEX('ST Enroll Export'!$A$2:$A$3230,MATCH($E26,'ST Enroll Export'!$B$2:$B$3230,0))="","",INDEX('ST Enroll Export'!$A$2:$A$3230,MATCH($E26,'ST Enroll Export'!$B$2:$B$3230,0))),"Not Found")) -> 2807672461 | R26: =IFERROR(INDEX('ST Enroll Export'!$G$2:$G$3230,MATCH($D26,'ST Enroll Export'!$A$2:$A$3230,0)),IFERROR(INDEX('ST Enroll Export'!$G$2:$G$3230,MATCH($E26,'ST Enroll Export'!$B$2:$B$3230,0)),"Not Found")) -> Southside Academy Charter School | S26: =IFERROR(INDEX('ST Enroll Export'!$B$2:$B$3230,MATCH($D26,'ST Enroll Export'!$A$2:$A$3230,0)),IFERROR(INDEX('ST Enroll Export'!$B$2:$B$3230,MATCH($E26,'ST Enroll Export'!$B$2:$B$3230,0)),"Not Found")) -> 200024256 | T26: =IF(ISNUMBER(MATCH($D26,'ST Enroll Export'!$A$2:$A$3230,0)),"NYSSIS Match",IF(ISNUMBER(MATCH($E26,'ST Enroll Export'!$B$2:$B$3230,0)),"SID Match","No ST Match")) -> NYSSIS Match | U26: =IF(ISNUMBER(MATCH($D26,Disability!$B$2:$B$5962,0)),"SPED","Gen Ed") -> SPED
A27: Southside 291462 | B27: 46174 | C27: southside_291462_unified-roster.xlsx | D27: 3908940154 | E27: 210002244 | F27: Lobban | G27: Kahwi | H27: 5 | I27: 41841 | J27: Southside Academy Charter School | K27: 45904 | L27: 45923 | M27: 0.05 | N27: No Good | O27: ST states: student enrolled at Southside Academy Charter School 7/1/25 - 9/8/25. Enrolled at STEAM @ Dr King / ES 9/18/25 - current. Entry date 3> day discrepancy. Need charter attendance record to change in ST. | P27: SPED | Q27: =IFERROR(INDEX('ST Enroll Export'!$A$2:$A$3230,MATCH($D27,'ST Enroll Export'!$A$2:$A$3230,0)),IFERROR(IF(INDEX('ST Enroll Export'!$A$2:$A$3230,MATCH($E27,'ST Enroll Export'!$B$2:$B$3230,0))="","",INDEX('ST Enroll Export'!$A$2:$A$3230,MATCH($E27,'ST Enroll Export'!$B$2:$B$3230,0))),"Not Found")) -> 3908940154 | R27: =IFERROR(INDEX('ST Enroll Export'!$G$2:$G$3230,MATCH($D27,'ST Enroll Export'!$A$2:$A$3230,0)),IFERROR(INDEX('ST Enroll Export'!$G$2:$G$3230,MATCH($E27,'ST Enroll Export'!$B$2:$B$3230,0)),"Not Found")) -> Southside Academy Charter School | S27: =IFERROR(INDEX('ST Enroll Export'!$B$2:$B$3230,MATCH($D27,'ST Enroll Export'!$A$2:$A$3230,0)),IFERROR(INDEX('ST Enroll Export'!$B$2:$B$3230,MATCH($E27,'ST Enroll Export'!$B$2:$B$3230,0)),"Not Found")) -> 210002244 | T27: =IF(ISNUMBER(MATCH($D27,'ST Enroll Export'!$A$2:$A$3230,0)),"NYSSIS Match",IF(ISNUMBER(MATCH($E27,'ST Enroll Export'!$B$2:$B$3230,0)),"SID Match","No ST Match")) -> NYSSIS Match | U27: =IF(ISNUMBER(MATCH($D27,Disability!$B$2:$B$5962,0)),"SPED","Gen Ed") -> SPED
A28: Southside 291462 | B28: 46174 | C28: southside_291462_unified-roster.xlsx | D28: 4658757613 | F28: Titus | G28: Kaiden | H28: K | I28: 44196 | J28: Southside Academy Charter School | K28: 45903 | M28: 1 | N28: No Good | O28: ST states: enrolled at McKinley Brighton ES 7/3/25-9/8/25. With note that parent reported child will attend Southside. Need charter attendance report to change in ST. | P28: Gen Ed | Q28: =IFERROR(INDEX('ST Enroll Export'!$A$2:$A$3230,MATCH($D28,'ST Enroll Export'!$A$2:$A$3230,0)),IFERROR(IF(INDEX('ST Enroll Export'!$A$2:$A$3230,MATCH($E28,'ST Enroll Export'!$B$2:$B$3230,0))="","",INDEX('ST Enroll Export'!$A$2:$A$3230,MATCH($E28,'ST Enroll Export'!$B$2:$B$3230,0))),"Not Found")) -> Not Found | R28: =IFERROR(INDEX('ST Enroll Export'!$G$2:$G$3230,MATCH($D28,'ST Enroll Export'!$A$2:$A$3230,0)),IFERROR(INDEX('ST Enroll Export'!$G$2:$G$3230,MATCH($E28,'ST Enroll Export'!$B$2:$B$3230,0)),"Not Found")) -> Not Found | S28: =IFERROR(INDEX('ST Enroll Export'!$B$2:$B$3230,MATCH($D28,'ST Enroll Export'!$A$2:$A$3230,0)),IFERROR(INDEX('ST Enroll Export'!$B$2:$B$3230,MATCH($E28,'ST Enroll Export'!$B$2:$B$3230,0)),"Not Found")) -> Not Found | T28: =IF(ISNUMBER(MATCH($D28,'ST Enroll Export'!$A$2:$A$3230,0)),"NYSSIS Match",IF(ISNUMBER(MATCH($E28,'ST Enroll Export'!$B$2:$B$3230,0)),"SID Match","No ST Match")) -> No ST Match | U28: =IF(ISNUMBER(MATCH($D28,Disability!$B$2:$B$5962,0)),"SPED","Gen Ed") -> Gen Ed
A29: Southside 291462 | B29: 46174 | C29: southside_291462_unified-roster.xlsx | D29: 2808195416 | E29: 210017791 | F29: Maddox | G29: Kelani | H29: K | I29: 44152 | J29: Southside Academy Charter School | K29: 45917 | M29: 0.95 | N29: No Good | O29: ST states: student enrolled at Southside Academy Charter School 11/12/25- current. Entry date 3> day discrepancy. Need charter attendance record to change in ST. | P29: Gen Ed | Q29: =IFERROR(INDEX('ST Enroll Export'!$A$2:$A$3230,MATCH($D29,'ST Enroll Export'!$A$2:$A$3230,0)),IFERROR(IF(INDEX('ST Enroll Export'!$A$2:$A$3230,MATCH($E29,'ST Enroll Export'!$B$2:$B$3230,0))="","",INDEX('ST Enroll Export'!$A$2:$A$3230,MATCH($E29,'ST Enroll Export'!$B$2:$B$3230,0))),"Not Found")) -> 2808195416 | R29: =IFERROR(INDEX('ST Enroll Export'!$G$2:$G$3230,MATCH($D29,'ST Enroll Export'!$A$2:$A$3230,0)),IFERROR(INDEX('ST Enroll Export'!$G$2:$G$3230,MATCH($E29,'ST Enroll Export'!$B$2:$B$3230,0)),"Not Found")) -> Southside Academy Charter School | S29: =IFERROR(INDEX('ST Enroll Export'!$B$2:$B$3230,MATCH($D29,'ST Enroll Export'!$A$2:$A$3230,0)),IFERROR(INDEX('ST Enroll Export'!$B$2:$B$3230,MATCH($E29,'ST Enroll Export'!$B$2:$B$3230,0)),"Not Found")) -> 210017791 | T29: =IF(ISNUMBER(MATCH($D29,'ST Enroll Export'!$A$2:$A$3230,0)),"NYSSIS Match",IF(ISNUMBER(MATCH($E29,'ST Enroll Export'!$B$2:$B$3230,0)),"SID Match","No ST Match")) -> NYSSIS Match | U29: =IF(ISNUMBER(MATCH($D29,Disability!$B$2:$B$5962,0)),"SPED","Gen Ed") -> Gen Ed
A30: Southside 291462 | B30: 46174 | C30: southside_291462_unified-roster.xlsx | D30: 8014067546 | E30: 210022082 | F30: Suressi | G30: Kilani | H30: K | I30: 43979 | J30: Southside Academy Charter School | K30: 45905 | L30: 46010 | M30: 0.35 | N30: No Good | O30: ST states: student enrolled at Southside Academy Charter School 12/10/2025 - 12/21/2025. Entry date 3> day discrepancy. Need charter attendance record to change in ST. | P30: Gen Ed | Q30: =IFERROR(INDEX('ST Enroll Export'!$A$2:$A$3230,MATCH($D30,'ST Enroll Export'!$A$2:$A$3230,0)),IFERROR(IF(INDEX('ST Enroll Export'!$A$2:$A$3230,MATCH($E30,'ST Enroll Export'!$B$2:$B$3230,0))="","",INDEX('ST Enroll Export'!$A$2:$A$3230,MATCH($E30,'ST Enroll Export'!$B$2:$B$3230,0))),"Not Found")) -> 8014067546 | R30: =IFERROR(INDEX('ST Enroll Export'!$G$2:$G$3230,MATCH($D30,'ST Enroll Export'!$A$2:$A$3230,0)),IFERROR(INDEX('ST Enroll Export'!$G$2:$G$3230,MATCH($E30,'ST Enroll Export'!$B$2:$B$3230,0)),"Not Found")) -> Southside Academy Charter School | S30: =IFERROR(INDEX('ST Enroll Export'!$B$2:$B$3230,MATCH($D30,'ST Enroll Export'!$A$2:$A$3230,0)),IFERROR(INDEX('ST Enroll Export'!$B$2:$B$3230,MATCH($E30,'ST Enroll Export'!$B$2:$B$3230,0)),"Not Found")) -> 210022082 | T30: =IF(ISNUMBER(MATCH($D30,'ST Enroll Export'!$A$2:$A$3230,0)),"NYSSIS Match",IF(ISNUMBER(MATCH($E30,'ST Enroll Export'!$B$2:$B$3230,0)),"SID Match","No ST Match")) -> NYSSIS Match | U30: =IF(ISNUMBER(MATCH($D30,Disability!$B$2:$B$5962,0)),"SPED","Gen Ed") -> Gen Ed
A31: Southside 291462 | B31: 46174 | C31: southside_291462_unified-roster.xlsx | F31: 0 | G31: Kisean | H31: 0 | J31: Southside Academy Charter School | K31: 46097 | M31: 0.35 | N31: Not in ST System | O31: Not pulling up in ST. Need more student information. NYSSIS ID, Last name,grade,parent info, gender, race, etc. | P31: Gen Ed | Q31: =IFERROR(INDEX('ST Enroll Export'!$A$2:$A$3230,MATCH($D31,'ST Enroll Export'!$A$2:$A$3230,0)),IFERROR(IF(INDEX('ST Enroll Export'!$A$2:$A$3230,MATCH($E31,'ST Enroll Export'!$B$2:$B$3230,0))="","",INDEX('ST Enroll Export'!$A$2:$A$3230,MATCH($E31,'ST Enroll Export'!$B$2:$B$3230,0))),"Not Found")) -> Not Found | R31: =IFERROR(INDEX('ST Enroll Export'!$G$2:$G$3230,MATCH($D31,'ST Enroll Export'!$A$2:$A$3230,0)),IFERROR(INDEX('ST Enroll Export'!$G$2:$G$3230,MATCH($E31,'ST Enroll Export'!$B$2:$B$3230,0)),"Not Found")) -> Not Found | S31: =IFERROR(INDEX('ST Enroll Export'!$B$2:$B$3230,MATCH($D31,'ST Enroll Export'!$A$2:$A$3230,0)),IFERROR(INDEX('ST Enroll Export'!$B$2:$B$3230,MATCH($E31,'ST Enroll Export'!$B$2:$B$3230,0)),"Not Found")) -> Not Found | T31: =IF(ISNUMBER(MATCH($D31,'ST Enroll Export'!$A$2:$A$3230,0)),"NYSSIS Match",IF(ISNUMBER(MATCH($E31,'ST Enroll Export'!$B$2:$B$3230,0)),"SID Match","No ST Match")) -> No ST Match | U31: =IF(ISNUMBER(MATCH($D31,Disability!$B$2:$B$5962,0)),"SPED","Gen Ed") -> Gen Ed
A32: Southside 291462 | B32: 46174 | C32: southside_291462_unified-roster.xlsx | D32: 8110682342 | E32: 210006494 | F32: Matthews | G32: LaMonte | H32: 2 | I32: 43322 | J32: Southside Academy Charter School | K32: 45903 | L32: 46079 | M32: 0.6 | N32: No Good | O32: ST states: student enrolled at Southside Academy Charter School 8/25/2025 - 2/18/2026. Enrolled at Van Duyn ES / ES 2/19/26- current Entry date 3> day discrepancy. Need charter attendance record to change in ST. | P32: SPED | Q32: =IFERROR(INDEX('ST Enroll Export'!$A$2:$A$3230,MATCH($D32,'ST Enroll Export'!$A$2:$A$3230,0)),IFERROR(IF(INDEX('ST Enroll Export'!$A$2:$A$3230,MATCH($E32,'ST Enroll Export'!$B$2:$B$3230,0))="","",INDEX('ST Enroll Export'!$A$2:$A$3230,MATCH($E32,'ST Enroll Export'!$B$2:$B$3230,0))),"Not Found")) -> 8110682342 | R32: =IFERROR(INDEX('ST Enroll Export'!$G$2:$G$3230,MATCH($D32,'ST Enroll Export'!$A$2:$A$3230,0)),IFERROR(INDEX('ST Enroll Export'!$G$2:$G$3230,MATCH($E32,'ST Enroll Export'!$B$2:$B$3230,0)),"Not Found")) -> Southside Academy Charter School | S32: =IFERROR(INDEX('ST Enroll Export'!$B$2:$B$3230,MATCH($D32,'ST Enroll Export'!$A$2:$A$3230,0)),IFERROR(INDEX('ST Enroll Export'!$B$2:$B$3230,MATCH($E32,'ST Enroll Export'!$B$2:$B$3230,0)),"Not Found")) -> 210006494 | T32: =IF(ISNUMBER(MATCH($D32,'ST Enroll Export'!$A$2:$A$3230,0)),"NYSSIS Match",IF(ISNUMBER(MATCH($E32,'ST Enroll Export'!$B$2:$B$3230,0)),"SID Match","No ST Match")) -> NYSSIS Match | U32: =IF(ISNUMBER(MATCH($D32,Disability!$B$2:$B$5962,0)),"SPED","Gen Ed") -> SPED
A33: Southside 291462 | B33: 46174 | C33: southside_291462_unified-roster.xlsx | D33: 2125386561 | F33: Brynien | G33: Liliana | H33: 4 | I33: 42384 | J33: Southside Academy Charter School | K33: 45964 | M33: 0.8 | N33: No Good | O33: No 25-26 enrollment in ST. Need charter attendance record to make change in ST. | P33: Gen Ed | Q33: =IFERROR(INDEX('ST Enroll Export'!$A$2:$A$3230,MATCH($D33,'ST Enroll Export'!$A$2:$A$3230,0)),IFERROR(IF(INDEX('ST Enroll Export'!$A$2:$A$3230,MATCH($E33,'ST Enroll Export'!$B$2:$B$3230,0))="","",INDEX('ST Enroll Export'!$A$2:$A$3230,MATCH($E33,'ST Enroll Export'!$B$2:$B$3230,0))),"Not Found")) -> Not Found | R33: =IFERROR(INDEX('ST Enroll Export'!$G$2:$G$3230,MATCH($D33,'ST Enroll Export'!$A$2:$A$3230,0)),IFERROR(INDEX('ST Enroll Export'!$G$2:$G$3230,MATCH($E33,'ST Enroll Export'!$B$2:$B$3230,0)),"Not Found")) -> Not Found | S33: =IFERROR(INDEX('ST Enroll Export'!$B$2:$B$3230,MATCH($D33,'ST Enroll Export'!$A$2:$A$3230,0)),IFERROR(INDEX('ST Enroll Export'!$B$2:$B$3230,MATCH($E33,'ST Enroll Export'!$B$2:$B$3230,0)),"Not Found")) -> Not Found | T33: =IF(ISNUMBER(MATCH($D33,'ST Enroll Export'!$A$2:$A$3230,0)),"NYSSIS Match",IF(ISNUMBER(MATCH($E33,'ST Enroll Export'!$B$2:$B$3230,0)),"SID Match","No ST Match")) -> No ST Match | U33: =IF(ISNUMBER(MATCH($D33,Disability!$B$2:$B$5962,0)),"SPED","Gen Ed") -> Gen Ed
A34: Southside 291462 | B34: 46174 | C34: southside_291462_unified-roster.xlsx | D34: 5279781642 | E34: 210017699 | F34: James-Haygood | G34: Llmanuel | H34: K | I34: 44110 | J34: Southside Academy Charter School | K34: 45908 | M34: 0.975 | N34: No Good | O34: ST states: Enrolled at Southside Academy Charter School 7/1/25 - 3/3/26. Need charter school attendance record to change in ST. | P34: Gen Ed | Q34: =IFERROR(INDEX('ST Enroll Export'!$A$2:$A$3230,MATCH($D34,'ST Enroll Export'!$A$2:$A$3230,0)),IFERROR(IF(INDEX('ST Enroll Export'!$A$2:$A$3230,MATCH($E34,'ST Enroll Export'!$B$2:$B$3230,0))="","",INDEX('ST Enroll Export'!$A$2:$A$3230,MATCH($E34,'ST Enroll Export'!$B$2:$B$3230,0))),"Not Found")) | R34: =IFERROR(INDEX('ST Enroll Export'!$G$2:$G$3230,MATCH($D34,'ST Enroll Export'!$A$2:$A$3230,0)),IFERROR(INDEX('ST Enroll Export'!$G$2:$G$3230,MATCH($E34,'ST Enroll Export'!$B$2:$B$3230,0)),"Not Found")) -> Southside Academy Charter School | S34: =IFERROR(INDEX('ST Enroll Export'!$B$2:$B$3230,MATCH($D34,'ST Enroll Export'!$A$2:$A$3230,0)),IFERROR(INDEX('ST Enroll Export'!$B$2:$B$3230,MATCH($E34,'ST Enroll Export'!$B$2:$B$3230,0)),"Not Found")) -> 210017699 | T34: =IF(ISNUMBER(MATCH($D34,'ST Enroll Export'!$A$2:$A$3230,0)),"NYSSIS Match",IF(ISNUMBER(MATCH($E34,'ST Enroll Export'!$B$2:$B$3230,0)),"SID Match","No ST Match")) -> SID Match | U34: =IF(ISNUMBER(MATCH($D34,Disability!$B$2:$B$5962,0)),"SPED","Gen Ed") -> Gen Ed
A35: Southside 291462 | B35: 46174 | C35: southside_291462_unified-roster.xlsx | D35: 6748943165 | E35: 210016382 | F35: Warde | G35: Malachi | H35: 6 | I35: 41501 | J35: Southside Academy Charter School | K35: 45903 | M35: 1 | N35: No Good | O35: ST states: student enrolled at Grant MS / MS 7/1/25 - 9/15/25. Enrolled at Southside Academy Charter School 9/16/25 - current. Entry date 3> day discrepancy. Need charter attendance record to change in ST. | P35: Gen Ed | Q35: =IFERROR(INDEX('ST Enroll Export'!$A$2:$A$3230,MATCH($D35,'ST Enroll Export'!$A$2:$A$3230,0)),IFERROR(IF(INDEX('ST Enroll Export'!$A$2:$A$3230,MATCH($E35,'ST Enroll Export'!$B$2:$B$3230,0))="","",INDEX('ST Enroll Export'!$A$2:$A$3230,MATCH($E35,'ST Enroll Export'!$B$2:$B$3230,0))),"Not Found")) -> 6748943165 | R35: =IFERROR(INDEX('ST Enroll Export'!$G$2:$G$3230,MATCH($D35,'ST Enroll Export'!$A$2:$A$3230,0)),IFERROR(INDEX('ST Enroll Export'!$G$2:$G$3230,MATCH($E35,'ST Enroll Export'!$B$2:$B$3230,0)),"Not Found")) -> Southside Academy Charter School | S35: =IFERROR(INDEX('ST Enroll Export'!$B$2:$B$3230,MATCH($D35,'ST Enroll Export'!$A$2:$A$3230,0)),IFERROR(INDEX('ST Enroll Export'!$B$2:$B$3230,MATCH($E35,'ST Enroll Export'!$B$2:$B$3230,0)),"Not Found")) -> 210016382 | T35: =IF(ISNUMBER(MATCH($D35,'ST Enroll Export'!$A$2:$A$3230,0)),"NYSSIS Match",IF(ISNUMBER(MATCH($E35,'ST Enroll Export'!$B$2:$B$3230,0)),"SID Match","No ST Match")) -> NYSSIS Match | U35: =IF(ISNUMBER(MATCH($D35,Disability!$B$2:$B$5962,0)),"SPED","Gen Ed") -> Gen Ed
A36: Southside 291462 | B36: 46174 | C36: southside_291462_unified-roster.xlsx | D36: 4302512531 | E36: 210002246 | F36: Lobban | G36: Mehki | H36: 5 | I36: 41841 | J36: Southside Academy Charter School | K36: 45904 | L36: 45919 | M36: 0.05 | N36: No Good | O36: ST states: student enrolled at Southside Academy Charter School 7/1/2025 - 9/8/2025. Enrolled at STEAM @ Dr King / ES 9/18/25 - current. Entry date 3> day discrepancy. Need charter attendance record to change in ST. | P36: SPED | Q36: =IFERROR(INDEX('ST Enroll Export'!$A$2:$A$3230,MATCH($D36,'ST Enroll Export'!$A$2:$A$3230,0)),IFERROR(IF(INDEX('ST Enroll Export'!$A$2:$A$3230,MATCH($E36,'ST Enroll Export'!$B$2:$B$3230,0))="","",INDEX('ST Enroll Export'!$A$2:$A$3230,MATCH($E36,'ST Enroll Export'!$B$2:$B$3230,0))),"Not Found")) -> 4302512531 | R36: =IFERROR(INDEX('ST Enroll Export'!$G$2:$G$3230,MATCH($D36,'ST Enroll Export'!$A$2:$A$3230,0)),IFERROR(INDEX('ST Enroll Export'!$G$2:$G$3230,MATCH($E36,'ST Enroll Export'!$B$2:$B$3230,0)),"Not Found")) -> Southside Academy Charter School | S36: =IFERROR(INDEX('ST Enroll Export'!$B$2:$B$3230,MATCH($D36,'ST Enroll Export'!$A$2:$A$3230,0)),IFERROR(INDEX('ST Enroll Export'!$B$2:$B$3230,MATCH($E36,'ST Enroll Export'!$B$2:$B$3230,0)),"Not Found")) -> 210002246 | T36: =IF(ISNUMBER(MATCH($D36,'ST Enroll Export'!$A$2:$A$3230,0)),"NYSSIS Match",IF(ISNUMBER(MATCH($E36,'ST Enroll Export'!$B$2:$B$3230,0)),"SID Match","No ST Match")) -> NYSSIS Match | U36: =IF(ISNUMBER(MATCH($D36,Disability!$B$2:$B$5962,0)),"SPED","Gen Ed") -> SPED
A37: Southside 291462 | B37: 46174 | C37: southside_291462_unified-roster.xlsx | D37: 8460982760 | E37: 210022815 | F37: Lindsey | G37: Nadir | H37: K | I37: 44033 | J37: Southside Academy Charter School | K37: 45964 | L37: 46010 | M37: 0.175 | N37: No Good | O37: ST states: Enrolled at Southside Academy Charter School 11/12/25-current. Entry date 3> day discrepancy. Need charter school attendance record to change in ST. | P37: Gen Ed | Q37: =IFERROR(INDEX('ST Enroll Export'!$A$2:$A$3230,MATCH($D37,'ST Enroll Export'!$A$2:$A$3230,0)),IFERROR(IF(INDEX('ST Enroll Export'!$A$2:$A$3230,MATCH($E37,'ST Enroll Export'!$B$2:$B$3230,0))="","",INDEX('ST Enroll Export'!$A$2:$A$3230,MATCH($E37,'ST Enroll Export'!$B$2:$B$3230,0))),"Not Found")) | R37: =IFERROR(INDEX('ST Enroll Export'!$G$2:$G$3230,MATCH($D37,'ST Enroll Export'!$A$2:$A$3230,0)),IFERROR(INDEX('ST Enroll Export'!$G$2:$G$3230,MATCH($E37,'ST Enroll Export'!$B$2:$B$3230,0)),"Not Found")) -> Southside Academy Charter School | S37: =IFERROR(INDEX('ST Enroll Export'!$B$2:$B$3230,MATCH($D37,'ST Enroll Export'!$A$2:$A$3230,0)),IFERROR(INDEX('ST Enroll Export'!$B$2:$B$3230,MATCH($E37,'ST Enroll Export'!$B$2:$B$3230,0)),"Not Found")) -> 210022815 | T37: =IF(ISNUMBER(MATCH($D37,'ST Enroll Export'!$A$2:$A$3230,0)),"NYSSIS Match",IF(ISNUMBER(MATCH($E37,'ST Enroll Export'!$B$2:$B$3230,0)),"SID Match","No ST Match")) -> SID Match | U37: =IF(ISNUMBER(MATCH($D37,Disability!$B$2:$B$5962,0)),"SPED","Gen Ed") -> Gen Ed
A38: Southside 291462 | B38: 46174 | C38: southside_291462_unified-roster.xlsx | D38: 2981769541 | E38: 210009975 | F38: Smith | G38: Natalia | H38: 1 | I38: 43468 | J38: Southside Academy Charter School | K38: 45968 | M38: 0.775 | N38: No Good | O38: ST states: student enrolled at Southside Academy Charter School 12/10/2025 - current. Entry date 3> day discrepancy. Need charter attendance record to change in ST. | P38: Gen Ed | Q38: =IFERROR(INDEX('ST Enroll Export'!$A$2:$A$3230,MATCH($D38,'ST Enroll Export'!$A$2:$A$3230,0)),IFERROR(IF(INDEX('ST Enroll Export'!$A$2:$A$3230,MATCH($E38,'ST Enroll Export'!$B$2:$B$3230,0))="","",INDEX('ST Enroll Export'!$A$2:$A$3230,MATCH($E38,'ST Enroll Export'!$B$2:$B$3230,0))),"Not Found")) -> 2981769541 | R38: =IFERROR(INDEX('ST Enroll Export'!$G$2:$G$3230,MATCH($D38,'ST Enroll Export'!$A$2:$A$3230,0)),IFERROR(INDEX('ST Enroll Export'!$G$2:$G$3230,MATCH($E38,'ST Enroll Export'!$B$2:$B$3230,0)),"Not Found")) -> Southside Academy Charter School | S38: =IFERROR(INDEX('ST Enroll Export'!$B$2:$B$3230,MATCH($D38,'ST Enroll Export'!$A$2:$A$3230,0)),IFERROR(INDEX('ST Enroll Export'!$B$2:$B$3230,MATCH($E38,'ST Enroll Export'!$B$2:$B$3230,0)),"Not Found")) -> 210009975 | T38: =IF(ISNUMBER(MATCH($D38,'ST Enroll Export'!$A$2:$A$3230,0)),"NYSSIS Match",IF(ISNUMBER(MATCH($E38,'ST Enroll Export'!$B$2:$B$3230,0)),"SID Match","No ST Match")) -> NYSSIS Match | U38: =IF(ISNUMBER(MATCH($D38,Disability!$B$2:$B$5962,0)),"SPED","Gen Ed") -> Gen Ed
A39: Southside 291462 | B39: 46174 | C39: southside_291462_unified-roster.xlsx | D39: 6994835771 | F39: Morris | G39: Rahmier | H39: K | I39: 44148 | J39: Southside Academy Charter School | K39: 45903 | L39: 45923 | M39: 0.075 | N39: No Good | O39: No enrollment record in ST. Need charter school attendance to create enrollment entry in ST. | P39: Gen Ed | Q39: =IFERROR(INDEX('ST Enroll Export'!$A$2:$A$3230,MATCH($D39,'ST Enroll Export'!$A$2:$A$3230,0)),IFERROR(IF(INDEX('ST Enroll Export'!$A$2:$A$3230,MATCH($E39,'ST Enroll Export'!$B$2:$B$3230,0))="","",INDEX('ST Enroll Export'!$A$2:$A$3230,MATCH($E39,'ST Enroll Export'!$B$2:$B$3230,0))),"Not Found")) -> Not Found | R39: =IFERROR(INDEX('ST Enroll Export'!$G$2:$G$3230,MATCH($D39,'ST Enroll Export'!$A$2:$A$3230,0)),IFERROR(INDEX('ST Enroll Export'!$G$2:$G$3230,MATCH($E39,'ST Enroll Export'!$B$2:$B$3230,0)),"Not Found")) -> Not Found | S39: =IFERROR(INDEX('ST Enroll Export'!$B$2:$B$3230,MATCH($D39,'ST Enroll Export'!$A$2:$A$3230,0)),IFERROR(INDEX('ST Enroll Export'!$B$2:$B$3230,MATCH($E39,'ST Enroll Export'!$B$2:$B$3230,0)),"Not Found")) -> Not Found | T39: =IF(ISNUMBER(MATCH($D39,'ST Enroll Export'!$A$2:$A$3230,0)),"NYSSIS Match",IF(ISNUMBER(MATCH($E39,'ST Enroll Export'!$B$2:$B$3230,0)),"SID Match","No ST Match")) -> No ST Match | U39: =IF(ISNUMBER(MATCH($D39,Disability!$B$2:$B$5962,0)),"SPED","Gen Ed") -> Gen Ed
A40: Southside 291462 | B40: 46174 | C40: southside_291462_unified-roster.xlsx | D40: 1565701023 | E40: 210022225 | F40: Tarrats | G40: Ruben | H40: 7 | I40: 41464 | J40: Southside Academy Charter School | K40: 45915 | M40: 0.95 | N40: No Good | O40: ST states: student enrolled at Southside Academy Charter School 10/15/2025 - current. Entry date 3> day discrepancy. Need charter attendance record to change in ST. | P40: Gen Ed | Q40: =IFERROR(INDEX('ST Enroll Export'!$A$2:$A$3230,MATCH($D40,'ST Enroll Export'!$A$2:$A$3230,0)),IFERROR(IF(INDEX('ST Enroll Export'!$A$2:$A$3230,MATCH($E40,'ST Enroll Export'!$B$2:$B$3230,0))="","",INDEX('ST Enroll Export'!$A$2:$A$3230,MATCH($E40,'ST Enroll Export'!$B$2:$B$3230,0))),"Not Found")) -> 1565701023 | R40: =IFERROR(INDEX('ST Enroll Export'!$G$2:$G$3230,MATCH($D40,'ST Enroll Export'!$A$2:$A$3230,0)),IFERROR(INDEX('ST Enroll Export'!$G$2:$G$3230,MATCH($E40,'ST Enroll Export'!$B$2:$B$3230,0)),"Not Found")) -> Southside Academy Charter School | S40: =IFERROR(INDEX('ST Enroll Export'!$B$2:$B$3230,MATCH($D40,'ST Enroll Export'!$A$2:$A$3230,0)),IFERROR(INDEX('ST Enroll Export'!$B$2:$B$3230,MATCH($E40,'ST Enroll Export'!$B$2:$B$3230,0)),"Not Found")) -> 210022225 | T40: =IF(ISNUMBER(MATCH($D40,'ST Enroll Export'!$A$2:$A$3230,0)),"NYSSIS Match",IF(ISNUMBER(MATCH($E40,'ST Enroll Export'!$B$2:$B$3230,0)),"SID Match","No ST Match")) -> NYSSIS Match | U40: =IF(ISNUMBER(MATCH($D40,Disability!$B$2:$B$5962,0)),"SPED","Gen Ed") -> Gen Ed
A41: Southside 291462 | B41: 46174 | C41: southside_291462_unified-roster.xlsx | D41: 1348451822 | E41: 210022690 | F41: Moore | G41: Samya | H41: 4 | I41: 42401 | J41: Southside Academy Charter School | K41: 45905 | M41: 0.975 | N41: No Good | O41: ST states: Enrolled at Southside Academy Charter School 10/27/25-current. Entry date 3> day discrepancy. Need charter school attendance record to change in ST. | P41: Gen Ed | Q41: =IFERROR(INDEX('ST Enroll Export'!$A$2:$A$3230,MATCH($D41,'ST Enroll Export'!$A$2:$A$3230,0)),IFERROR(IF(INDEX('ST Enroll Export'!$A$2:$A$3230,MATCH($E41,'ST Enroll Export'!$B$2:$B$3230,0))="","",INDEX('ST Enroll Export'!$A$2:$A$3230,MATCH($E41,'ST Enroll Export'!$B$2:$B$3230,0))),"Not Found")) | R41: =IFERROR(INDEX('ST Enroll Export'!$G$2:$G$3230,MATCH($D41,'ST Enroll Export'!$A$2:$A$3230,0)),IFERROR(INDEX('ST Enroll Export'!$G$2:$G$3230,MATCH($E41,'ST Enroll Export'!$B$2:$B$3230,0)),"Not Found")) -> Southside Academy Charter School | S41: =IFERROR(INDEX('ST Enroll Export'!$B$2:$B$3230,MATCH($D41,'ST Enroll Export'!$A$2:$A$3230,0)),IFERROR(INDEX('ST Enroll Export'!$B$2:$B$3230,MATCH($E41,'ST Enroll Export'!$B$2:$B$3230,0)),"Not Found")) -> 210022690 | T41: =IF(ISNUMBER(MATCH($D41,'ST Enroll Export'!$A$2:$A$3230,0)),"NYSSIS Match",IF(ISNUMBER(MATCH($E41,'ST Enroll Export'!$B$2:$B$3230,0)),"SID Match","No ST Match")) -> SID Match | U41: =IF(ISNUMBER(MATCH($D41,Disability!$B$2:$B$5962,0)),"SPED","Gen Ed") -> Gen Ed
A42: Southside 291462 | B42: 46174 | C42: southside_291462_unified-roster.xlsx | D42: 6885359396 | F42: Thurman | G42: Xavier | H42: 1 | I42: 43656 | J42: Southside Academy Charter School | K42: 45903 | L42: 45981 | M42: 0.275 | N42: No Good | O42: No charter enrollment for current year 25-26 in ST. Only Projected Enrollment for Southside Academy for 7/1/26. Need charter attendance record to change in ST. | P42: Gen Ed | Q42: =IFERROR(INDEX('ST Enroll Export'!$A$2:$A$3230,MATCH($D42,'ST Enroll Export'!$A$2:$A$3230,0)),IFERROR(IF(INDEX('ST Enroll Export'!$A$2:$A$3230,MATCH($E42,'ST Enroll Export'!$B$2:$B$3230,0))="","",INDEX('ST Enroll Export'!$A$2:$A$3230,MATCH($E42,'ST Enroll Export'!$B$2:$B$3230,0))),"Not Found")) -> Not Found | R42: =IFERROR(INDEX('ST Enroll Export'!$G$2:$G$3230,MATCH($D42,'ST Enroll Export'!$A$2:$A$3230,0)),IFERROR(INDEX('ST Enroll Export'!$G$2:$G$3230,MATCH($E42,'ST Enroll Export'!$B$2:$B$3230,0)),"Not Found")) -> Not Found | S42: =IFERROR(INDEX('ST Enroll Export'!$B$2:$B$3230,MATCH($D42,'ST Enroll Export'!$A$2:$A$3230,0)),IFERROR(INDEX('ST Enroll Export'!$B$2:$B$3230,MATCH($E42,'ST Enroll Export'!$B$2:$B$3230,0)),"Not Found")) -> Not Found | T42: =IF(ISNUMBER(MATCH($D42,'ST Enroll Export'!$A$2:$A$3230,0)),"NYSSIS Match",IF(ISNUMBER(MATCH($E42,'ST Enroll Export'!$B$2:$B$3230,0)),"SID Match","No ST Match")) -> No ST Match | U42: =IF(ISNUMBER(MATCH($D42,Disability!$B$2:$B$5962,0)),"SPED","Gen Ed") -> Gen Ed
A43: Southside 291462 | B43: 46174 | C43: southside_291462_unified-roster.xlsx | D43: 9391717043 | E43: 210022224 | F43: Tarrats | G43: Zailashay | H43: 6 | I43: 41897 | J43: Southside Academy Charter School | K43: 45930 | M43: 0.9 | N43: No Good | O43: ST states: student enrolled at Southside Academy Charter School 10/15/2025 - current. Entry date 3> day discrepancy. Need charter attendance record to change in ST. | P43: Gen Ed | Q43: =IFERROR(INDEX('ST Enroll Export'!$A$2:$A$3230,MATCH($D43,'ST Enroll Export'!$A$2:$A$3230,0)),IFERROR(IF(INDEX('ST Enroll Export'!$A$2:$A$3230,MATCH($E43,'ST Enroll Export'!$B$2:$B$3230,0))="","",INDEX('ST Enroll Export'!$A$2:$A$3230,MATCH($E43,'ST Enroll Export'!$B$2:$B$3230,0))),"Not Found")) -> 9391717043 | R43: =IFERROR(INDEX('ST Enroll Export'!$G$2:$G$3230,MATCH($D43,'ST Enroll Export'!$A$2:$A$3230,0)),IFERROR(INDEX('ST Enroll Export'!$G$2:$G$3230,MATCH($E43,'ST Enroll Export'!$B$2:$B$3230,0)),"Not Found")) -> Southside Academy Charter School | S43: =IFERROR(INDEX('ST Enroll Export'!$B$2:$B$3230,MATCH($D43,'ST Enroll Export'!$A$2:$A$3230,0)),IFERROR(INDEX('ST Enroll Export'!$B$2:$B$3230,MATCH($E43,'ST Enroll Export'!$B$2:$B$3230,0)),"Not Found")) -> 210022224 | T43: =IF(ISNUMBER(MATCH($D43,'ST Enroll Export'!$A$2:$A$3230,0)),"NYSSIS Match",IF(ISNUMBER(MATCH($E43,'ST Enroll Export'!$B$2:$B$3230,0)),"SID Match","No ST Match")) -> NYSSIS Match | U43: =IF(ISNUMBER(MATCH($D43,Disability!$B$2:$B$5962,0)),"SPED","Gen Ed") -> Gen Ed
A44: Southside 291462 | B44: 46174 | C44: southside_291462_unified-roster.xlsx | D44: 3015231426 | E44: 210023269 | F44: Walker | G44: Zayvian | H44: K | I44: 43861 | J44: Southside Academy Charter School | K44: 45903 | M44: 1 | N44: No Good | O44: ST states: student enrolled at Southside Academy on 4/9/26- current. 3> day discrepancy. Need charter attendance record to change in ST. | P44: Gen Ed | Q44: =IFERROR(INDEX('ST Enroll Export'!$A$2:$A$3230,MATCH($D44,'ST Enroll Export'!$A$2:$A$3230,0)),IFERROR(IF(INDEX('ST Enroll Export'!$A$2:$A$3230,MATCH($E44,'ST Enroll Export'!$B$2:$B$3230,0))="","",INDEX('ST Enroll Export'!$A$2:$A$3230,MATCH($E44,'ST Enroll Export'!$B$2:$B$3230,0))),"Not Found")) | R44: =IFERROR(INDEX('ST Enroll Export'!$G$2:$G$3230,MATCH($D44,'ST Enroll Export'!$A$2:$A$3230,0)),IFERROR(INDEX('ST Enroll Export'!$G$2:$G$3230,MATCH($E44,'ST Enroll Export'!$B$2:$B$3230,0)),"Not Found")) -> Southside Academy Charter School | S44: =IFERROR(INDEX('ST Enroll Export'!$B$2:$B$3230,MATCH($D44,'ST Enroll Export'!$A$2:$A$3230,0)),IFERROR(INDEX('ST Enroll Export'!$B$2:$B$3230,MATCH($E44,'ST Enroll Export'!$B$2:$B$3230,0)),"Not Found")) -> 210023269 | T44: =IF(ISNUMBER(MATCH($D44,'ST Enroll Export'!$A$2:$A$3230,0)),"NYSSIS Match",IF(ISNUMBER(MATCH($E44,'ST Enroll Export'!$B$2:$B$3230,0)),"SID Match","No ST Match")) -> SID Match | U44: =IF(ISNUMBER(MATCH($D44,Disability!$B$2:$B$5962,0)),"SPED","Gen Ed") -> Gen Ed
A45: Southside 291462 | B45: 46174 | C45: southside_291462_unified-roster.xlsx | D45: 5714663321 | E45: 200036826 | F45: Parrilla | G45: Aaminah | H45: 6 | I45: 41964 | J45: Southside Academy Charter School | K45: 45903 | M45: 1 | N45: Good | O45: 0 | P45: SPED | Q45: =IFERROR(INDEX('ST Enroll Export'!$A$2:$A$3230,MATCH($D45,'ST Enroll Export'!$A$2:$A$3230,0)),IFERROR(IF(INDEX('ST Enroll Export'!$A$2:$A$3230,MATCH($E45,'ST Enroll Export'!$B$2:$B$3230,0))="","",INDEX('ST Enroll Export'!$A$2:$A$3230,MATCH($E45,'ST Enroll Export'!$B$2:$B$3230,0))),"Not Found")) -> 5714663321 | R45: =IFERROR(INDEX('ST Enroll Export'!$G$2:$G$3230,MATCH($D45,'ST Enroll Export'!$A$2:$A$3230,0)),IFERROR(INDEX('ST Enroll Export'!$G$2:$G$3230,MATCH($E45,'ST Enroll Export'!$B$2:$B$3230,0)),"Not Found")) -> Southside Academy Charter School | S45: =IFERROR(INDEX('ST Enroll Export'!$B$2:$B$3230,MATCH($D45,'ST Enroll Export'!$A$2:$A$3230,0)),IFERROR(INDEX('ST Enroll Export'!$B$2:$B$3230,MATCH($E45,'ST Enroll Export'!$B$2:$B$3230,0)),"Not Found")) -> 200036826 | T45: =IF(ISNUMBER(MATCH($D45,'ST Enroll Export'!$A$2:$A$3230,0)),"NYSSIS Match",IF(ISNUMBER(MATCH($E45,'ST Enroll Export'!$B$2:$B$3230,0)),"SID Match","No ST Match")) -> NYSSIS Match | U45: =IF(ISNUMBER(MATCH($D45,Disability!$B$2:$B$5962,0)),"SPED","Gen Ed") -> SPED
A46: Southside 291462 | B46: 46174 | C46: southside_291462_unified-roster.xlsx | D46: 9977865516 | E46: 210018968 | F46: Lynch | G46: Aaron | H46: 1 | I46: 43557 | J46: Southside Academy Charter School | K46: 45915 | M46: 0.95 | N46: Good | O46: 0 | P46: Gen Ed | Q46: =IFERROR(INDEX('ST Enroll Export'!$A$2:$A$3230,MATCH($D46,'ST Enroll Export'!$A$2:$A$3230,0)),IFERROR(IF(INDEX('ST Enroll Export'!$A$2:$A$3230,MATCH($E46,'ST Enroll Export'!$B$2:$B$3230,0))="","",INDEX('ST Enroll Export'!$A$2:$A$3230,MATCH($E46,'ST Enroll Export'!$B$2:$B$3230,0))),"Not Found")) -> 9977865516 | R46: =IFERROR(INDEX('ST Enroll Export'!$G$2:$G$3230,MATCH($D46,'ST Enroll Export'!$A$2:$A$3230,0)),IFERROR(INDEX('ST Enroll Export'!$G$2:$G$3230,MATCH($E46,'ST Enroll Export'!$B$2:$B$3230,0)),"Not Found")) -> Southside Academy Charter School | S46: =IFERROR(INDEX('ST Enroll Export'!$B$2:$B$3230,MATCH($D46,'ST Enroll Export'!$A$2:$A$3230,0)),IFERROR(INDEX('ST Enroll Export'!$B$2:$B$3230,MATCH($E46,'ST Enroll Export'!$B$2:$B$3230,0)),"Not Found")) -> 210018968 | T46: =IF(ISNUMBER(MATCH($D46,'ST Enroll Export'!$A$2:$A$3230,0)),"NYSSIS Match",IF(ISNUMBER(MATCH($E46,'ST Enroll Export'!$B$2:$B$3230,0)),"SID Match","No ST Match")) -> NYSSIS Match | U46: =IF(ISNUMBER(MATCH($D46,Disability!$B$2:$B$5962,0)),"SPED","Gen Ed") -> Gen Ed
A47: Southside 291462 | B47: 46174 | C47: southside_291462_unified-roster.xlsx | D47: 4986713632 | E47: 210003070 | F47: Smith | G47: Aaron | H47: 5 | I47: 41842 | J47: Southside Academy Charter School | K47: 45903 | M47: 1 | N47: Good | O47: 0 | P47: Gen Ed | Q47: =IFERROR(INDEX('ST Enroll Export'!$A$2:$A$3230,MATCH($D47,'ST Enroll Export'!$A$2:$A$3230,0)),IFERROR(IF(INDEX('ST Enroll Export'!$A$2:$A$3230,MATCH($E47,'ST Enroll Export'!$B$2:$B$3230,0))="","",INDEX('ST Enroll Export'!$A$2:$A$3230,MATCH($E47,'ST Enroll Export'!$B$2:$B$3230,0))),"Not Found")) -> 4986713632 | R47: =IFERROR(INDEX('ST Enroll Export'!$G$2:$G$3230,MATCH($D47,'ST Enroll Export'!$A$2:$A$3230,0)),IFERROR(INDEX('ST Enroll Export'!$G$2:$G$3230,MATCH($E47,'ST Enroll Export'!$B$2:$B$3230,0)),"Not Found")) -> Southside Academy Charter School | S47: =IFERROR(INDEX('ST Enroll Export'!$B$2:$B$3230,MATCH($D47,'ST Enroll Export'!$A$2:$A$3230,0)),IFERROR(INDEX('ST Enroll Export'!$B$2:$B$3230,MATCH($E47,'ST Enroll Export'!$B$2:$B$3230,0)),"Not Found")) -> 210003070 | T47: =IF(ISNUMBER(MATCH($D47,'ST Enroll Export'!$A$2:$A$3230,0)),"NYSSIS Match",IF(ISNUMBER(MATCH($E47,'ST Enroll Export'!$B$2:$B$3230,0)),"SID Match","No ST Match")) -> NYSSIS Match | U47: =IF(ISNUMBER(MATCH($D47,Disability!$B$2:$B$5962,0)),"SPED","Gen Ed") -> Gen Ed
A48: Southside 291462 | B48: 46174 | C48: southside_291462_unified-roster.xlsx | D48: 9323458081 | E48: 210014696 | F48: Anderson | G48: Aayden | H48: 1 | I48: 43550 | J48: Southside Academy Charter School | K48: 45903 | L48: 46085 | M48: 0.625 | N48: Good | O48: 0 | P48: SPED | Q48: =IFERROR(INDEX('ST Enroll Export'!$A$2:$A$3230,MATCH($D48,'ST Enroll Export'!$A$2:$A$3230,0)),IFERROR(IF(INDEX('ST Enroll Export'!$A$2:$A$3230,MATCH($E48,'ST Enroll Export'!$B$2:$B$3230,0))="","",INDEX('ST Enroll Export'!$A$2:$A$3230,MATCH($E48,'ST Enroll Export'!$B$2:$B$3230,0))),"Not Found")) -> 9323458081 | R48: =IFERROR(INDEX('ST Enroll Export'!$G$2:$G$3230,MATCH($D48,'ST Enroll Export'!$A$2:$A$3230,0)),IFERROR(INDEX('ST Enroll Export'!$G$2:$G$3230,MATCH($E48,'ST Enroll Export'!$B$2:$B$3230,0)),"Not Found")) -> Southside Academy Charter School | S48: =IFERROR(INDEX('ST Enroll Export'!$B$2:$B$3230,MATCH($D48,'ST Enroll Export'!$A$2:$A$3230,0)),IFERROR(INDEX('ST Enroll Export'!$B$2:$B$3230,MATCH($E48,'ST Enroll Export'!$B$2:$B$3230,0)),"Not Found")) -> 210014696 | T48: =IF(ISNUMBER(MATCH($D48,'ST Enroll Export'!$A$2:$A$3230,0)),"NYSSIS Match",IF(ISNUMBER(MATCH($E48,'ST Enroll Export'!$B$2:$B$3230,0)),"SID Match","No ST Match")) -> NYSSIS Match | U48: =IF(ISNUMBER(MATCH($D48,Disability!$B$2:$B$5962,0)),"SPED","Gen Ed") -> SPED
A49: Southside 291462 | B49: 46174 | C49: southside_291462_unified-roster.xlsx | D49: 1983806742 | E49: 210018426 | F49: Durham | G49: Adam | H49: 1 | I49: 43605 | J49: Southside Academy Charter School | K49: 45903 | M49: 1 | N49: Good | O49: 0 | P49: Gen Ed | Q49: =IFERROR(INDEX('ST Enroll Export'!$A$2:$A$3230,MATCH($D49,'ST Enroll Export'!$A$2:$A$3230,0)),IFERROR(IF(INDEX('ST Enroll Export'!$A$2:$A$3230,MATCH($E49,'ST Enroll Export'!$B$2:$B$3230,0))="","",INDEX('ST Enroll Export'!$A$2:$A$3230,MATCH($E49,'ST Enroll Export'!$B$2:$B$3230,0))),"Not Found")) -> 1983806742 | R49: =IFERROR(INDEX('ST Enroll Export'!$G$2:$G$3230,MATCH($D49,'ST Enroll Export'!$A$2:$A$3230,0)),IFERROR(INDEX('ST Enroll Export'!$G$2:$G$3230,MATCH($E49,'ST Enroll Export'!$B$2:$B$3230,0)),"Not Found")) -> Southside Academy Charter School | S49: =IFERROR(INDEX('ST Enroll Export'!$B$2:$B$3230,MATCH($D49,'ST Enroll Export'!$A$2:$A$3230,0)),IFERROR(INDEX('ST Enroll Export'!$B$2:$B$3230,MATCH($E49,'ST Enroll Export'!$B$2:$B$3230,0)),"Not Found")) -> 210018426 | T49: =IF(ISNUMBER(MATCH($D49,'ST Enroll Export'!$A$2:$A$3230,0)),"NYSSIS Match",IF(ISNUMBER(MATCH($E49,'ST Enroll Export'!$B$2:$B$3230,0)),"SID Match","No ST Match")) -> NYSSIS Match | U49: =IF(ISNUMBER(MATCH($D49,Disability!$B$2:$B$5962,0)),"SPED","Gen Ed") -> Gen Ed
A50: Southside 291462 | B50: 46174 | C50: southside_291462_unified-roster.xlsx | D50: 9265754471 | E50: 200031166 | F50: Perdomo | G50: Adelina | H50: 7 | I50: 41281 | J50: Southside Academy Charter School | K50: 45903 | M50: 1 | N50: Good | O50: 0 | P50: Gen Ed | Q50: =IFERROR(INDEX('ST Enroll Export'!$A$2:$A$3230,MATCH($D50,'ST Enroll Export'!$A$2:$A$3230,0)),IFERROR(IF(INDEX('ST Enroll Export'!$A$2:$A$3230,MATCH($E50,'ST Enroll Export'!$B$2:$B$3230,0))="","",INDEX('ST Enroll Export'!$A$2:$A$3230,MATCH($E50,'ST Enroll Export'!$B$2:$B$3230,0))),"Not Found")) -> 9265754471 | R50: =IFERROR(INDEX('ST Enroll Export'!$G$2:$G$3230,MATCH($D50,'ST Enroll Export'!$A$2:$A$3230,0)),IFERROR(INDEX('ST Enroll Export'!$G$2:$G$3230,MATCH($E50,'ST Enroll Export'!$B$2:$B$3230,0)),"Not Found")) -> Southside Academy Charter School | S50: =IFERROR(INDEX('ST Enroll Export'!$B$2:$B$3230,MATCH($D50,'ST Enroll Export'!$A$2:$A$3230,0)),IFERROR(INDEX('ST Enroll Export'!$B$2:$B$3230,MATCH($E50,'ST Enroll Export'!$B$2:$B$3230,0)),"Not Found")) -> 200031166 | T50: =IF(ISNUMBER(MATCH($D50,'ST Enroll Export'!$A$2:$A$3230,0)),"NYSSIS Match",IF(ISNUMBER(MATCH($E50,'ST Enroll Export'!$B$2:$B$3230,0)),"SID Match","No ST Match")) -> NYSSIS Match | U50: =IF(ISNUMBER(MATCH($D50,Disability!$B$2:$B$5962,0)),"SPED","Gen Ed") -> Gen Ed
A51: Southside 291462 | B51: 46174 | C51: southside_291462_unified-roster.xlsx | D51: 2349311626 | E51: 200026850 | F51: Mann | G51: Adonis | H51: 8 | I51: 40622 | J51: Southside Academy Charter School | K51: 45903 | M51: 1 | N51: Good | O51: 0 | P51: SPED | Q51: =IFERROR(INDEX('ST Enroll Export'!$A$2:$A$3230,MATCH($D51,'ST Enroll Export'!$A$2:$A$3230,0)),IFERROR(IF(INDEX('ST Enroll Export'!$A$2:$A$3230,MATCH($E51,'ST Enroll Export'!$B$2:$B$3230,0))="","",INDEX('ST Enroll Export'!$A$2:$A$3230,MATCH($E51,'ST Enroll Export'!$B$2:$B$3230,0))),"Not Found")) -> 2349311626 | R51: =IFERROR(INDEX('ST Enroll Export'!$G$2:$G$3230,MATCH($D51,'ST Enroll Export'!$A$2:$A$3230,0)),IFERROR(INDEX('ST Enroll Export'!$G$2:$G$3230,MATCH($E51,'ST Enroll Export'!$B$2:$B$3230,0)),"Not Found")) -> Southside Academy Charter School | S51: =IFERROR(INDEX('ST Enroll Export'!$B$2:$B$3230,MATCH($D51,'ST Enroll Export'!$A$2:$A$3230,0)),IFERROR(INDEX('ST Enroll Export'!$B$2:$B$3230,MATCH($E51,'ST Enroll Export'!$B$2:$B$3230,0)),"Not Found")) -> 200026850 | T51: =IF(ISNUMBER(MATCH($D51,'ST Enroll Export'!$A$2:$A$3230,0)),"NYSSIS Match",IF(ISNUMBER(MATCH($E51,'ST Enroll Export'!$B$2:$B$3230,0)),"SID Match","No ST Match")) -> NYSSIS Match | U51: =IF(ISNUMBER(MATCH($D51,Disability!$B$2:$B$5962,0)),"SPED","Gen Ed") -> SPED
A52: Southside 291462 | B52: 46174 | C52: southside_291462_unified-roster.xlsx | D52: 6920438320 | E52: 210005255 | F52: Smith | G52: Adoriannah | H52: 6 | I52: 41864 | J52: Southside Academy Charter School | K52: 45908 | M52: 0.975 | N52: Good | O52: 0 | P52: Gen Ed | Q52: =IFERROR(INDEX('ST Enroll Export'!$A$2:$A$3230,MATCH($D52,'ST Enroll Export'!$A$2:$A$3230,0)),IFERROR(IF(INDEX('ST Enroll Export'!$A$2:$A$3230,MATCH($E52,'ST Enroll Export'!$B$2:$B$3230,0))="","",INDEX('ST Enroll Export'!$A$2:$A$3230,MATCH($E52,'ST Enroll Export'!$B$2:$B$3230,0))),"Not Found")) -> 6920438320 | R52: =IFERROR(INDEX('ST Enroll Export'!$G$2:$G$3230,MATCH($D52,'ST Enroll Export'!$A$2:$A$3230,0)),IFERROR(INDEX('ST Enroll Export'!$G$2:$G$3230,MATCH($E52,'ST Enroll Export'!$B$2:$B$3230,0)),"Not Found")) -> Southside Academy Charter School | S52: =IFERROR(INDEX('ST Enroll Export'!$B$2:$B$3230,MATCH($D52,'ST Enroll Export'!$A$2:$A$3230,0)),IFERROR(INDEX('ST Enroll Export'!$B$2:$B$3230,MATCH($E52,'ST Enroll Export'!$B$2:$B$3230,0)),"Not Found")) -> 210005255 | T52: =IF(ISNUMBER(MATCH($D52,'ST Enroll Export'!$A$2:$A$3230,0)),"NYSSIS Match",IF(ISNUMBER(MATCH($E52,'ST Enroll Export'!$B$2:$B$3230,0)),"SID Match","No ST Match")) -> NYSSIS Match | U52: =IF(ISNUMBER(MATCH($D52,Disability!$B$2:$B$5962,0)),"SPED","Gen Ed") -> Gen Ed
A53: Southside 291462 | B53: 46174 | C53: southside_291462_unified-roster.xlsx | D53: 2859324671 | E53: 200030533 | F53: Harris | G53: Adrayla | H53: 8 | I53: 41151 | J53: Southside Academy Charter School | K53: 45903 | M53: 1 | N53: Good | O53: 0 | P53: Gen Ed | Q53: =IFERROR(INDEX('ST Enroll Export'!$A$2:$A$3230,MATCH($D53,'ST Enroll Export'!$A$2:$A$3230,0)),IFERROR(IF(INDEX('ST Enroll Export'!$A$2:$A$3230,MATCH($E53,'ST Enroll Export'!$B$2:$B$3230,0))="","",INDEX('ST Enroll Export'!$A$2:$A$3230,MATCH($E53,'ST Enroll Export'!$B$2:$B$3230,0))),"Not Found")) -> 2859324671 | R53: =IFERROR(INDEX('ST Enroll Export'!$G$2:$G$3230,MATCH($D53,'ST Enroll Export'!$A$2:$A$3230,0)),IFERROR(INDEX('ST Enroll Export'!$G$2:$G$3230,MATCH($E53,'ST Enroll Export'!$B$2:$B$3230,0)),"Not Found")) -> Southside Academy Charter School | S53: =IFERROR(INDEX('ST Enroll Export'!$B$2:$B$3230,MATCH($D53,'ST Enroll Export'!$A$2:$A$3230,0)),IFERROR(INDEX('ST Enroll Export'!$B$2:$B$3230,MATCH($E53,'ST Enroll Export'!$B$2:$B$3230,0)),"Not Found")) -> 200030533 | T53: =IF(ISNUMBER(MATCH($D53,'ST Enroll Export'!$A$2:$A$3230,0)),"NYSSIS Match",IF(ISNUMBER(MATCH($E53,'ST Enroll Export'!$B$2:$B$3230,0)),"SID Match","No ST Match")) -> NYSSIS Match | U53: =IF(ISNUMBER(MATCH($D53,Disability!$B$2:$B$5962,0)),"SPED","Gen Ed") -> Gen Ed
A54: Southside 291462 | B54: 46174 | C54: southside_291462_unified-roster.xlsx | D54: 9004836816 | E54: 210007545 | F54: Rowland | G54: Adrianna | H54: 8 | I54: 40934 | J54: Southside Academy Charter School | K54: 45903 | M54: 1 | N54: Good | O54: 0 | P54: Gen Ed | Q54: =IFERROR(INDEX('ST Enroll Export'!$A$2:$A$3230,MATCH($D54,'ST Enroll Export'!$A$2:$A$3230,0)),IFERROR(IF(INDEX('ST Enroll Export'!$A$2:$A$3230,MATCH($E54,'ST Enroll Export'!$B$2:$B$3230,0))="","",INDEX('ST Enroll Export'!$A$2:$A$3230,MATCH($E54,'ST Enroll Export'!$B$2:$B$3230,0))),"Not Found")) -> 9004836816 | R54: =IFERROR(INDEX('ST Enroll Export'!$G$2:$G$3230,MATCH($D54,'ST Enroll Export'!$A$2:$A$3230,0)),IFERROR(INDEX('ST Enroll Export'!$G$2:$G$3230,MATCH($E54,'ST Enroll Export'!$B$2:$B$3230,0)),"Not Found")) -> Southside Academy Charter School | S54: =IFERROR(INDEX('ST Enroll Export'!$B$2:$B$3230,MATCH($D54,'ST Enroll Export'!$A$2:$A$3230,0)),IFERROR(INDEX('ST Enroll Export'!$B$2:$B$3230,MATCH($E54,'ST Enroll Export'!$B$2:$B$3230,0)),"Not Found")) -> 210007545 | T54: =IF(ISNUMBER(MATCH($D54,'ST Enroll Export'!$A$2:$A$3230,0)),"NYSSIS Match",IF(ISNUMBER(MATCH($E54,'ST Enroll Export'!$B$2:$B$3230,0)),"SID Match","No ST Match")) -> NYSSIS Match | U54: =IF(ISNUMBER(MATCH($D54,Disability!$B$2:$B$5962,0)),"SPED","Gen Ed") -> Gen Ed
A55: Southside 291462 | B55: 46174 | C55: southside_291462_unified-roster.xlsx | D55: 4798198643 | E55: 210011819 | F55: Davis | G55: A-Drianna | H55: 1 | I55: 43589 | J55: Southside Academy Charter School | K55: 45903 | M55: 1 | N55: Good | O55: 0 | P55: Gen Ed | Q55: =IFERROR(INDEX('ST Enroll Export'!$A$2:$A$3230,MATCH($D55,'ST Enroll Export'!$A$2:$A$3230,0)),IFERROR(IF(INDEX('ST Enroll Export'!$A$2:$A$3230,MATCH($E55,'ST Enroll Export'!$B$2:$B$3230,0))="","",INDEX('ST Enroll Export'!$A$2:$A$3230,MATCH($E55,'ST Enroll Export'!$B$2:$B$3230,0))),"Not Found")) -> 4798198643 | R55: =IFERROR(INDEX('ST Enroll Export'!$G$2:$G$3230,MATCH($D55,'ST Enroll Export'!$A$2:$A$3230,0)),IFERROR(INDEX('ST Enroll Export'!$G$2:$G$3230,MATCH($E55,'ST Enroll Export'!$B$2:$B$3230,0)),"Not Found")) -> Southside Academy Charter School | S55: =IFERROR(INDEX('ST Enroll Export'!$B$2:$B$3230,MATCH($D55,'ST Enroll Export'!$A$2:$A$3230,0)),IFERROR(INDEX('ST Enroll Export'!$B$2:$B$3230,MATCH($E55,'ST Enroll Export'!$B$2:$B$3230,0)),"Not Found")) -> 210011819 | T55: =IF(ISNUMBER(MATCH($D55,'ST Enroll Export'!$A$2:$A$3230,0)),"NYSSIS Match",IF(ISNUMBER(MATCH($E55,'ST Enroll Export'!$B$2:$B$3230,0)),"SID Match","No ST Match")) -> NYSSIS Match | U55: =IF(ISNUMBER(MATCH($D55,Disability!$B$2:$B$5962,0)),"SPED","Gen Ed") -> Gen Ed
A56: Southside 291462 | B56: 46174 | C56: southside_291462_unified-roster.xlsx | D56: 5716749290 | E56: 200038876 | F56: Green-Hayward | G56: AdriElla | H56: 6 | I56: 41861 | J56: Southside Academy Charter School | K56: 45903 | M56: 1 | N56: Good | O56: 0 | P56: Gen Ed | Q56: =IFERROR(INDEX('ST Enroll Export'!$A$2:$A$3230,MATCH($D56,'ST Enroll Export'!$A$2:$A$3230,0)),IFERROR(IF(INDEX('ST Enroll Export'!$A$2:$A$3230,MATCH($E56,'ST Enroll Export'!$B$2:$B$3230,0))="","",INDEX('ST Enroll Export'!$A$2:$A$3230,MATCH($E56,'ST Enroll Export'!$B$2:$B$3230,0))),"Not Found")) -> 5716749290 | R56: =IFERROR(INDEX('ST Enroll Export'!$G$2:$G$3230,MATCH($D56,'ST Enroll Export'!$A$2:$A$3230,0)),IFERROR(INDEX('ST Enroll Export'!$G$2:$G$3230,MATCH($E56,'ST Enroll Export'!$B$2:$B$3230,0)),"Not Found")) -> Southside Academy Charter School | S56: =IFERROR(INDEX('ST Enroll Export'!$B$2:$B$3230,MATCH($D56,'ST Enroll Export'!$A$2:$A$3230,0)),IFERROR(INDEX('ST Enroll Export'!$B$2:$B$3230,MATCH($E56,'ST Enroll Export'!$B$2:$B$3230,0)),"Not Found")) -> 200038876 | T56: =IF(ISNUMBER(MATCH($D56,'ST Enroll Export'!$A$2:$A$3230,0)),"NYSSIS Match",IF(ISNUMBER(MATCH($E56,'ST Enroll Export'!$B$2:$B$3230,0)),"SID Match","No ST Match")) -> NYSSIS Match | U56: =IF(ISNUMBER(MATCH($D56,Disability!$B$2:$B$5962,0)),"SPED","Gen Ed") -> Gen Ed
A57: Southside 291462 | B57: 46174 | C57: southside_291462_unified-roster.xlsx | D57: 9816245530 | E57: 210016421 | F57: Timori | G57: Ahmad | H57: 5 | I57: 41917 | J57: Southside Academy Charter School | K57: 45903 | M57: 1 | N57: Good | O57: 0 | P57: Gen Ed | Q57: =IFERROR(INDEX('ST Enroll Export'!$A$2:$A$3230,MATCH($D57,'ST Enroll Export'!$A$2:$A$3230,0)),IFERROR(IF(INDEX('ST Enroll Export'!$A$2:$A$3230,MATCH($E57,'ST Enroll Export'!$B$2:$B$3230,0))="","",INDEX('ST Enroll Export'!$A$2:$A$3230,MATCH($E57,'ST Enroll Export'!$B$2:$B$3230,0))),"Not Found")) -> 9816245530 | R57: =IFERROR(INDEX('ST Enroll Export'!$G$2:$G$3230,MATCH($D57,'ST Enroll Export'!$A$2:$A$3230,0)),IFERROR(INDEX('ST Enroll Export'!$G$2:$G$3230,MATCH($E57,'ST Enroll Export'!$B$2:$B$3230,0)),"Not Found")) -> Southside Academy Charter School | S57: =IFERROR(INDEX('ST Enroll Export'!$B$2:$B$3230,MATCH($D57,'ST Enroll Export'!$A$2:$A$3230,0)),IFERROR(INDEX('ST Enroll Export'!$B$2:$B$3230,MATCH($E57,'ST Enroll Export'!$B$2:$B$3230,0)),"Not Found")) -> 210016421 | T57: =IF(ISNUMBER(MATCH($D57,'ST Enroll Export'!$A$2:$A$3230,0)),"NYSSIS Match",IF(ISNUMBER(MATCH($E57,'ST Enroll Export'!$B$2:$B$3230,0)),"SID Match","No ST Match")) -> NYSSIS Match | U57: =IF(ISNUMBER(MATCH($D57,Disability!$B$2:$B$5962,0)),"SPED","Gen Ed") -> Gen Ed
A58: Southside 291462 | B58: 46174 | C58: southside_291462_unified-roster.xlsx | D58: 9112250374 | E58: 210004384 | F58: Capers | G58: Aiden | H58: 4 | I58: 42418 | J58: Southside Academy Charter School | K58: 45903 | M58: 1 | N58: Good | O58: 0 | P58: Gen Ed | Q58: =IFERROR(INDEX('ST Enroll Export'!$A$2:$A$3230,MATCH($D58,'ST Enroll Export'!$A$2:$A$3230,0)),IFERROR(IF(INDEX('ST Enroll Export'!$A$2:$A$3230,MATCH($E58,'ST Enroll Export'!$B$2:$B$3230,0))="","",INDEX('ST Enroll Export'!$A$2:$A$3230,MATCH($E58,'ST Enroll Export'!$B$2:$B$3230,0))),"Not Found")) -> 9112250374 | R58: =IFERROR(INDEX('ST Enroll Export'!$G$2:$G$3230,MATCH($D58,'ST Enroll Export'!$A$2:$A$3230,0)),IFERROR(INDEX('ST Enroll Export'!$G$2:$G$3230,MATCH($E58,'ST Enroll Export'!$B$2:$B$3230,0)),"Not Found")) -> Southside Academy Charter School | S58: =IFERROR(INDEX('ST Enroll Export'!$B$2:$B$3230,MATCH($D58,'ST Enroll Export'!$A$2:$A$3230,0)),IFERROR(INDEX('ST Enroll Export'!$B$2:$B$3230,MATCH($E58,'ST Enroll Export'!$B$2:$B$3230,0)),"Not Found")) -> 210004384 | T58: =IF(ISNUMBER(MATCH($D58,'ST Enroll Export'!$A$2:$A$3230,0)),"NYSSIS Match",IF(ISNUMBER(MATCH($E58,'ST Enroll Export'!$B$2:$B$3230,0)),"SID Match","No ST Match")) -> NYSSIS Match | U58: =IF(ISNUMBER(MATCH($D58,Disability!$B$2:$B$5962,0)),"SPED","Gen Ed") -> Gen Ed
A59: Southside 291462 | B59: 46174 | C59: southside_291462_unified-roster.xlsx | D59: 5308675136 | E59: 210017359 | F59: Akot | G59: Akot | H59: K | I59: 44049 | J59: Southside Academy Charter School | K59: 45903 | L59: 46052 | M59: 0.5 | N59: Good | O59: 0 | P59: Gen Ed | Q59: =IFERROR(INDEX('ST Enroll Export'!$A$2:$A$3230,MATCH($D59,'ST Enroll Export'!$A$2:$A$3230,0)),IFERROR(IF(INDEX('ST Enroll Export'!$A$2:$A$3230,MATCH($E59,'ST Enroll Export'!$B$2:$B$3230,0))="","",INDEX('ST Enroll Export'!$A$2:$A$3230,MATCH($E59,'ST Enroll Export'!$B$2:$B$3230,0))),"Not Found")) -> 5308675136 | R59: =IFERROR(INDEX('ST Enroll Export'!$G$2:$G$3230,MATCH($D59,'ST Enroll Export'!$A$2:$A$3230,0)),IFERROR(INDEX('ST Enroll Export'!$G$2:$G$3230,MATCH($E59,'ST Enroll Export'!$B$2:$B$3230,0)),"Not Found")) -> Citizenship & Science Academy of Syracuse Charter | S59: =IFERROR(INDEX('ST Enroll Export'!$B$2:$B$3230,MATCH($D59,'ST Enroll Export'!$A$2:$A$3230,0)),IFERROR(INDEX('ST Enroll Export'!$B$2:$B$3230,MATCH($E59,'ST Enroll Export'!$B$2:$B$3230,0)),"Not Found")) -> 210017359 | T59: =IF(ISNUMBER(MATCH($D59,'ST Enroll Export'!$A$2:$A$3230,0)),"NYSSIS Match",IF(ISNUMBER(MATCH($E59,'ST Enroll Export'!$B$2:$B$3230,0)),"SID Match","No ST Match")) -> NYSSIS Match | U59: =IF(ISNUMBER(MATCH($D59,Disability!$B$2:$B$5962,0)),"SPED","Gen Ed") -> Gen Ed
A60: Southside 291462 | B60: 46174 | C60: southside_291462_unified-roster.xlsx | D60: 6862971750 | E60: 200030599 | F60: Kodet | G60: Alana | H60: 7 | I60: 41500 | J60: Southside Academy Charter School | K60: 45903 | M60: 1 | N60: Good | O60: 0 | P60: Gen Ed | Q60: =IFERROR(INDEX('ST Enroll Export'!$A$2:$A$3230,MATCH($D60,'ST Enroll Export'!$A$2:$A$3230,0)),IFERROR(IF(INDEX('ST Enroll Export'!$A$2:$A$3230,MATCH($E60,'ST Enroll Export'!$B$2:$B$3230,0))="","",INDEX('ST Enroll Export'!$A$2:$A$3230,MATCH($E60,'ST Enroll Export'!$B$2:$B$3230,0))),"Not Found")) -> 6862971750 | R60: =IFERROR(INDEX('ST Enroll Export'!$G$2:$G$3230,MATCH($D60,'ST Enroll Export'!$A$2:$A$3230,0)),IFERROR(INDEX('ST Enroll Export'!$G$2:$G$3230,MATCH($E60,'ST Enroll Export'!$B$2:$B$3230,0)),"Not Found")) -> Southside Academy Charter School | S60: =IFERROR(INDEX('ST Enroll Export'!$B$2:$B$3230,MATCH($D60,'ST Enroll Export'!$A$2:$A$3230,0)),IFERROR(INDEX('ST Enroll Export'!$B$2:$B$3230,MATCH($E60,'ST Enroll Export'!$B$2:$B$3230,0)),"Not Found")) -> 200030599 | T60: =IF(ISNUMBER(MATCH($D60,'ST Enroll Export'!$A$2:$A$3230,0)),"NYSSIS Match",IF(ISNUMBER(MATCH($E60,'ST Enroll Export'!$B$2:$B$3230,0)),"SID Match","No ST Match")) -> NYSSIS Match | U60: =IF(ISNUMBER(MATCH($D60,Disability!$B$2:$B$5962,0)),"SPED","Gen Ed") -> Gen Ed
A61: Southside 291462 | B61: 46174 | C61: southside_291462_unified-roster.xlsx | D61: 1012369440 | E61: 210004998 | F61: Salem | G61: Alanna | H61: 4 | I61: 42475 | J61: Southside Academy Charter School | K61: 45903 | M61: 1 | N61: Good | O61: 0 | P61: Gen Ed | Q61: =IFERROR(INDEX('ST Enroll Export'!$A$2:$A$3230,MATCH($D61,'ST Enroll Export'!$A$2:$A$3230,0)),IFERROR(IF(INDEX('ST Enroll Export'!$A$2:$A$3230,MATCH($E61,'ST Enroll Export'!$B$2:$B$3230,0))="","",INDEX('ST Enroll Export'!$A$2:$A$3230,MATCH($E61,'ST Enroll Export'!$B$2:$B$3230,0))),"Not Found")) -> 1012369440 | R61: =IFERROR(INDEX('ST Enroll Export'!$G$2:$G$3230,MATCH($D61,'ST Enroll Export'!$A$2:$A$3230,0)),IFERROR(INDEX('ST Enroll Export'!$G$2:$G$3230,MATCH($E61,'ST Enroll Export'!$B$2:$B$3230,0)),"Not Found")) -> Southside Academy Charter School | S61: =IFERROR(INDEX('ST Enroll Export'!$B$2:$B$3230,MATCH($D61,'ST Enroll Export'!$A$2:$A$3230,0)),IFERROR(INDEX('ST Enroll Export'!$B$2:$B$3230,MATCH($E61,'ST Enroll Export'!$B$2:$B$3230,0)),"Not Found")) -> 210004998 | T61: =IF(ISNUMBER(MATCH($D61,'ST Enroll Export'!$A$2:$A$3230,0)),"NYSSIS Match",IF(ISNUMBER(MATCH($E61,'ST Enroll Export'!$B$2:$B$3230,0)),"SID Match","No ST Match")) -> NYSSIS Match | U61: =IF(ISNUMBER(MATCH($D61,Disability!$B$2:$B$5962,0)),"SPED","Gen Ed") -> Gen Ed
A62: Southside 291462 | B62: 46174 | C62: southside_291462_unified-roster.xlsx | D62: 4003684191 | E62: 200038430 | F62: Tillie | G62: Alayiah | H62: 4 | I62: 42281 | J62: Southside Academy Charter School | K62: 45903 | M62: 1 | N62: Good | O62: 0 | P62: SPED | Q62: =IFERROR(INDEX('ST Enroll Export'!$A$2:$A$3230,MATCH($D62,'ST Enroll Export'!$A$2:$A$3230,0)),IFERROR(IF(INDEX('ST Enroll Export'!$A$2:$A$3230,MATCH($E62,'ST Enroll Export'!$B$2:$B$3230,0))="","",INDEX('ST Enroll Export'!$A$2:$A$3230,MATCH($E62,'ST Enroll Export'!$B$2:$B$3230,0))),"Not Found")) -> 4003684191 | R62: =IFERROR(INDEX('ST Enroll Export'!$G$2:$G$3230,MATCH($D62,'ST Enroll Export'!$A$2:$A$3230,0)),IFERROR(INDEX('ST Enroll Export'!$G$2:$G$3230,MATCH($E62,'ST Enroll Export'!$B$2:$B$3230,0)),"Not Found")) -> Southside Academy Charter School | S62: =IFERROR(INDEX('ST Enroll Export'!$B$2:$B$3230,MATCH($D62,'ST Enroll Export'!$A$2:$A$3230,0)),IFERROR(INDEX('ST Enroll Export'!$B$2:$B$3230,MATCH($E62,'ST Enroll Export'!$B$2:$B$3230,0)),"Not Found")) -> 200038430 | T62: =IF(ISNUMBER(MATCH($D62,'ST Enroll Export'!$A$2:$A$3230,0)),"NYSSIS Match",IF(ISNUMBER(MATCH($E62,'ST Enroll Export'!$B$2:$B$3230,0)),"SID Match","No ST Match")) -> NYSSIS Match | U62: =IF(ISNUMBER(MATCH($D62,Disability!$B$2:$B$5962,0)),"SPED","Gen Ed") -> SPED
A63: Southside 291462 | B63: 46174 | C63: southside_291462_unified-roster.xlsx | D63: 8037443260 | E63: 210012357 | F63: Allan Jr | G63: Alexander | H63: 3 | I63: 42781 | J63: Southside Academy Charter School | K63: 45918 | M63: 0.925 | N63: Good | O63: 0 | P63: SPED | Q63: =IFERROR(INDEX('ST Enroll Export'!$A$2:$A$3230,MATCH($D63,'ST Enroll Export'!$A$2:$A$3230,0)),IFERROR(IF(INDEX('ST Enroll Export'!$A$2:$A$3230,MATCH($E63,'ST Enroll Export'!$B$2:$B$3230,0))="","",INDEX('ST Enroll Export'!$A$2:$A$3230,MATCH($E63,'ST Enroll Export'!$B$2:$B$3230,0))),"Not Found")) -> 8037443260 | R63: =IFERROR(INDEX('ST Enroll Export'!$G$2:$G$3230,MATCH($D63,'ST Enroll Export'!$A$2:$A$3230,0)),IFERROR(INDEX('ST Enroll Export'!$G$2:$G$3230,MATCH($E63,'ST Enroll Export'!$B$2:$B$3230,0)),"Not Found")) -> Southside Academy Charter School | S63: =IFERROR(INDEX('ST Enroll Export'!$B$2:$B$3230,MATCH($D63,'ST Enroll Export'!$A$2:$A$3230,0)),IFERROR(INDEX('ST Enroll Export'!$B$2:$B$3230,MATCH($E63,'ST Enroll Export'!$B$2:$B$3230,0)),"Not Found")) -> 210012357 | T63: =IF(ISNUMBER(MATCH($D63,'ST Enroll Export'!$A$2:$A$3230,0)),"NYSSIS Match",IF(ISNUMBER(MATCH($E63,'ST Enroll Export'!$B$2:$B$3230,0)),"SID Match","No ST Match")) -> NYSSIS Match | U63: =IF(ISNUMBER(MATCH($D63,Disability!$B$2:$B$5962,0)),"SPED","Gen Ed") -> SPED
A64: Southside 291462 | B64: 46174 | C64: southside_291462_unified-roster.xlsx | D64: 1757340380 | E64: 210005851 | F64: May | G64: Alina | H64: 2 | I64: 43109 | J64: Southside Academy Charter School | K64: 45903 | M64: 1 | N64: Good | O64: 0 | P64: SPED | Q64: =IFERROR(INDEX('ST Enroll Export'!$A$2:$A$3230,MATCH($D64,'ST Enroll Export'!$A$2:$A$3230,0)),IFERROR(IF(INDEX('ST Enroll Export'!$A$2:$A$3230,MATCH($E64,'ST Enroll Export'!$B$2:$B$3230,0))="","",INDEX('ST Enroll Export'!$A$2:$A$3230,MATCH($E64,'ST Enroll Export'!$B$2:$B$3230,0))),"Not Found")) -> 1757340380 | R64: =IFERROR(INDEX('ST Enroll Export'!$G$2:$G$3230,MATCH($D64,'ST Enroll Export'!$A$2:$A$3230,0)),IFERROR(INDEX('ST Enroll Export'!$G$2:$G$3230,MATCH($E64,'ST Enroll Export'!$B$2:$B$3230,0)),"Not Found")) -> Southside Academy Charter School | S64: =IFERROR(INDEX('ST Enroll Export'!$B$2:$B$3230,MATCH($D64,'ST Enroll Export'!$A$2:$A$3230,0)),IFERROR(INDEX('ST Enroll Export'!$B$2:$B$3230,MATCH($E64,'ST Enroll Export'!$B$2:$B$3230,0)),"Not Found")) -> 210005851 | T64: =IF(ISNUMBER(MATCH($D64,'ST Enroll Export'!$A$2:$A$3230,0)),"NYSSIS Match",IF(ISNUMBER(MATCH($E64,'ST Enroll Export'!$B$2:$B$3230,0)),"SID Match","No ST Match")) -> NYSSIS Match | U64: =IF(ISNUMBER(MATCH($D64,Disability!$B$2:$B$5962,0)),"SPED","Gen Ed") -> SPED
A65: Southside 291462 | B65: 46174 | C65: southside_291462_unified-roster.xlsx | D65: 9247943203 | E65: 200032807 | F65: Aiken | G65: Aliya | H65: 8 | I65: 41174 | J65: Southside Academy Charter School | K65: 45903 | M65: 1 | N65: Good | O65: 0 | P65: Gen Ed | Q65: =IFERROR(INDEX('ST Enroll Export'!$A$2:$A$3230,MATCH($D65,'ST Enroll Export'!$A$2:$A$3230,0)),IFERROR(IF(INDEX('ST Enroll Export'!$A$2:$A$3230,MATCH($E65,'ST Enroll Export'!$B$2:$B$3230,0))="","",INDEX('ST Enroll Export'!$A$2:$A$3230,MATCH($E65,'ST Enroll Export'!$B$2:$B$3230,0))),"Not Found")) -> 9247943203 | R65: =IFERROR(INDEX('ST Enroll Export'!$G$2:$G$3230,MATCH($D65,'ST Enroll Export'!$A$2:$A$3230,0)),IFERROR(INDEX('ST Enroll Export'!$G$2:$G$3230,MATCH($E65,'ST Enroll Export'!$B$2:$B$3230,0)),"Not Found")) -> Southside Academy Charter School | S65: =IFERROR(INDEX('ST Enroll Export'!$B$2:$B$3230,MATCH($D65,'ST Enroll Export'!$A$2:$A$3230,0)),IFERROR(INDEX('ST Enroll Export'!$B$2:$B$3230,MATCH($E65,'ST Enroll Export'!$B$2:$B$3230,0)),"Not Found")) -> 200032807 | T65: =IF(ISNUMBER(MATCH($D65,'ST Enroll Export'!$A$2:$A$3230,0)),"NYSSIS Match",IF(ISNUMBER(MATCH($E65,'ST Enroll Export'!$B$2:$B$3230,0)),"SID Match","No ST Match")) -> NYSSIS Match | U65: =IF(ISNUMBER(MATCH($D65,Disability!$B$2:$B$5962,0)),"SPED","Gen Ed") -> Gen Ed
A66: Southside 291462 | B66: 46174 | C66: southside_291462_unified-roster.xlsx | D66: 2018797941 | E66: 200037650 | F66: Blunt | G66: Aliyah | H66: 5 | I66: 42094 | J66: Southside Academy Charter School | K66: 45903 | M66: 1 | N66: Good | O66: 0 | P66: Gen Ed | Q66: =IFERROR(INDEX('ST Enroll Export'!$A$2:$A$3230,MATCH($D66,'ST Enroll Export'!$A$2:$A$3230,0)),IFERROR(IF(INDEX('ST Enroll Export'!$A$2:$A$3230,MATCH($E66,'ST Enroll Export'!$B$2:$B$3230,0))="","",INDEX('ST Enroll Export'!$A$2:$A$3230,MATCH($E66,'ST Enroll Export'!$B$2:$B$3230,0))),"Not Found")) -> 2018797941 | R66: =IFERROR(INDEX('ST Enroll Export'!$G$2:$G$3230,MATCH($D66,'ST Enroll Export'!$A$2:$A$3230,0)),IFERROR(INDEX('ST Enroll Export'!$G$2:$G$3230,MATCH($E66,'ST Enroll Export'!$B$2:$B$3230,0)),"Not Found")) -> Southside Academy Charter School | S66: =IFERROR(INDEX('ST Enroll Export'!$B$2:$B$3230,MATCH($D66,'ST Enroll Export'!$A$2:$A$3230,0)),IFERROR(INDEX('ST Enroll Export'!$B$2:$B$3230,MATCH($E66,'ST Enroll Export'!$B$2:$B$3230,0)),"Not Found")) -> 200037650 | T66: =IF(ISNUMBER(MATCH($D66,'ST Enroll Export'!$A$2:$A$3230,0)),"NYSSIS Match",IF(ISNUMBER(MATCH($E66,'ST Enroll Export'!$B$2:$B$3230,0)),"SID Match","No ST Match")) -> NYSSIS Match | U66: =IF(ISNUMBER(MATCH($D66,Disability!$B$2:$B$5962,0)),"SPED","Gen Ed") -> Gen Ed
A67: Southside 291462 | B67: 46174 | C67: southside_291462_unified-roster.xlsx | D67: 7271659280 | E67: 200038218 | F67: Smith | G67: Allanna | H67: 6 | I67: 41726 | J67: Southside Academy Charter School | K67: 45903 | L67: 46059 | M67: 0.525 | N67: Good | O67: 0 | P67: Gen Ed | Q67: =IFERROR(INDEX('ST Enroll Export'!$A$2:$A$3230,MATCH($D67,'ST Enroll Export'!$A$2:$A$3230,0)),IFERROR(IF(INDEX('ST Enroll Export'!$A$2:$A$3230,MATCH($E67,'ST Enroll Export'!$B$2:$B$3230,0))="","",INDEX('ST Enroll Export'!$A$2:$A$3230,MATCH($E67,'ST Enroll Export'!$B$2:$B$3230,0))),"Not Found")) -> 7271659280 | R67: =IFERROR(INDEX('ST Enroll Export'!$G$2:$G$3230,MATCH($D67,'ST Enroll Export'!$A$2:$A$3230,0)),IFERROR(INDEX('ST Enroll Export'!$G$2:$G$3230,MATCH($E67,'ST Enroll Export'!$B$2:$B$3230,0)),"Not Found")) -> Southside Academy Charter School | S67: =IFERROR(INDEX('ST Enroll Export'!$B$2:$B$3230,MATCH($D67,'ST Enroll Export'!$A$2:$A$3230,0)),IFERROR(INDEX('ST Enroll Export'!$B$2:$B$3230,MATCH($E67,'ST Enroll Export'!$B$2:$B$3230,0)),"Not Found")) -> 200038218 | T67: =IF(ISNUMBER(MATCH($D67,'ST Enroll Export'!$A$2:$A$3230,0)),"NYSSIS Match",IF(ISNUMBER(MATCH($E67,'ST Enroll Export'!$B$2:$B$3230,0)),"SID Match","No ST Match")) -> NYSSIS Match | U67: =IF(ISNUMBER(MATCH($D67,Disability!$B$2:$B$5962,0)),"SPED","Gen Ed") -> Gen Ed
A68: Southside 291462 | B68: 46174 | C68: southside_291462_unified-roster.xlsx | D68: 200029382 | E68: 200029382 | F68: Colon | G68: Alyani | H68: 8 | I68: 40559 | J68: Southside Academy Charter School | K68: 45903 | M68: 1 | N68: Good | O68: 0 | P68: Gen Ed | Q68: =IFERROR(INDEX('ST Enroll Export'!$A$2:$A$3230,MATCH($D68,'ST Enroll Export'!$A$2:$A$3230,0)),IFERROR(IF(INDEX('ST Enroll Export'!$A$2:$A$3230,MATCH($E68,'ST Enroll Export'!$B$2:$B$3230,0))="","",INDEX('ST Enroll Export'!$A$2:$A$3230,MATCH($E68,'ST Enroll Export'!$B$2:$B$3230,0))),"Not Found")) -> 7161763382 | R68: =IFERROR(INDEX('ST Enroll Export'!$G$2:$G$3230,MATCH($D68,'ST Enroll Export'!$A$2:$A$3230,0)),IFERROR(INDEX('ST Enroll Export'!$G$2:$G$3230,MATCH($E68,'ST Enroll Export'!$B$2:$B$3230,0)),"Not Found")) -> Southside Academy Charter School | S68: =IFERROR(INDEX('ST Enroll Export'!$B$2:$B$3230,MATCH($D68,'ST Enroll Export'!$A$2:$A$3230,0)),IFERROR(INDEX('ST Enroll Export'!$B$2:$B$3230,MATCH($E68,'ST Enroll Export'!$B$2:$B$3230,0)),"Not Found")) -> 200029382 | T68: =IF(ISNUMBER(MATCH($D68,'ST Enroll Export'!$A$2:$A$3230,0)),"NYSSIS Match",IF(ISNUMBER(MATCH($E68,'ST Enroll Export'!$B$2:$B$3230,0)),"SID Match","No ST Match")) -> SID Match | U68: =IF(ISNUMBER(MATCH($D68,Disability!$B$2:$B$5962,0)),"SPED","Gen Ed") -> Gen Ed
A69: Southside 291462 | B69: 46174 | C69: southside_291462_unified-roster.xlsx | D69: 2799458756 | E69: 210004202 | F69: Jacobs | G69: Amara | H69: 3 | I69: 42788 | J69: Southside Academy Charter School | K69: 45909 | M69: 0.975 | N69: Good | O69: 0 | P69: Gen Ed | Q69: =IFERROR(INDEX('ST Enroll Export'!$A$2:$A$3230,MATCH($D69,'ST Enroll Export'!$A$2:$A$3230,0)),IFERROR(IF(INDEX('ST Enroll Export'!$A$2:$A$3230,MATCH($E69,'ST Enroll Export'!$B$2:$B$3230,0))="","",INDEX('ST Enroll Export'!$A$2:$A$3230,MATCH($E69,'ST Enroll Export'!$B$2:$B$3230,0))),"Not Found")) -> 2799458756 | R69: =IFERROR(INDEX('ST Enroll Export'!$G$2:$G$3230,MATCH($D69,'ST Enroll Export'!$A$2:$A$3230,0)),IFERROR(INDEX('ST Enroll Export'!$G$2:$G$3230,MATCH($E69,'ST Enroll Export'!$B$2:$B$3230,0)),"Not Found")) -> Southside Academy Charter School | S69: =IFERROR(INDEX('ST Enroll Export'!$B$2:$B$3230,MATCH($D69,'ST Enroll Export'!$A$2:$A$3230,0)),IFERROR(INDEX('ST Enroll Export'!$B$2:$B$3230,MATCH($E69,'ST Enroll Export'!$B$2:$B$3230,0)),"Not Found")) -> 210004202 | T69: =IF(ISNUMBER(MATCH($D69,'ST Enroll Export'!$A$2:$A$3230,0)),"NYSSIS Match",IF(ISNUMBER(MATCH($E69,'ST Enroll Export'!$B$2:$B$3230,0)),"SID Match","No ST Match")) -> NYSSIS Match | U69: =IF(ISNUMBER(MATCH($D69,Disability!$B$2:$B$5962,0)),"SPED","Gen Ed") -> Gen Ed
A70: Southside 291462 | B70: 46174 | C70: southside_291462_unified-roster.xlsx | D70: 3948567923 | E70: 200029630 | F70: Coston | G70: Amare | H70: 6 | I70: 41522 | J70: Southside Academy Charter School | K70: 45903 | M70: 1 | N70: Good | O70: 0 | P70: Gen Ed | Q70: =IFERROR(INDEX('ST Enroll Export'!$A$2:$A$3230,MATCH($D70,'ST Enroll Export'!$A$2:$A$3230,0)),IFERROR(IF(INDEX('ST Enroll Export'!$A$2:$A$3230,MATCH($E70,'ST Enroll Export'!$B$2:$B$3230,0))="","",INDEX('ST Enroll Export'!$A$2:$A$3230,MATCH($E70,'ST Enroll Export'!$B$2:$B$3230,0))),"Not Found")) -> 3948567923 | R70: =IFERROR(INDEX('ST Enroll Export'!$G$2:$G$3230,MATCH($D70,'ST Enroll Export'!$A$2:$A$3230,0)),IFERROR(INDEX('ST Enroll Export'!$G$2:$G$3230,MATCH($E70,'ST Enroll Export'!$B$2:$B$3230,0)),"Not Found")) -> Southside Academy Charter School | S70: =IFERROR(INDEX('ST Enroll Export'!$B$2:$B$3230,MATCH($D70,'ST Enroll Export'!$A$2:$A$3230,0)),IFERROR(INDEX('ST Enroll Export'!$B$2:$B$3230,MATCH($E70,'ST Enroll Export'!$B$2:$B$3230,0)),"Not Found")) -> 200029630 | T70: =IF(ISNUMBER(MATCH($D70,'ST Enroll Export'!$A$2:$A$3230,0)),"NYSSIS Match",IF(ISNUMBER(MATCH($E70,'ST Enroll Export'!$B$2:$B$3230,0)),"SID Match","No ST Match")) -> NYSSIS Match | U70: =IF(ISNUMBER(MATCH($D70,Disability!$B$2:$B$5962,0)),"SPED","Gen Ed") -> Gen Ed
A71: Southside 291462 | B71: 46174 | C71: southside_291462_unified-roster.xlsx | D71: 2365285906 | E71: 210004781 | F71: McFadden | G71: Amari | H71: 2 | I71: 43026 | J71: Southside Academy Charter School | K71: 45903 | M71: 1 | N71: Good | O71: 0 | P71: SPED | Q71: =IFERROR(INDEX('ST Enroll Export'!$A$2:$A$3230,MATCH($D71,'ST Enroll Export'!$A$2:$A$3230,0)),IFERROR(IF(INDEX('ST Enroll Export'!$A$2:$A$3230,MATCH($E71,'ST Enroll Export'!$B$2:$B$3230,0))="","",INDEX('ST Enroll Export'!$A$2:$A$3230,MATCH($E71,'ST Enroll Export'!$B$2:$B$3230,0))),"Not Found")) -> 2365285906 | R71: =IFERROR(INDEX('ST Enroll Export'!$G$2:$G$3230,MATCH($D71,'ST Enroll Export'!$A$2:$A$3230,0)),IFERROR(INDEX('ST Enroll Export'!$G$2:$G$3230,MATCH($E71,'ST Enroll Export'!$B$2:$B$3230,0)),"Not Found")) -> Southside Academy Charter School | S71: =IFERROR(INDEX('ST Enroll Export'!$B$2:$B$3230,MATCH($D71,'ST Enroll Export'!$A$2:$A$3230,0)),IFERROR(INDEX('ST Enroll Export'!$B$2:$B$3230,MATCH($E71,'ST Enroll Export'!$B$2:$B$3230,0)),"Not Found")) -> 210004781 | T71: =IF(ISNUMBER(MATCH($D71,'ST Enroll Export'!$A$2:$A$3230,0)),"NYSSIS Match",IF(ISNUMBER(MATCH($E71,'ST Enroll Export'!$B$2:$B$3230,0)),"SID Match","No ST Match")) -> NYSSIS Match | U71: =IF(ISNUMBER(MATCH($D71,Disability!$B$2:$B$5962,0)),"SPED","Gen Ed") -> SPED
A72: Southside 291462 | B72: 46174 | C72: southside_291462_unified-roster.xlsx | D72: 5003227753 | E72: 200037678 | F72: Vega Davila | G72: Amarilys | H72: 5 | I72: 41985 | J72: Southside Academy Charter School | K72: 45903 | M72: 1 | N72: Good | O72: 0 | P72: Gen Ed | Q72: =IFERROR(INDEX('ST Enroll Export'!$A$2:$A$3230,MATCH($D72,'ST Enroll Export'!$A$2:$A$3230,0)),IFERROR(IF(INDEX('ST Enroll Export'!$A$2:$A$3230,MATCH($E72,'ST Enroll Export'!$B$2:$B$3230,0))="","",INDEX('ST Enroll Export'!$A$2:$A$3230,MATCH($E72,'ST Enroll Export'!$B$2:$B$3230,0))),"Not Found")) -> 5003227753 | R72: =IFERROR(INDEX('ST Enroll Export'!$G$2:$G$3230,MATCH($D72,'ST Enroll Export'!$A$2:$A$3230,0)),IFERROR(INDEX('ST Enroll Export'!$G$2:$G$3230,MATCH($E72,'ST Enroll Export'!$B$2:$B$3230,0)),"Not Found")) -> Southside Academy Charter School | S72: =IFERROR(INDEX('ST Enroll Export'!$B$2:$B$3230,MATCH($D72,'ST Enroll Export'!$A$2:$A$3230,0)),IFERROR(INDEX('ST Enroll Export'!$B$2:$B$3230,MATCH($E72,'ST Enroll Export'!$B$2:$B$3230,0)),"Not Found")) -> 200037678 | T72: =IF(ISNUMBER(MATCH($D72,'ST Enroll Export'!$A$2:$A$3230,0)),"NYSSIS Match",IF(ISNUMBER(MATCH($E72,'ST Enroll Export'!$B$2:$B$3230,0)),"SID Match","No ST Match")) -> NYSSIS Match | U72: =IF(ISNUMBER(MATCH($D72,Disability!$B$2:$B$5962,0)),"SPED","Gen Ed") -> Gen Ed
A73: Southside 291462 | B73: 46174 | C73: southside_291462_unified-roster.xlsx | D73: 1647851873 | E73: 210004236 | F73: Morales | G73: Amaya | H73: 5 | I73: 41740 | J73: Southside Academy Charter School | K73: 45903 | M73: 1 | N73: Good | O73: 0 | P73: Gen Ed | Q73: =IFERROR(INDEX('ST Enroll Export'!$A$2:$A$3230,MATCH($D73,'ST Enroll Export'!$A$2:$A$3230,0)),IFERROR(IF(INDEX('ST Enroll Export'!$A$2:$A$3230,MATCH($E73,'ST Enroll Export'!$B$2:$B$3230,0))="","",INDEX('ST Enroll Export'!$A$2:$A$3230,MATCH($E73,'ST Enroll Export'!$B$2:$B$3230,0))),"Not Found")) -> 1647851873 | R73: =IFERROR(INDEX('ST Enroll Export'!$G$2:$G$3230,MATCH($D73,'ST Enroll Export'!$A$2:$A$3230,0)),IFERROR(INDEX('ST Enroll Export'!$G$2:$G$3230,MATCH($E73,'ST Enroll Export'!$B$2:$B$3230,0)),"Not Found")) -> Southside Academy Charter School | S73: =IFERROR(INDEX('ST Enroll Export'!$B$2:$B$3230,MATCH($D73,'ST Enroll Export'!$A$2:$A$3230,0)),IFERROR(INDEX('ST Enroll Export'!$B$2:$B$3230,MATCH($E73,'ST Enroll Export'!$B$2:$B$3230,0)),"Not Found")) -> 210004236 | T73: =IF(ISNUMBER(MATCH($D73,'ST Enroll Export'!$A$2:$A$3230,0)),"NYSSIS Match",IF(ISNUMBER(MATCH($E73,'ST Enroll Export'!$B$2:$B$3230,0)),"SID Match","No ST Match")) -> NYSSIS Match | U73: =IF(ISNUMBER(MATCH($D73,Disability!$B$2:$B$5962,0)),"SPED","Gen Ed") -> Gen Ed
A74: Southside 291462 | B74: 46174 | C74: southside_291462_unified-roster.xlsx | D74: 1635879015 | E74: 210004000 | F74: Ruiz-Mclain | G74: Ameliah | H74: 4 | I74: 42388 | J74: Southside Academy Charter School | K74: 45903 | M74: 1 | N74: Good | O74: 0 | P74: Gen Ed | Q74: =IFERROR(INDEX('ST Enroll Export'!$A$2:$A$3230,MATCH($D74,'ST Enroll Export'!$A$2:$A$3230,0)),IFERROR(IF(INDEX('ST Enroll Export'!$A$2:$A$3230,MATCH($E74,'ST Enroll Export'!$B$2:$B$3230,0))="","",INDEX('ST Enroll Export'!$A$2:$A$3230,MATCH($E74,'ST Enroll Export'!$B$2:$B$3230,0))),"Not Found")) -> 1635879015 | R74: =IFERROR(INDEX('ST Enroll Export'!$G$2:$G$3230,MATCH($D74,'ST Enroll Export'!$A$2:$A$3230,0)),IFERROR(INDEX('ST Enroll Export'!$G$2:$G$3230,MATCH($E74,'ST Enroll Export'!$B$2:$B$3230,0)),"Not Found")) -> Southside Academy Charter School | S74: =IFERROR(INDEX('ST Enroll Export'!$B$2:$B$3230,MATCH($D74,'ST Enroll Export'!$A$2:$A$3230,0)),IFERROR(INDEX('ST Enroll Export'!$B$2:$B$3230,MATCH($E74,'ST Enroll Export'!$B$2:$B$3230,0)),"Not Found")) -> 210004000 | T74: =IF(ISNUMBER(MATCH($D74,'ST Enroll Export'!$A$2:$A$3230,0)),"NYSSIS Match",IF(ISNUMBER(MATCH($E74,'ST Enroll Export'!$B$2:$B$3230,0)),"SID Match","No ST Match")) -> NYSSIS Match | U74: =IF(ISNUMBER(MATCH($D74,Disability!$B$2:$B$5962,0)),"SPED","Gen Ed") -> Gen Ed
A75: Southside 291462 | B75: 46174 | C75: southside_291462_unified-roster.xlsx | D75: 2567760593 | E75: 200030543 | F75: Chandler | G75: Amerie | H75: 7 | I75: 41095 | J75: Southside Academy Charter School | K75: 45903 | M75: 1 | N75: Good | O75: 0 | P75: Gen Ed | Q75: =IFERROR(INDEX('ST Enroll Export'!$A$2:$A$3230,MATCH($D75,'ST Enroll Export'!$A$2:$A$3230,0)),IFERROR(IF(INDEX('ST Enroll Export'!$A$2:$A$3230,MATCH($E75,'ST Enroll Export'!$B$2:$B$3230,0))="","",INDEX('ST Enroll Export'!$A$2:$A$3230,MATCH($E75,'ST Enroll Export'!$B$2:$B$3230,0))),"Not Found")) -> 2567760593 | R75: =IFERROR(INDEX('ST Enroll Export'!$G$2:$G$3230,MATCH($D75,'ST Enroll Export'!$A$2:$A$3230,0)),IFERROR(INDEX('ST Enroll Export'!$G$2:$G$3230,MATCH($E75,'ST Enroll Export'!$B$2:$B$3230,0)),"Not Found")) -> Southside Academy Charter School | S75: =IFERROR(INDEX('ST Enroll Export'!$B$2:$B$3230,MATCH($D75,'ST Enroll Export'!$A$2:$A$3230,0)),IFERROR(INDEX('ST Enroll Export'!$B$2:$B$3230,MATCH($E75,'ST Enroll Export'!$B$2:$B$3230,0)),"Not Found")) -> 200030543 | T75: =IF(ISNUMBER(MATCH($D75,'ST Enroll Export'!$A$2:$A$3230,0)),"NYSSIS Match",IF(ISNUMBER(MATCH($E75,'ST Enroll Export'!$B$2:$B$3230,0)),"SID Match","No ST Match")) -> NYSSIS Match | U75: =IF(ISNUMBER(MATCH($D75,Disability!$B$2:$B$5962,0)),"SPED","Gen Ed") -> Gen Ed
A76: Southside 291462 | B76: 46174 | C76: southside_291462_unified-roster.xlsx | D76: 8535798744 | E76: 210017318 | F76: Clifton | G76: Amias | H76: K | I76: 43817 | J76: Southside Academy Charter School | K76: 45903 | M76: 1 | N76: Good | O76: 0 | P76: Gen Ed | Q76: =IFERROR(INDEX('ST Enroll Export'!$A$2:$A$3230,MATCH($D76,'ST Enroll Export'!$A$2:$A$3230,0)),IFERROR(IF(INDEX('ST Enroll Export'!$A$2:$A$3230,MATCH($E76,'ST Enroll Export'!$B$2:$B$3230,0))="","",INDEX('ST Enroll Export'!$A$2:$A$3230,MATCH($E76,'ST Enroll Export'!$B$2:$B$3230,0))),"Not Found")) -> 8535798744 | R76: =IFERROR(INDEX('ST Enroll Export'!$G$2:$G$3230,MATCH($D76,'ST Enroll Export'!$A$2:$A$3230,0)),IFERROR(INDEX('ST Enroll Export'!$G$2:$G$3230,MATCH($E76,'ST Enroll Export'!$B$2:$B$3230,0)),"Not Found")) -> Southside Academy Charter School | S76: =IFERROR(INDEX('ST Enroll Export'!$B$2:$B$3230,MATCH($D76,'ST Enroll Export'!$A$2:$A$3230,0)),IFERROR(INDEX('ST Enroll Export'!$B$2:$B$3230,MATCH($E76,'ST Enroll Export'!$B$2:$B$3230,0)),"Not Found")) -> 210017318 | T76: =IF(ISNUMBER(MATCH($D76,'ST Enroll Export'!$A$2:$A$3230,0)),"NYSSIS Match",IF(ISNUMBER(MATCH($E76,'ST Enroll Export'!$B$2:$B$3230,0)),"SID Match","No ST Match")) -> NYSSIS Match | U76: =IF(ISNUMBER(MATCH($D76,Disability!$B$2:$B$5962,0)),"SPED","Gen Ed") -> Gen Ed
A77: Southside 291462 | B77: 46174 | C77: southside_291462_unified-roster.xlsx | D77: 6124086535 | E77: 210007964 | F77: Cirino | G77: Amir | H77: 3 | I77: 42940 | J77: Southside Academy Charter School | K77: 45904 | M77: 0.975 | N77: Good | O77: 0 | P77: Gen Ed | Q77: =IFERROR(INDEX('ST Enroll Export'!$A$2:$A$3230,MATCH($D77,'ST Enroll Export'!$A$2:$A$3230,0)),IFERROR(IF(INDEX('ST Enroll Export'!$A$2:$A$3230,MATCH($E77,'ST Enroll Export'!$B$2:$B$3230,0))="","",INDEX('ST Enroll Export'!$A$2:$A$3230,MATCH($E77,'ST Enroll Export'!$B$2:$B$3230,0))),"Not Found")) -> 6124086535 | R77: =IFERROR(INDEX('ST Enroll Export'!$G$2:$G$3230,MATCH($D77,'ST Enroll Export'!$A$2:$A$3230,0)),IFERROR(INDEX('ST Enroll Export'!$G$2:$G$3230,MATCH($E77,'ST Enroll Export'!$B$2:$B$3230,0)),"Not Found")) -> Southside Academy Charter School | S77: =IFERROR(INDEX('ST Enroll Export'!$B$2:$B$3230,MATCH($D77,'ST Enroll Export'!$A$2:$A$3230,0)),IFERROR(INDEX('ST Enroll Export'!$B$2:$B$3230,MATCH($E77,'ST Enroll Export'!$B$2:$B$3230,0)),"Not Found")) -> 210007964 | T77: =IF(ISNUMBER(MATCH($D77,'ST Enroll Export'!$A$2:$A$3230,0)),"NYSSIS Match",IF(ISNUMBER(MATCH($E77,'ST Enroll Export'!$B$2:$B$3230,0)),"SID Match","No ST Match")) -> NYSSIS Match | U77: =IF(ISNUMBER(MATCH($D77,Disability!$B$2:$B$5962,0)),"SPED","Gen Ed") -> Gen Ed
A78: Southside 291462 | B78: 46174 | C78: southside_291462_unified-roster.xlsx | D78: 2741058673 | E78: 210011629 | F78: Johnson | G78: Amir | H78: 2 | I78: 43132 | J78: Southside Academy Charter School | K78: 45904 | M78: 0.975 | N78: Good | O78: 0 | P78: Gen Ed | Q78: =IFERROR(INDEX('ST Enroll Export'!$A$2:$A$3230,MATCH($D78,'ST Enroll Export'!$A$2:$A$3230,0)),IFERROR(IF(INDEX('ST Enroll Export'!$A$2:$A$3230,MATCH($E78,'ST Enroll Export'!$B$2:$B$3230,0))="","",INDEX('ST Enroll Export'!$A$2:$A$3230,MATCH($E78,'ST Enroll Export'!$B$2:$B$3230,0))),"Not Found")) -> 2741058673 | R78: =IFERROR(INDEX('ST Enroll Export'!$G$2:$G$3230,MATCH($D78,'ST Enroll Export'!$A$2:$A$3230,0)),IFERROR(INDEX('ST Enroll Export'!$G$2:$G$3230,MATCH($E78,'ST Enroll Export'!$B$2:$B$3230,0)),"Not Found")) -> Southside Academy Charter School | S78: =IFERROR(INDEX('ST Enroll Export'!$B$2:$B$3230,MATCH($D78,'ST Enroll Export'!$A$2:$A$3230,0)),IFERROR(INDEX('ST Enroll Export'!$B$2:$B$3230,MATCH($E78,'ST Enroll Export'!$B$2:$B$3230,0)),"Not Found")) -> 210011629 | T78: =IF(ISNUMBER(MATCH($D78,'ST Enroll Export'!$A$2:$A$3230,0)),"NYSSIS Match",IF(ISNUMBER(MATCH($E78,'ST Enroll Export'!$B$2:$B$3230,0)),"SID Match","No ST Match")) -> NYSSIS Match | U78: =IF(ISNUMBER(MATCH($D78,Disability!$B$2:$B$5962,0)),"SPED","Gen Ed") -> Gen Ed
A79: Southside 291462 | B79: 46174 | C79: southside_291462_unified-roster.xlsx | D79: 3898545173 | E79: 200037239 | F79: Aiken | G79: Amira | H79: 6 | I79: 41632 | J79: Southside Academy Charter School | K79: 45903 | M79: 1 | N79: Good | O79: 0 | P79: Gen Ed | Q79: =IFERROR(INDEX('ST Enroll Export'!$A$2:$A$3230,MATCH($D79,'ST Enroll Export'!$A$2:$A$3230,0)),IFERROR(IF(INDEX('ST Enroll Export'!$A$2:$A$3230,MATCH($E79,'ST Enroll Export'!$B$2:$B$3230,0))="","",INDEX('ST Enroll Export'!$A$2:$A$3230,MATCH($E79,'ST Enroll Export'!$B$2:$B$3230,0))),"Not Found")) -> 3898545173 | R79: =IFERROR(INDEX('ST Enroll Export'!$G$2:$G$3230,MATCH($D79,'ST Enroll Export'!$A$2:$A$3230,0)),IFERROR(INDEX('ST Enroll Export'!$G$2:$G$3230,MATCH($E79,'ST Enroll Export'!$B$2:$B$3230,0)),"Not Found")) -> Southside Academy Charter School | S79: =IFERROR(INDEX('ST Enroll Export'!$B$2:$B$3230,MATCH($D79,'ST Enroll Export'!$A$2:$A$3230,0)),IFERROR(INDEX('ST Enroll Export'!$B$2:$B$3230,MATCH($E79,'ST Enroll Export'!$B$2:$B$3230,0)),"Not Found")) -> 200037239 | T79: =IF(ISNUMBER(MATCH($D79,'ST Enroll Export'!$A$2:$A$3230,0)),"NYSSIS Match",IF(ISNUMBER(MATCH($E79,'ST Enroll Export'!$B$2:$B$3230,0)),"SID Match","No ST Match")) -> NYSSIS Match | U79: =IF(ISNUMBER(MATCH($D79,Disability!$B$2:$B$5962,0)),"SPED","Gen Ed") -> Gen Ed
... A95: Southside 291462 | B95: 46174 | C95: southside_291462_unified-roster.xlsx | D95: 8775651313 | E95: 210013145 | F95: Stroman | G95: Anthony | H95: 3 | I95: 42916 | J95: Southside Academy Charter School | K95: 45903 | M95: 1 | N95: Good | O95: 0 | P95: Gen Ed | Q95: =IFERROR(INDEX('ST Enroll Export'!$A$2:$A$3230,MATCH($D95,'ST Enroll Export'!$A$2:$A$3230,0)),IFERROR(IF(INDEX('ST Enroll Export'!$A$2:$A$3230,MATCH($E95,'ST Enroll Export'!$B$2:$B$3230,0))="","",INDEX('ST Enroll Export'!$A$2:$A$3230,MATCH($E95,'ST Enroll Export'!$B$2:$B$3230,0))),"Not Found")) -> 8775651313 | R95: =IFERROR(INDEX('ST Enroll Export'!$G$2:$G$3230,MATCH($D95,'ST Enroll Export'!$A$2:$A$3230,0)),IFERROR(INDEX('ST Enroll Export'!$G$2:$G$3230,MATCH($E95,'ST Enroll Export'!$B$2:$B$3230,0)),"Not Found")) -> Southside Academy Charter School | S95: =IFERROR(INDEX('ST Enroll Export'!$B$2:$B$3230,MATCH($D95,'ST Enroll Export'!$A$2:$A$3230,0)),IFERROR(INDEX('ST Enroll Export'!$B$2:$B$3230,MATCH($E95,'ST Enroll Export'!$B$2:$B$3230,0)),"Not Found")) -> 210013145 | T95: =IF(ISNUMBER(MATCH($D95,'ST Enroll Export'!$A$2:$A$3230,0)),"NYSSIS Match",IF(ISNUMBER(MATCH($E95,'ST Enroll Export'!$B$2:$B$3230,0)),"SID Match","No ST Match")) -> NYSSIS Match | U95: =IF(ISNUMBER(MATCH($D95,Disability!$B$2:$B$5962,0)),"SPED","Gen Ed") -> Gen Ed
A96: Southside 291462 | B96: 46174 | C96: southside_291462_unified-roster.xlsx | D96: 9394640522 | E96: 210010093 | F96: Davis-El | G96: Anubis | H96: 2 | I96: 43011 | J96: Southside Academy Charter School | K96: 45903 | L96: 45940 | M96: 0.15 | N96: Good | O96: 0 | P96: Gen Ed | Q96: =IFERROR(INDEX('ST Enroll Export'!$A$2:$A$3230,MATCH($D96,'ST Enroll Export'!$A$2:$A$3230,0)),IFERROR(IF(INDEX('ST Enroll Export'!$A$2:$A$3230,MATCH($E96,'ST Enroll Export'!$B$2:$B$3230,0))="","",INDEX('ST Enroll Export'!$A$2:$A$3230,MATCH($E96,'ST Enroll Export'!$B$2:$B$3230,0))),"Not Found")) -> 9394640522 | R96: =IFERROR(INDEX('ST Enroll Export'!$G$2:$G$3230,MATCH($D96,'ST Enroll Export'!$A$2:$A$3230,0)),IFERROR(INDEX('ST Enroll Export'!$G$2:$G$3230,MATCH($E96,'ST Enroll Export'!$B$2:$B$3230,0)),"Not Found")) -> Southside Academy Charter School | S96: =IFERROR(INDEX('ST Enroll Export'!$B$2:$B$3230,MATCH($D96,'ST Enroll Export'!$A$2:$A$3230,0)),IFERROR(INDEX('ST Enroll Export'!$B$2:$B$3230,MATCH($E96,'ST Enroll Export'!$B$2:$B$3230,0)),"Not Found")) -> 210010093 | T96: =IF(ISNUMBER(MATCH($D96,'ST Enroll Export'!$A$2:$A$3230,0)),"NYSSIS Match",IF(ISNUMBER(MATCH($E96,'ST Enroll Export'!$B$2:$B$3230,0)),"SID Match","No ST Match")) -> NYSSIS Match | U96: =IF(ISNUMBER(MATCH($D96,Disability!$B$2:$B$5962,0)),"SPED","Gen Ed") -> Gen Ed
A97: Southside 291462 | B97: 46174 | C97: southside_291462_unified-roster.xlsx | D97: 9394640522 | E97: 210010093 | F97: Davis-El | G97: Anubis | H97: 2 | I97: 43011 | J97: Southside Academy Charter School | K97: 46042 | M97: 0.55 | N97: Good | O97: 0 | P97: Gen Ed | Q97: =IFERROR(INDEX('ST Enroll Export'!$A$2:$A$3230,MATCH($D97,'ST Enroll Export'!$A$2:$A$3230,0)),IFERROR(IF(INDEX('ST Enroll Export'!$A$2:$A$3230,MATCH($E97,'ST Enroll Export'!$B$2:$B$3230,0))="","",INDEX('ST Enroll Export'!$A$2:$A$3230,MATCH($E97,'ST Enroll Export'!$B$2:$B$3230,0))),"Not Found")) -> 9394640522 | R97: =IFERROR(INDEX('ST Enroll Export'!$G$2:$G$3230,MATCH($D97,'ST Enroll Export'!$A$2:$A$3230,0)),IFERROR(INDEX('ST Enroll Export'!$G$2:$G$3230,MATCH($E97,'ST Enroll Export'!$B$2:$B$3230,0)),"Not Found")) -> Southside Academy Charter School | S97: =IFERROR(INDEX('ST Enroll Export'!$B$2:$B$3230,MATCH($D97,'ST Enroll Export'!$A$2:$A$3230,0)),IFERROR(INDEX('ST Enroll Export'!$B$2:$B$3230,MATCH($E97,'ST Enroll Export'!$B$2:$B$3230,0)),"Not Found")) -> 210010093 | T97: =IF(ISNUMBER(MATCH($D97,'ST Enroll Export'!$A$2:$A$3230,0)),"NYSSIS Match",IF(ISNUMBER(MATCH($E97,'ST Enroll Export'!$B$2:$B$3230,0)),"SID Match","No ST Match")) -> NYSSIS Match | U97: =IF(ISNUMBER(MATCH($D97,Disability!$B$2:$B$5962,0)),"SPED","Gen Ed") -> Gen Ed
A98: Southside 291462 | B98: 46174 | C98: southside_291462_unified-roster.xlsx | D98: 7329456485 | E98: 210008329 | F98: Billingsley | G98: Anyia | H98: 2 | I98: 43389 | J98: Southside Academy Charter School | K98: 45903 | M98: 1 | N98: Good | O98: 0 | P98: Gen Ed | Q98: =IFERROR(INDEX('ST Enroll Export'!$A$2:$A$3230,MATCH($D98,'ST Enroll Export'!$A$2:$A$3230,0)),IFERROR(IF(INDEX('ST Enroll Export'!$A$2:$A$3230,MATCH($E98,'ST Enroll Export'!$B$2:$B$3230,0))="","",INDEX('ST Enroll Export'!$A$2:$A$3230,MATCH($E98,'ST Enroll Export'!$B$2:$B$3230,0))),"Not Found")) -> 7329456485 | R98: =IFERROR(INDEX('ST Enroll Export'!$G$2:$G$3230,MATCH($D98,'ST Enroll Export'!$A$2:$A$3230,0)),IFERROR(INDEX('ST Enroll Export'!$G$2:$G$3230,MATCH($E98,'ST Enroll Export'!$B$2:$B$3230,0)),"Not Found")) -> Southside Academy Charter School | S98: =IFERROR(INDEX('ST Enroll Export'!$B$2:$B$3230,MATCH($D98,'ST Enroll Export'!$A$2:$A$3230,0)),IFERROR(INDEX('ST Enroll Export'!$B$2:$B$3230,MATCH($E98,'ST Enroll Export'!$B$2:$B$3230,0)),"Not Found")) -> 210008329 | T98: =IF(ISNUMBER(MATCH($D98,'ST Enroll Export'!$A$2:$A$3230,0)),"NYSSIS Match",IF(ISNUMBER(MATCH($E98,'ST Enroll Export'!$B$2:$B$3230,0)),"SID Match","No ST Match")) -> NYSSIS Match | U98: =IF(ISNUMBER(MATCH($D98,Disability!$B$2:$B$5962,0)),"SPED","Gen Ed") -> Gen Ed
A99: Southside 291462 | B99: 46174 | C99: southside_291462_unified-roster.xlsx | D99: 3550907634 | E99: 210011269 | F99: Titus | G99: Anyla | H99: 2 | I99: 43453 | J99: Southside Academy Charter School | K99: 45903 | M99: 1 | N99: Good | O99: 0 | P99: Gen Ed | Q99: =IFERROR(INDEX('ST Enroll Export'!$A$2:$A$3230,MATCH($D99,'ST Enroll Export'!$A$2:$A$3230,0)),IFERROR(IF(INDEX('ST Enroll Export'!$A$2:$A$3230,MATCH($E99,'ST Enroll Export'!$B$2:$B$3230,0))="","",INDEX('ST Enroll Export'!$A$2:$A$3230,MATCH($E99,'ST Enroll Export'!$B$2:$B$3230,0))),"Not Found")) -> 3550907634 | R99: =IFERROR(INDEX('ST Enroll Export'!$G$2:$G$3230,MATCH($D99,'ST Enroll Export'!$A$2:$A$3230,0)),IFERROR(INDEX('ST Enroll Export'!$G$2:$G$3230,MATCH($E99,'ST Enroll Export'!$B$2:$B$3230,0)),"Not Found")) -> Southside Academy Charter School | S99: =IFERROR(INDEX('ST Enroll Export'!$B$2:$B$3230,MATCH($D99,'ST Enroll Export'!$A$2:$A$3230,0)),IFERROR(INDEX('ST Enroll Export'!$B$2:$B$3230,MATCH($E99,'ST Enroll Export'!$B$2:$B$3230,0)),"Not Found")) -> 210011269 | T99: =IF(ISNUMBER(MATCH($D99,'ST Enroll Export'!$A$2:$A$3230,0)),"NYSSIS Match",IF(ISNUMBER(MATCH($E99,'ST Enroll Export'!$B$2:$B$3230,0)),"SID Match","No ST Match")) -> NYSSIS Match | U99: =IF(ISNUMBER(MATCH($D99,Disability!$B$2:$B$5962,0)),"SPED","Gen Ed") -> Gen Ed
A100: Southside 291462 | B100: 46174 | C100: southside_291462_unified-roster.xlsx | D100: 1580562481 | E100: 210014023 | F100: Works | G100: ARayvia | H100: 2 | I100: 43126 | J100: Southside Academy Charter School | K100: 45904 | M100: 0.975 | N100: Good | O100: 0 | P100: Gen Ed | Q100: =IFERROR(INDEX('ST Enroll Export'!$A$2:$A$3230,MATCH($D100,'ST Enroll Export'!$A$2:$A$3230,0)),IFERROR(IF(INDEX('ST Enroll Export'!$A$2:$A$3230,MATCH($E100,'ST Enroll Export'!$B$2:$B$3230,0))="","",INDEX('ST Enroll Export'!$A$2:$A$3230,MATCH($E100,'ST Enroll Export'!$B$2:$B$3230,0))),"Not Found")) -> 1580562481 | R100: =IFERROR(INDEX('ST Enroll Export'!$G$2:$G$3230,MATCH($D100,'ST Enroll Export'!$A$2:$A$3230,0)),IFERROR(INDEX('ST Enroll Export'!$G$2:$G$3230,MATCH($E100,'ST Enroll Export'!$B$2:$B$3230,0)),"Not Found")) -> Southside Academy Charter School | S100: =IFERROR(INDEX('ST Enroll Export'!$B$2:$B$3230,MATCH($D100,'ST Enroll Export'!$A$2:$A$3230,0)),IFERROR(INDEX('ST Enroll Export'!$B$2:$B$3230,MATCH($E100,'ST Enroll Export'!$B$2:$B$3230,0)),"Not Found")) -> 210014023 | T100: =IF(ISNUMBER(MATCH($D100,'ST Enroll Export'!$A$2:$A$3230,0)),"NYSSIS Match",IF(ISNUMBER(MATCH($E100,'ST Enroll Export'!$B$2:$B$3230,0)),"SID Match","No ST Match")) -> NYSSIS Match | U100: =IF(ISNUMBER(MATCH($D100,Disability!$B$2:$B$5962,0)),"SPED","Gen Ed") -> Gen Ed
A101: Southside 291462 | B101: 46174 | C101: southside_291462_unified-roster.xlsx | D101: 8769895202 | E101: 200029205 | F101: Luter | G101: Aria | H101: 7 | I101: 41324 | J101: Southside Academy Charter School | K101: 45903 | M101: 1 | N101: Good | O101: 0 | P101: Gen Ed | Q101: =IFERROR(INDEX('ST Enroll Export'!$A$2:$A$3230,MATCH($D101,'ST Enroll Export'!$A$2:$A$3230,0)),IFERROR(IF(INDEX('ST Enroll Export'!$A$2:$A$3230,MATCH($E101,'ST Enroll Export'!$B$2:$B$3230,0))="","",INDEX('ST Enroll Export'!$A$2:$A$3230,MATCH($E101,'ST Enroll Export'!$B$2:$B$3230,0))),"Not Found")) -> 8769895202 | R101: =IFERROR(INDEX('ST Enroll Export'!$G$2:$G$3230,MATCH($D101,'ST Enroll Export'!$A$2:$A$3230,0)),IFERROR(INDEX('ST Enroll Export'!$G$2:$G$3230,MATCH($E101,'ST Enroll Export'!$B$2:$B$3230,0)),"Not Found")) -> Southside Academy Charter School | S101: =IFERROR(INDEX('ST Enroll Export'!$B$2:$B$3230,MATCH($D101,'ST Enroll Export'!$A$2:$A$3230,0)),IFERROR(INDEX('ST Enroll Export'!$B$2:$B$3230,MATCH($E101,'ST Enroll Export'!$B$2:$B$3230,0)),"Not Found")) -> 200029205 | T101: =IF(ISNUMBER(MATCH($D101,'ST Enroll Export'!$A$2:$A$3230,0)),"NYSSIS Match",IF(ISNUMBER(MATCH($E101,'ST Enroll Export'!$B$2:$B$3230,0)),"SID Match","No ST Match")) -> NYSSIS Match | U101: =IF(ISNUMBER(MATCH($D101,Disability!$B$2:$B$5962,0)),"SPED","Gen Ed") -> Gen Ed
A102: Southside 291462 | B102: 46174 | C102: southside_291462_unified-roster.xlsx | D102: 5516246433 | E102: 210007891 | F102: Colon | G102: Ariel | H102: 3 | I102: 42835 | J102: Southside Academy Charter School | K102: 45903 | M102: 1 | N102: Good | O102: 0 | P102: Gen Ed | Q102: =IFERROR(INDEX('ST Enroll Export'!$A$2:$A$3230,MATCH($D102,'ST Enroll Export'!$A$2:$A$3230,0)),IFERROR(IF(INDEX('ST Enroll Export'!$A$2:$A$3230,MATCH($E102,'ST Enroll Export'!$B$2:$B$3230,0))="","",INDEX('ST Enroll Export'!$A$2:$A$3230,MATCH($E102,'ST Enroll Export'!$B$2:$B$3230,0))),"Not Found")) -> 5516246433 | R102: =IFERROR(INDEX('ST Enroll Export'!$G$2:$G$3230,MATCH($D102,'ST Enroll Export'!$A$2:$A$3230,0)),IFERROR(INDEX('ST Enroll Export'!$G$2:$G$3230,MATCH($E102,'ST Enroll Export'!$B$2:$B$3230,0)),"Not Found")) -> Southside Academy Charter School | S102: =IFERROR(INDEX('ST Enroll Export'!$B$2:$B$3230,MATCH($D102,'ST Enroll Export'!$A$2:$A$3230,0)),IFERROR(INDEX('ST Enroll Export'!$B$2:$B$3230,MATCH($E102,'ST Enroll Export'!$B$2:$B$3230,0)),"Not Found")) -> 210007891 | T102: =IF(ISNUMBER(MATCH($D102,'ST Enroll Export'!$A$2:$A$3230,0)),"NYSSIS Match",IF(ISNUMBER(MATCH($E102,'ST Enroll Export'!$B$2:$B$3230,0)),"SID Match","No ST Match")) -> NYSSIS Match | U102: =IF(ISNUMBER(MATCH($D102,Disability!$B$2:$B$5962,0)),"SPED","Gen Ed") -> Gen Ed
A103: Southside 291462 | B103: 46174 | C103: southside_291462_unified-roster.xlsx | D103: 6887336141 | E103: 210007601 | F103: Price | G103: Ariel | H103: 2 | I103: 42947 | J103: Southside Academy Charter School | K103: 45903 | M103: 1 | N103: Good | O103: 0 | P103: Gen Ed | Q103: =IFERROR(INDEX('ST Enroll Export'!$A$2:$A$3230,MATCH($D103,'ST Enroll Export'!$A$2:$A$3230,0)),IFERROR(IF(INDEX('ST Enroll Export'!$A$2:$A$3230,MATCH($E103,'ST Enroll Export'!$B$2:$B$3230,0))="","",INDEX('ST Enroll Export'!$A$2:$A$3230,MATCH($E103,'ST Enroll Export'!$B$2:$B$3230,0))),"Not Found")) -> 6887336141 | R103: =IFERROR(INDEX('ST Enroll Export'!$G$2:$G$3230,MATCH($D103,'ST Enroll Export'!$A$2:$A$3230,0)),IFERROR(INDEX('ST Enroll Export'!$G$2:$G$3230,MATCH($E103,'ST Enroll Export'!$B$2:$B$3230,0)),"Not Found")) -> Southside Academy Charter School | S103: =IFERROR(INDEX('ST Enroll Export'!$B$2:$B$3230,MATCH($D103,'ST Enroll Export'!$A$2:$A$3230,0)),IFERROR(INDEX('ST Enroll Export'!$B$2:$B$3230,MATCH($E103,'ST Enroll Export'!$B$2:$B$3230,0)),"Not Found")) -> 210007601 | T103: =IF(ISNUMBER(MATCH($D103,'ST Enroll Export'!$A$2:$A$3230,0)),"NYSSIS Match",IF(ISNUMBER(MATCH($E103,'ST Enroll Export'!$B$2:$B$3230,0)),"SID Match","No ST Match")) -> NYSSIS Match | U103: =IF(ISNUMBER(MATCH($D103,Disability!$B$2:$B$5962,0)),"SPED","Gen Ed") -> Gen Ed
A104: Southside 291462 | B104: 46174 | C104: southside_291462_unified-roster.xlsx | D104: 4006453581 | E104: 210009775 | F104: Flowers | G104: Aries | H104: 3 | I104: 42816 | J104: Southside Academy Charter School | K104: 45915 | M104: 0.95 | N104: Good | O104: 0 | P104: Gen Ed | Q104: =IFERROR(INDEX('ST Enroll Export'!$A$2:$A$3230,MATCH($D104,'ST Enroll Export'!$A$2:$A$3230,0)),IFERROR(IF(INDEX('ST Enroll Export'!$A$2:$A$3230,MATCH($E104,'ST Enroll Export'!$B$2:$B$3230,0))="","",INDEX('ST Enroll Export'!$A$2:$A$3230,MATCH($E104,'ST Enroll Export'!$B$2:$B$3230,0))),"Not Found")) -> 4006453581 | R104: =IFERROR(INDEX('ST Enroll Export'!$G$2:$G$3230,MATCH($D104,'ST Enroll Export'!$A$2:$A$3230,0)),IFERROR(INDEX('ST Enroll Export'!$G$2:$G$3230,MATCH($E104,'ST Enroll Export'!$B$2:$B$3230,0)),"Not Found")) -> Southside Academy Charter School | S104: =IFERROR(INDEX('ST Enroll Export'!$B$2:$B$3230,MATCH($D104,'ST Enroll Export'!$A$2:$A$3230,0)),IFERROR(INDEX('ST Enroll Export'!$B$2:$B$3230,MATCH($E104,'ST Enroll Export'!$B$2:$B$3230,0)),"Not Found")) -> 210009775 | T104: =IF(ISNUMBER(MATCH($D104,'ST Enroll Export'!$A$2:$A$3230,0)),"NYSSIS Match",IF(ISNUMBER(MATCH($E104,'ST Enroll Export'!$B$2:$B$3230,0)),"SID Match","No ST Match")) -> NYSSIS Match | U104: =IF(ISNUMBER(MATCH($D104,Disability!$B$2:$B$5962,0)),"SPED","Gen Ed") -> Gen Ed
A105: Southside 291462 | B105: 46174 | C105: southside_291462_unified-roster.xlsx | D105: 1781894942 | E105: 200038707 | F105: Williams | G105: Ariya | H105: 5 | I105: 42329 | J105: Southside Academy Charter School | K105: 45903 | M105: 1 | N105: Good | O105: 0 | P105: Gen Ed | Q105: =IFERROR(INDEX('ST Enroll Export'!$A$2:$A$3230,MATCH($D105,'ST Enroll Export'!$A$2:$A$3230,0)),IFERROR(IF(INDEX('ST Enroll Export'!$A$2:$A$3230,MATCH($E105,'ST Enroll Export'!$B$2:$B$3230,0))="","",INDEX('ST Enroll Export'!$A$2:$A$3230,MATCH($E105,'ST Enroll Export'!$B$2:$B$3230,0))),"Not Found")) -> 1781894942 | R105: =IFERROR(INDEX('ST Enroll Export'!$G$2:$G$3230,MATCH($D105,'ST Enroll Export'!$A$2:$A$3230,0)),IFERROR(INDEX('ST Enroll Export'!$G$2:$G$3230,MATCH($E105,'ST Enroll Export'!$B$2:$B$3230,0)),"Not Found")) -> Southside Academy Charter School | S105: =IFERROR(INDEX('ST Enroll Export'!$B$2:$B$3230,MATCH($D105,'ST Enroll Export'!$A$2:$A$3230,0)),IFERROR(INDEX('ST Enroll Export'!$B$2:$B$3230,MATCH($E105,'ST Enroll Export'!$B$2:$B$3230,0)),"Not Found")) -> 200038707 | T105: =IF(ISNUMBER(MATCH($D105,'ST Enroll Export'!$A$2:$A$3230,0)),"NYSSIS Match",IF(ISNUMBER(MATCH($E105,'ST Enroll Export'!$B$2:$B$3230,0)),"SID Match","No ST Match")) -> NYSSIS Match | U105: =IF(ISNUMBER(MATCH($D105,Disability!$B$2:$B$5962,0)),"SPED","Gen Ed") -> Gen Ed
A106: Southside 291462 | B106: 46174 | C106: southside_291462_unified-roster.xlsx | D106: 4699043762 | E106: 210007108 | F106: Cirino | G106: Armani | H106: 4 | I106: 42559 | J106: Southside Academy Charter School | K106: 45904 | M106: 0.975 | N106: Good | O106: 0 | P106: Gen Ed | Q106: =IFERROR(INDEX('ST Enroll Export'!$A$2:$A$3230,MATCH($D106,'ST Enroll Export'!$A$2:$A$3230,0)),IFERROR(IF(INDEX('ST Enroll Export'!$A$2:$A$3230,MATCH($E106,'ST Enroll Export'!$B$2:$B$3230,0))="","",INDEX('ST Enroll Export'!$A$2:$A$3230,MATCH($E106,'ST Enroll Export'!$B$2:$B$3230,0))),"Not Found")) -> 4699043762 | R106: =IFERROR(INDEX('ST Enroll Export'!$G$2:$G$3230,MATCH($D106,'ST Enroll Export'!$A$2:$A$3230,0)),IFERROR(INDEX('ST Enroll Export'!$G$2:$G$3230,MATCH($E106,'ST Enroll Export'!$B$2:$B$3230,0)),"Not Found")) -> Southside Academy Charter School | S106: =IFERROR(INDEX('ST Enroll Export'!$B$2:$B$3230,MATCH($D106,'ST Enroll Export'!$A$2:$A$3230,0)),IFERROR(INDEX('ST Enroll Export'!$B$2:$B$3230,MATCH($E106,'ST Enroll Export'!$B$2:$B$3230,0)),"Not Found")) -> 210007108 | T106: =IF(ISNUMBER(MATCH($D106,'ST Enroll Export'!$A$2:$A$3230,0)),"NYSSIS Match",IF(ISNUMBER(MATCH($E106,'ST Enroll Export'!$B$2:$B$3230,0)),"SID Match","No ST Match")) -> NYSSIS Match | U106: =IF(ISNUMBER(MATCH($D106,Disability!$B$2:$B$5962,0)),"SPED","Gen Ed") -> Gen Ed
A107: Southside 291462 | B107: 46174 | C107: southside_291462_unified-roster.xlsx | D107: 5975014716 | E107: 210013616 | F107: Murray | G107: Armarni | H107: K | I107: 43945 | J107: Southside Academy Charter School | K107: 45903 | M107: 1 | N107: Good | O107: 0 | P107: Gen Ed | Q107: =IFERROR(INDEX('ST Enroll Export'!$A$2:$A$3230,MATCH($D107,'ST Enroll Export'!$A$2:$A$3230,0)),IFERROR(IF(INDEX('ST Enroll Export'!$A$2:$A$3230,MATCH($E107,'ST Enroll Export'!$B$2:$B$3230,0))="","",INDEX('ST Enroll Export'!$A$2:$A$3230,MATCH($E107,'ST Enroll Export'!$B$2:$B$3230,0))),"Not Found")) -> 5975014716 | R107: =IFERROR(INDEX('ST Enroll Export'!$G$2:$G$3230,MATCH($D107,'ST Enroll Export'!$A$2:$A$3230,0)),IFERROR(INDEX('ST Enroll Export'!$G$2:$G$3230,MATCH($E107,'ST Enroll Export'!$B$2:$B$3230,0)),"Not Found")) -> Southside Academy Charter School | S107: =IFERROR(INDEX('ST Enroll Export'!$B$2:$B$3230,MATCH($D107,'ST Enroll Export'!$A$2:$A$3230,0)),IFERROR(INDEX('ST Enroll Export'!$B$2:$B$3230,MATCH($E107,'ST Enroll Export'!$B$2:$B$3230,0)),"Not Found")) -> 210013616 | T107: =IF(ISNUMBER(MATCH($D107,'ST Enroll Export'!$A$2:$A$3230,0)),"NYSSIS Match",IF(ISNUMBER(MATCH($E107,'ST Enroll Export'!$B$2:$B$3230,0)),"SID Match","No ST Match")) -> NYSSIS Match | U107: =IF(ISNUMBER(MATCH($D107,Disability!$B$2:$B$5962,0)),"SPED","Gen Ed") -> Gen Ed
A108: Southside 291462 | B108: 46174 | C108: southside_291462_unified-roster.xlsx | D108: 1761288976 | E108: 210005225 | F108: Colon | G108: Armauni | H108: 2 | I108: 43161 | J108: Southside Academy Charter School | K108: 45903 | M108: 1 | N108: Good | O108: 0 | P108: SPED | Q108: =IFERROR(INDEX('ST Enroll Export'!$A$2:$A$3230,MATCH($D108,'ST Enroll Export'!$A$2:$A$3230,0)),IFERROR(IF(INDEX('ST Enroll Export'!$A$2:$A$3230,MATCH($E108,'ST Enroll Export'!$B$2:$B$3230,0))="","",INDEX('ST Enroll Export'!$A$2:$A$3230,MATCH($E108,'ST Enroll Export'!$B$2:$B$3230,0))),"Not Found")) -> 1761288976 | R108: =IFERROR(INDEX('ST Enroll Export'!$G$2:$G$3230,MATCH($D108,'ST Enroll Export'!$A$2:$A$3230,0)),IFERROR(INDEX('ST Enroll Export'!$G$2:$G$3230,MATCH($E108,'ST Enroll Export'!$B$2:$B$3230,0)),"Not Found")) -> Southside Academy Charter School | S108: =IFERROR(INDEX('ST Enroll Export'!$B$2:$B$3230,MATCH($D108,'ST Enroll Export'!$A$2:$A$3230,0)),IFERROR(INDEX('ST Enroll Export'!$B$2:$B$3230,MATCH($E108,'ST Enroll Export'!$B$2:$B$3230,0)),"Not Found")) -> 210005225 | T108: =IF(ISNUMBER(MATCH($D108,'ST Enroll Export'!$A$2:$A$3230,0)),"NYSSIS Match",IF(ISNUMBER(MATCH($E108,'ST Enroll Export'!$B$2:$B$3230,0)),"SID Match","No ST Match")) -> NYSSIS Match | U108: =IF(ISNUMBER(MATCH($D108,Disability!$B$2:$B$5962,0)),"SPED","Gen Ed") -> SPED
... A158: Southside 291462 | B158: 46174 | C158: southside_291462_unified-roster.xlsx | D158: 7690309653 | E158: 200037763 | F158: Donai | G158: Daniel | H158: 8 | I158: 41007 | J158: Southside Academy Charter School | K158: 45903 | M158: 1 | N158: Good | O158: 0 | P158: Gen Ed | Q158: =IFERROR(INDEX('ST Enroll Export'!$A$2:$A$3230,MATCH($D158,'ST Enroll Export'!$A$2:$A$3230,0)),IFERROR(IF(INDEX('ST Enroll Export'!$A$2:$A$3230,MATCH($E158,'ST Enroll Export'!$B$2:$B$3230,0))="","",INDEX('ST Enroll Export'!$A$2:$A$3230,MATCH($E158,'ST Enroll Export'!$B$2:$B$3230,0))),"Not Found")) -> 7690309653 | R158: =IFERROR(INDEX('ST Enroll Export'!$G$2:$G$3230,MATCH($D158,'ST Enroll Export'!$A$2:$A$3230,0)),IFERROR(INDEX('ST Enroll Export'!$G$2:$G$3230,MATCH($E158,'ST Enroll Export'!$B$2:$B$3230,0)),"Not Found")) -> Southside Academy Charter School | S158: =IFERROR(INDEX('ST Enroll Export'!$B$2:$B$3230,MATCH($D158,'ST Enroll Export'!$A$2:$A$3230,0)),IFERROR(INDEX('ST Enroll Export'!$B$2:$B$3230,MATCH($E158,'ST Enroll Export'!$B$2:$B$3230,0)),"Not Found")) -> 200037763 | T158: =IF(ISNUMBER(MATCH($D158,'ST Enroll Export'!$A$2:$A$3230,0)),"NYSSIS Match",IF(ISNUMBER(MATCH($E158,'ST Enroll Export'!$B$2:$B$3230,0)),"SID Match","No ST Match")) -> NYSSIS Match | U158: =IF(ISNUMBER(MATCH($D158,Disability!$B$2:$B$5962,0)),"SPED","Gen Ed") -> SPED
A159: Southside 291462 | B159: 46174 | C159: southside_291462_unified-roster.xlsx | D159: 6229109670 | E159: 210021510 | F159: Rivera Filomeno | G159: Dariel | H159: 7 | I159: 41116 | J159: Southside Academy Charter School | K159: 45904 | L159: 45957 | M159: 0.2 | N159: Good | O159: 0 | P159: SPED | Q159: =IFERROR(INDEX('ST Enroll Export'!$A$2:$A$3230,MATCH($D159,'ST Enroll Export'!$A$2:$A$3230,0)),IFERROR(IF(INDEX('ST Enroll Export'!$A$2:$A$3230,MATCH($E159,'ST Enroll Export'!$B$2:$B$3230,0))="","",INDEX('ST Enroll Export'!$A$2:$A$3230,MATCH($E159,'ST Enroll Export'!$B$2:$B$3230,0))),"Not Found")) -> 6229109670 | R159: =IFERROR(INDEX('ST Enroll Export'!$G$2:$G$3230,MATCH($D159,'ST Enroll Export'!$A$2:$A$3230,0)),IFERROR(INDEX('ST Enroll Export'!$G$2:$G$3230,MATCH($E159,'ST Enroll Export'!$B$2:$B$3230,0)),"Not Found")) -> Southside Academy Charter School | S159: =IFERROR(INDEX('ST Enroll Export'!$B$2:$B$3230,MATCH($D159,'ST Enroll Export'!$A$2:$A$3230,0)),IFERROR(INDEX('ST Enroll Export'!$B$2:$B$3230,MATCH($E159,'ST Enroll Export'!$B$2:$B$3230,0)),"Not Found")) -> 210021510 | T159: =IF(ISNUMBER(MATCH($D159,'ST Enroll Export'!$A$2:$A$3230,0)),"NYSSIS Match",IF(ISNUMBER(MATCH($E159,'ST Enroll Export'!$B$2:$B$3230,0)),"SID Match","No ST Match")) -> NYSSIS Match | U159: =IF(ISNUMBER(MATCH($D159,Disability!$B$2:$B$5962,0)),"SPED","Gen Ed") -> SPED
A160: Southside 291462 | B160: 46174 | C160: southside_291462_unified-roster.xlsx | D160: 200032748 | E160: 200032748 | F160: Rucker | G160: Daryaun | H160: 5 | I160: 41999 | J160: Southside Academy Charter School | K160: 45915 | M160: 0.95 | N160: Good | O160: 0 | P160: Gen Ed | Q160: =IFERROR(INDEX('ST Enroll Export'!$A$2:$A$3230,MATCH($D160,'ST Enroll Export'!$A$2:$A$3230,0)),IFERROR(IF(INDEX('ST Enroll Export'!$A$2:$A$3230,MATCH($E160,'ST Enroll Export'!$B$2:$B$3230,0))="","",INDEX('ST Enroll Export'!$A$2:$A$3230,MATCH($E160,'ST Enroll Export'!$B$2:$B$3230,0))),"Not Found")) -> 5089472930 | R160: =IFERROR(INDEX('ST Enroll Export'!$G$2:$G$3230,MATCH($D160,'ST Enroll Export'!$A$2:$A$3230,0)),IFERROR(INDEX('ST Enroll Export'!$G$2:$G$3230,MATCH($E160,'ST Enroll Export'!$B$2:$B$3230,0)),"Not Found")) -> Southside Academy Charter School | S160: =IFERROR(INDEX('ST Enroll Export'!$B$2:$B$3230,MATCH($D160,'ST Enroll Export'!$A$2:$A$3230,0)),IFERROR(INDEX('ST Enroll Export'!$B$2:$B$3230,MATCH($E160,'ST Enroll Export'!$B$2:$B$3230,0)),"Not Found")) -> 200032748 | T160: =IF(ISNUMBER(MATCH($D160,'ST Enroll Export'!$A$2:$A$3230,0)),"NYSSIS Match",IF(ISNUMBER(MATCH($E160,'ST Enroll Export'!$B$2:$B$3230,0)),"SID Match","No ST Match")) -> SID Match | U160: =IF(ISNUMBER(MATCH($D160,Disability!$B$2:$B$5962,0)),"SPED","Gen Ed") -> Gen Ed
A161: Southside 291462 | B161: 46174 | C161: southside_291462_unified-roster.xlsx | D161: 6015998781 | E161: 210002243 | F161: St. Louis | G161: Davion | H161: 5 | I161: 42073 | J161: Southside Academy Charter School | K161: 45903 | M161: 1 | N161: Good | O161: 0 | P161: Gen Ed | Q161: =IFERROR(INDEX('ST Enroll Export'!$A$2:$A$3230,MATCH($D161,'ST Enroll Export'!$A$2:$A$3230,0)),IFERROR(IF(INDEX('ST Enroll Export'!$A$2:$A$3230,MATCH($E161,'ST Enroll Export'!$B$2:$B$3230,0))="","",INDEX('ST Enroll Export'!$A$2:$A$3230,MATCH($E161,'ST Enroll Export'!$B$2:$B$3230,0))),"Not Found")) -> 6015998781 | R161: =IFERROR(INDEX('ST Enroll Export'!$G$2:$G$3230,MATCH($D161,'ST Enroll Export'!$A$2:$A$3230,0)),IFERROR(INDEX('ST Enroll Export'!$G$2:$G$3230,MATCH($E161,'ST Enroll Export'!$B$2:$B$3230,0)),"Not Found")) -> Southside Academy Charter School | S161: =IFERROR(INDEX('ST Enroll Export'!$B$2:$B$3230,MATCH($D161,'ST Enroll Export'!$A$2:$A$3230,0)),IFERROR(INDEX('ST Enroll Export'!$B$2:$B$3230,MATCH($E161,'ST Enroll Export'!$B$2:$B$3230,0)),"Not Found")) -> 210002243 | T161: =IF(ISNUMBER(MATCH($D161,'ST Enroll Export'!$A$2:$A$3230,0)),"NYSSIS Match",IF(ISNUMBER(MATCH($E161,'ST Enroll Export'!$B$2:$B$3230,0)),"SID Match","No ST Match")) -> NYSSIS Match | U161: =IF(ISNUMBER(MATCH($D161,Disability!$B$2:$B$5962,0)),"SPED","Gen Ed") -> Gen Ed
A162: Southside 291462 | B162: 46174 | C162: southside_291462_unified-roster.xlsx | D162: 8655911084 | E162: 200030088 | F162: Knight | G162: DaVore | H162: 7 | I162: 41481 | J162: Southside Academy Charter School | K162: 45903 | L162: 46066 | M162: 0.55 | N162: Good | O162: 0 | P162: Gen Ed | Q162: =IFERROR(INDEX('ST Enroll Export'!$A$2:$A$3230,MATCH($D162,'ST Enroll Export'!$A$2:$A$3230,0)),IFERROR(IF(INDEX('ST Enroll Export'!$A$2:$A$3230,MATCH($E162,'ST Enroll Export'!$B$2:$B$3230,0))="","",INDEX('ST Enroll Export'!$A$2:$A$3230,MATCH($E162,'ST Enroll Export'!$B$2:$B$3230,0))),"Not Found")) -> 8655911084 | R162: =IFERROR(INDEX('ST Enroll Export'!$G$2:$G$3230,MATCH($D162,'ST Enroll Export'!$A$2:$A$3230,0)),IFERROR(INDEX('ST Enroll Export'!$G$2:$G$3230,MATCH($E162,'ST Enroll Export'!$B$2:$B$3230,0)),"Not Found")) -> Southside Academy Charter School | S162: =IFERROR(INDEX('ST Enroll Export'!$B$2:$B$3230,MATCH($D162,'ST Enroll Export'!$A$2:$A$3230,0)),IFERROR(INDEX('ST Enroll Export'!$B$2:$B$3230,MATCH($E162,'ST Enroll Export'!$B$2:$B$3230,0)),"Not Found")) -> 200030088 | T162: =IF(ISNUMBER(MATCH($D162,'ST Enroll Export'!$A$2:$A$3230,0)),"NYSSIS Match",IF(ISNUMBER(MATCH($E162,'ST Enroll Export'!$B$2:$B$3230,0)),"SID Match","No ST Match")) -> NYSSIS Match | U162: =IF(ISNUMBER(MATCH($D162,Disability!$B$2:$B$5962,0)),"SPED","Gen Ed") -> Gen Ed
A163: Southside 291462 | B163: 46174 | C163: southside_291462_unified-roster.xlsx | D163: 5594297206 | E163: 200039236 | F163: Harper | G163: Dawuan | H163: 4 | I163: 42607 | J163: Southside Academy Charter School | K163: 45903 | M163: 1 | N163: Good | O163: 0 | P163: SPED | Q163: =IFERROR(INDEX('ST Enroll Export'!$A$2:$A$3230,MATCH($D163,'ST Enroll Export'!$A$2:$A$3230,0)),IFERROR(IF(INDEX('ST Enroll Export'!$A$2:$A$3230,MATCH($E163,'ST Enroll Export'!$B$2:$B$3230,0))="","",INDEX('ST Enroll Export'!$A$2:$A$3230,MATCH($E163,'ST Enroll Export'!$B$2:$B$3230,0))),"Not Found")) -> 5594297206 | R163: =IFERROR(INDEX('ST Enroll Export'!$G$2:$G$3230,MATCH($D163,'ST Enroll Export'!$A$2:$A$3230,0)),IFERROR(INDEX('ST Enroll Export'!$G$2:$G$3230,MATCH($E163,'ST Enroll Export'!$B$2:$B$3230,0)),"Not Found")) -> Southside Academy Charter School | S163: =IFERROR(INDEX('ST Enroll Export'!$B$2:$B$3230,MATCH($D163,'ST Enroll Export'!$A$2:$A$3230,0)),IFERROR(INDEX('ST Enroll Export'!$B$2:$B$3230,MATCH($E163,'ST Enroll Export'!$B$2:$B$3230,0)),"Not Found")) -> 200039236 | T163: =IF(ISNUMBER(MATCH($D163,'ST Enroll Export'!$A$2:$A$3230,0)),"NYSSIS Match",IF(ISNUMBER(MATCH($E163,'ST Enroll Export'!$B$2:$B$3230,0)),"SID Match","No ST Match")) -> NYSSIS Match | U163: =IF(ISNUMBER(MATCH($D163,Disability!$B$2:$B$5962,0)),"SPED","Gen Ed") -> SPED
A164: Southside 291462 | B164: 46174 | C164: southside_291462_unified-roster.xlsx | D164: 7290173314 | E164: 210011342 | F164: Smiley Delee | G164: Deanni | H164: 2 | I164: 42715 | J164: Southside Academy Charter School | K164: 45904 | M164: 0.975 | N164: Good | O164: 0 | P164: Gen Ed | Q164: =IFERROR(INDEX('ST Enroll Export'!$A$2:$A$3230,MATCH($D164,'ST Enroll Export'!$A$2:$A$3230,0)),IFERROR(IF(INDEX('ST Enroll Export'!$A$2:$A$3230,MATCH($E164,'ST Enroll Export'!$B$2:$B$3230,0))="","",INDEX('ST Enroll Export'!$A$2:$A$3230,MATCH($E164,'ST Enroll Export'!$B$2:$B$3230,0))),"Not Found")) -> 7290173314 | R164: =IFERROR(INDEX('ST Enroll Export'!$G$2:$G$3230,MATCH($D164,'ST Enroll Export'!$A$2:$A$3230,0)),IFERROR(INDEX('ST Enroll Export'!$G$2:$G$3230,MATCH($E164,'ST Enroll Export'!$B$2:$B$3230,0)),"Not Found")) -> Southside Academy Charter School | S164: =IFERROR(INDEX('ST Enroll Export'!$B$2:$B$3230,MATCH($D164,'ST Enroll Export'!$A$2:$A$3230,0)),IFERROR(INDEX('ST Enroll Export'!$B$2:$B$3230,MATCH($E164,'ST Enroll Export'!$B$2:$B$3230,0)),"Not Found")) -> 210011342 | T164: =IF(ISNUMBER(MATCH($D164,'ST Enroll Export'!$A$2:$A$3230,0)),"NYSSIS Match",IF(ISNUMBER(MATCH($E164,'ST Enroll Export'!$B$2:$B$3230,0)),"SID Match","No ST Match")) -> NYSSIS Match | U164: =IF(ISNUMBER(MATCH($D164,Disability!$B$2:$B$5962,0)),"SPED","Gen Ed") -> Gen Ed
...

Sheet Copy & Paste
A1: COPY & PASTE READY | Select A3:P2655, copy, paste VALUES ONLY into FY 25-26 master.
A2: Charter_Source Ticket # | B2: Charter Month | C2: Source_File | D2: NYSSIS ID | E2: Student ID | F2: Last Name | G2: First Name | H2: Grade Level | I2: DOB | J2: School Name | K2: Enroll Date | L2: Withdraw Date | M2: SCSD FTE | N2: Student Status | O2: Notes for Patrick | P2: SPED_Flag
A3: Southside 291462 | B3: 46174 | C3: southside_291462_unified-roster.xlsx | D3: 1630725543 | E3: 210010695 | F3: Thomas | G3: Aaleiyah | H3: 2 | I3: 43094 | J3: Southside Academy Charter School | K3: 45904 | M3: 1 | N3: No Good | O3: ST states: student enrolled at Southside Academy Charter School 8/2/255 - 9/1/25 . Entry date is 3> discrepancy. Need charter attendance record to change in ST. | P3: Gen Ed
A4: Southside 291462 | B4: 46174 | C4: southside_291462_unified-roster.xlsx | D4: 7417895120 | E4: 210022348 | F4: East | G4: Abel | H4: K | I4: 43993 | J4: Southside Academy Charter School | K4: 45903 | L4: 45940 | M4: 0.15 | N4: No Good | O4: ST states: student started Southside Academy Charter School 9/3/25 . Entry date is 3> discrepancy. Need charter attendance record to change in ST. | P4: Gen Ed
A5: Southside 291462 | B5: 46174 | C5: southside_291462_unified-roster.xlsx | D5: 6114934235 | E5: 200036757 | F5: Smith | G5: Adorre | H5: 4 | I5: 42225 | J5: Southside Academy Charter School | K5: 45904 | M5: 0.975 | N5: No Good | O5: ST states: student started McKiunley Brighton ES 4/8/26-current. Need charter attendance record to change in ST. | P5: SPED
A6: Southside 291462 | B6: 46174 | C6: southside_291462_unified-roster.xlsx | D6: 8894205962 | E6: 200032672 | F6: Maloof | G6: Aiden | H6: 8 | I6: 41220 | J6: Southside Academy Charter School | K6: 45903 | L6: 46077 | M6: 0.575 | N6: No Good | O6: ST states: Enrolled at Southside Academy 7/1/25-2/9/26. Enrolled at Lincoln MS 2/10/26-current. Exit date 3> discrepancy. Need charter attendance record to change in ST. | P6: Gen Ed
A7: Southside 291462 | B7: 46174 | C7: southside_291462_unified-roster.xlsx | D7: 9715356981 | E7: 210019407 | F7: McClain | G7: Ali | H7: K | I7: 44190 | J7: Southside Academy Charter School | K7: 45904 | M7: 0.975 | N7: No Good | O7: ST states: student enrolled at Southside Academy Charter 1/15/26-current. Entry date is 3> day discrepancy. Need charter attendance record to change in ST. | P7: Gen Ed
A8: Southside 291462 | B8: 46174 | C8: southside_291462_unified-roster.xlsx | D8: 7916282794 | E8: 210003054 | F8: Rufus | G8: Amir | H8: 4 | I8: 42677 | J8: Southside Academy Charter School | K8: 45909 | M8: 0.975 | N8: No Good | O8: ST states: student enrolled at Southside Academny 9/29/25. Entry date 3> day discrepancy. Need charter attendance record to change in ST. | P8: Gen Ed
A9: Southside 291462 | B9: 46174 | C9: southside_291462_unified-roster.xlsx | D9: 5016968523 | F9: Felder | G9: Anessa | H9: 1 | I9: 43675 | J9: Southside Academy Charter School | K9: 45904 | L9: 45917 | M9: 0.05 | N9: No Good | O9: ST states: No charter 25-26 enrollment in ST.Bellevue ES / ES enrollment 7/1/25 - 9/15/25. Enrolled at Van Duyn ES Van Duyn ES / ES - current. Need charter school attendance record to change in ST. | P9: Gen Ed
A10: Southside 291462 | B10: 46174 | C10: southside_291462_unified-roster.xlsx | D10: 1567036743 | E10: 210022223 | F10: Tindley | G10: Annalisse | H10: 2 | I10: 43334 | J10: Southside Academy Charter School | K10: 45915 | M10: 0.95 | N10: No Good | O10: ST states: student enrolled at Southside Academny 9/26/25. Entry date 3> day discrepancy. Need charter attendance record to change in ST. | P10: Gen Ed
A11: Southside 291462 | B11: 46174 | C11: southside_291462_unified-roster.xlsx | D11: 9622581930 | E11: 210014483 | F11: Dennis | G11: Arhianna | H11: 1 | I11: 43699 | J11: Southside Academy Charter School | K11: 45904 | L11: 45994 | M11: 0.3 | N11: No Good | O11: ST states: student enrolled at Southside Academy Charter School 8/16/25.25 11/25/25. Enrolled at HW Smith PK-8 12/1/25 - current. Entry date 3> day discrepancy. Need charter attendance record to change in ST. | P11: Gen Ed
A12: Southside 291462 | B12: 46174 | C12: southside_291462_unified-roster.xlsx | D12: 8381796603 | F12: Loper | G12: Bobby | H12: K | I12: 44194 | J12: Southside Academy Charter School | K12: 45903 | M12: 1 | N12: No Good | O12: ST states:No 25-26 charter shool enrollment entry in ST student enrolled at Bellevue ES 7/1/25-9/10/25. | P12: Gen Ed
A13: Southside 291462 | B13: 46174 | C13: southside_291462_unified-roster.xlsx | D13: 8993227873 | E13: 210019759 | F13: Reome | G13: Caylyn | H13: 1 | I13: 43543 | J13: Southside Academy Charter School | K13: 45903 | L13: 45915 | M13: 0.05 | N13: No Good | O13: ST states: student enrolled at Southside Academy 7/1/25 - 9/11/25. Exit date 3> day discrepancy. Need charter attendance record to change in ST. Enrolled at Syracuse Academy of Science Elementary at St James 9/12/25 | P13: Gen Ed
A14: Southside 291462 | B14: 46174 | C14: southside_291462_unified-roster.xlsx | D14: 5531469482 | E14: 210003314 | F14: Reome Jr. | G14: Christopher | H14: 3 | I14: 42876 | J14: Southside Academy Charter School | K14: 45903 | L14: 45915 | M14: 0.05 | N14: No Good | O14: ST states: student enrolled at Southside Academy 7/1/25 - 9/11/25. Exit date 3> day discrepancy. Need charter attendance record to change in ST. Enrolled at Syracuse Academy of Science Elementary at St James 9/12/25 | P14: Gen Ed
A15: Southside 291462 | B15: 46174 | C15: southside_291462_unified-roster.xlsx | D15: 7205350121 | E15: 210018482 | F15: Davis | G15: Cyh'Mora | H15: 1 | I15: 43826 | J15: Southside Academy Charter School | K15: 45903 | M15: 1 | N15: No Good | O15: ST states: student enrolled at Southside Academy Charter School9/25/25 - current. Entry date 3> day discrepancy. Need charter attendance record to change in ST. | P15: Gen Ed
A16: Southside 291462 | B16: 46174 | C16: southside_291462_unified-roster.xlsx | D16: 4427385530 | F16: 0 | G16: Donald | H16: K | I16: 44172 | J16: Southside Academy Charter School | K16: 45903 | M16: 1 | N16: Not in ST System | O16: Not pulling up in ST. Need more student information. NYSSIS ID, Last name,grade,parent info, gender, race, etc. | P16: Gen Ed
A17: Southside 291462 | B17: 46174 | C17: southside_291462_unified-roster.xlsx | D17: 5481567902 | E17: 210022691 | F17: Hatfield | G17: Draylan | H17: K | I17: 43853 | J17: Southside Academy Charter School | K17: 45905 | M17: 0.975 | N17: No Good | O17: ST states: student enrolled at Southside Academy Charter School 10/28/25 - current. Entry date 3> day discrepancy. Need charter attendance record to change in ST. | P17: SPED
A18: Southside 291462 | B18: 46174 | C18: southside_291462_unified-roster.xlsx | D18: 9345645621 | F18: 0 | G18: Edward | H18: K | I18: 43910 | J18: Southside Academy Charter School | K18: 45918 | M18: 0.925 | N18: Not in ST System | O18: Not pulling up in ST. Need more student information. NYSSIS ID, Last name,grade,parent info, gender, race, etc. | P18: Gen Ed
A19: Southside 291462 | B19: 46174 | C19: southside_291462_unified-roster.xlsx | D19: 3226816591 | E19: 210018247 | F19: Giddings | G19: Gracie | H19: K | I19: 44192 | J19: Southside Academy Charter School | K19: 45904 | M19: 0.975 | N19: No Good | O19: ST states: student enrolled at Southside Academy Charter School 1/7/25- current. Entry date 3> day discrepancy. Need charter attendance record to change in ST. | P19: Gen Ed
A20: Southside 291462 | B20: 46174 | C20: southside_291462_unified-roster.xlsx | D20: 8891043605 | E20: 210011263 | F20: Maldonado | G20: INessa | H20: 2 | I20: 43358 | J20: Southside Academy Charter School | K20: 45910 | M20: 0.975 | N20: No Good | O20: ST states: student enrolled at Southside Academy Charter School 11/5/25- current. Entry date 3> day discrepancy. Need charter attendance record to change in ST. | P20: SPED
A21: Southside 291462 | B21: 46174 | C21: southside_291462_unified-roster.xlsx | D21: 6207168494 | E21: 200038985 | F21: Sallard | G21: Jaliyah | H21: 4 | I21: 42561 | J21: Southside Academy Charter School | K21: 45915 | M21: 0.95 | N21: No Good | O21: ST states: student enrolled at Southside Academy Charter School 9/24/25- current. Entry date 3> day discrepancy. Need charter attendance record to change in ST. | P21: Gen Ed
A22: Southside 291462 | B22: 46174 | C22: southside_291462_unified-roster.xlsx | D22: 7360992380 | E22: 210022689 | F22: Vaughns | G22: Jayceon | H22: 2 | I22: 43318 | J22: Southside Academy Charter School | K22: 45905 | M22: 0.975 | N22: No Good | O22: ST states: student enrolled at Southside Academy Charter School 10/28/25- current. Entry date 3> day discrepancy. Need charter attendance record to change in ST. | P22: SPED
A23: Southside 291462 | B23: 46174 | C23: southside_291462_unified-roster.xlsx | D23: 9316354706 | E23: 210014757 | F23: Jackson | G23: Jordyn | H23: K | I23: 44128 | J23: Southside Academy Charter School | K23: 45903 | M23: 1 | N23: No Good | O23: ST states: student enrolled at Syracuse Academy of Science Elementary at St James 8/15/25 - 9/14/25. Enrolled at Southside Academy 9/15/25 - current. Entry 3> day discrepancy. Need charter attendance record to change in ST. | P23: Gen Ed
A24: Southside 291462 | B24: 46174 | C24: southside_291462_unified-roster.xlsx | F24: 0 | G24: Josiah | H24: 7 | I24: 41450 | J24: Southside Academy Charter School | K24: 45903 | M24: 1 | N24: Not in ST System | O24: Not pulling up in ST. | P24: Gen Ed
A25: Southside 291462 | B25: 46174 | C25: southside_291462_unified-roster.xlsx | D25: 4148681903 | E25: 210019004 | F25: Robertson | G25: Jovanni | H25: 1 | I25: 43725 | J25: Citizenship & Science Academy of Syracuse Charter | K25: 45903 | M25: 1 | N25: No Good | O25: ST states: student enrolled at Citizenship & Science Academy of Syracuse Charter 7/1/25 - 9/10/25.. Enrolled at Southside Academy 9/24/25 - current. Entry 3> day discrepancy. Need charter attendance record to change in ST. | P25: Gen Ed
A26: Southside 291462 | B26: 46174 | C26: southside_291462_unified-roster.xlsx | D26: 3321809294 | E26: 200033900 | F26: Anderson | G26: Juelez | H26: 5 | I26: 41625 | J26: Southside Academy Charter School | K26: 45903 | L26: 45995 | M26: 0.325 | N26: No Good | O26: ST states: student enrolled at Southside Academy Charter School 7/1/25- 11/24/25. Enrolled at STEAM @ Dr King / ES 11/25/25- current. Entry date 3> day discrepancy. Need charter attendance record to change in ST. | P26: SPED
A27: Southside 291462 | B27: 46174 | C27: southside_291462_unified-roster.xlsx | D27: 2807672461 | E27: 200024256 | F27: Cenzalli JR | G27: Justin | H27: 8 | I27: 41042 | J27: Southside Academy Charter School | K27: 45903 | L27: 45919 | M27: 0.075 | N27: No Good | O27: ST states: student enrolled at Southside Academy Charter School 9/6/25 - 9/11/25. Enrolled at Ed Smith PK-8 / MS 9/18/25- 2/6/25. Entry date 3> day discrepancy. Need charter attendance record to change in ST. | P27: SPED
A28: Southside 291462 | B28: 46174 | C28: southside_291462_unified-roster.xlsx | D28: 3908940154 | E28: 210002244 | F28: Lobban | G28: Kahwi | H28: 5 | I28: 41841 | J28: Southside Academy Charter School | K28: 45904 | L28: 45923 | M28: 0.05 | N28: No Good | O28: ST states: student enrolled at Southside Academy Charter School 7/1/25 - 9/8/25. Enrolled at STEAM @ Dr King / ES 9/18/25 - current. Entry date 3> day discrepancy. Need charter attendance record to change in ST. | P28: SPED
A29: Southside 291462 | B29: 46174 | C29: southside_291462_unified-roster.xlsx | D29: 4658757613 | F29: Titus | G29: Kaiden | H29: K | I29: 44196 | J29: Southside Academy Charter School | K29: 45903 | M29: 1 | N29: No Good | O29: ST states: enrolled at McKinley Brighton ES 7/3/25-9/8/25. With note that parent reported child will attend Southside. Need charter attendance report to change in ST. | P29: Gen Ed
A30: Southside 291462 | B30: 46174 | C30: southside_291462_unified-roster.xlsx | D30: 2808195416 | E30: 210017791 | F30: Maddox | G30: Kelani | H30: K | I30: 44152 | J30: Southside Academy Charter School | K30: 45917 | M30: 0.95 | N30: No Good | O30: ST states: student enrolled at Southside Academy Charter School 11/12/25- current. Entry date 3> day discrepancy. Need charter attendance record to change in ST. | P30: Gen Ed
A31: Southside 291462 | B31: 46174 | C31: southside_291462_unified-roster.xlsx | D31: 8014067546 | E31: 210022082 | F31: Suressi | G31: Kilani | H31: K | I31: 43979 | J31: Southside Academy Charter School | K31: 45905 | L31: 46010 | M31: 0.35 | N31: No Good | O31: ST states: student enrolled at Southside Academy Charter School 12/10/2025 - 12/21/2025. Entry date 3> day discrepancy. Need charter attendance record to change in ST. | P31: Gen Ed
A32: Southside 291462 | B32: 46174 | C32: southside_291462_unified-roster.xlsx | F32: 0 | G32: Kisean | H32: 0 | J32: Southside Academy Charter School | K32: 46097 | M32: 0.35 | N32: Not in ST System | O32: Not pulling up in ST. Need more student information. NYSSIS ID, Last name,grade,parent info, gender, race, etc. | P32: Gen Ed
A33: Southside 291462 | B33: 46174 | C33: southside_291462_unified-roster.xlsx | D33: 8110682342 | E33: 210006494 | F33: Matthews | G33: LaMonte | H33: 2 | I33: 43322 | J33: Southside Academy Charter School | K33: 45903 | L33: 46079 | M33: 0.6 | N33: No Good | O33: ST states: student enrolled at Southside Academy Charter School 8/25/2025 - 2/18/2026. Enrolled at Van Duyn ES / ES 2/19/26- current Entry date 3> day discrepancy. Need charter attendance record to change in ST. | P33: SPED
A34: Southside 291462 | B34: 46174 | C34: southside_291462_unified-roster.xlsx | D34: 2125386561 | F34: Brynien | G34: Liliana | H34: 4 | I34: 42384 | J34: Southside Academy Charter School | K34: 45964 | M34: 0.8 | N34: No Good | O34: No 25-26 enrollment in ST. Need charter attendance record to make change in ST. | P34: Gen Ed
A35: Southside 291462 | B35: 46174 | C35: southside_291462_unified-roster.xlsx | D35: 5279781642 | E35: 210017699 | F35: James-Haygood | G35: Llmanuel | H35: K | I35: 44110 | J35: Southside Academy Charter School | K35: 45908 | M35: 0.975 | N35: No Good | O35: ST states: Enrolled at Southside Academy Charter School 7/1/25 - 3/3/26. Need charter school attendance record to change in ST. | P35: Gen Ed
A36: Southside 291462 | B36: 46174 | C36: southside_291462_unified-roster.xlsx | D36: 6748943165 | E36: 210016382 | F36: Warde | G36: Malachi | H36: 6 | I36: 41501 | J36: Southside Academy Charter School | K36: 45903 | M36: 1 | N36: No Good | O36: ST states: student enrolled at Grant MS / MS 7/1/25 - 9/15/25. Enrolled at Southside Academy Charter School 9/16/25 - current. Entry date 3> day discrepancy. Need charter attendance record to change in ST. | P36: Gen Ed
A37: Southside 291462 | B37: 46174 | C37: southside_291462_unified-roster.xlsx | D37: 4302512531 | E37: 210002246 | F37: Lobban | G37: Mehki | H37: 5 | I37: 41841 | J37: Southside Academy Charter School | K37: 45904 | L37: 45919 | M37: 0.05 | N37: No Good | O37: ST states: student enrolled at Southside Academy Charter School 7/1/2025 - 9/8/2025. Enrolled at STEAM @ Dr King / ES 9/18/25 - current. Entry date 3> day discrepancy. Need charter attendance record to change in ST. | P37: SPED
A38: Southside 291462 | B38: 46174 | C38: southside_291462_unified-roster.xlsx | D38: 8460982760 | E38: 210022815 | F38: Lindsey | G38: Nadir | H38: K | I38: 44033 | J38: Southside Academy Charter School | K38: 45964 | L38: 46010 | M38: 0.175 | N38: No Good | O38: ST states: Enrolled at Southside Academy Charter School 11/12/25-current. Entry date 3> day discrepancy. Need charter school attendance record to change in ST. | P38: Gen Ed
A39: Southside 291462 | B39: 46174 | C39: southside_291462_unified-roster.xlsx | D39: 2981769541 | E39: 210009975 | F39: Smith | G39: Natalia | H39: 1 | I39: 43468 | J39: Southside Academy Charter School | K39: 45968 | M39: 0.775 | N39: No Good | O39: ST states: student enrolled at Southside Academy Charter School 12/10/2025 - current. Entry date 3> day discrepancy. Need charter attendance record to change in ST. | P39: Gen Ed
A40: Southside 291462 | B40: 46174 | C40: southside_291462_unified-roster.xlsx | D40: 6994835771 | F40: Morris | G40: Rahmier | H40: K | I40: 44148 | J40: Southside Academy Charter School | K40: 45903 | L40: 45923 | M40: 0.075 | N40: No Good | O40: No enrollment record in ST. Need charter school attendance to create enrollment entry in ST. | P40: Gen Ed
A41: Southside 291462 | B41: 46174 | C41: southside_291462_unified-roster.xlsx | D41: 1565701023 | E41: 210022225 | F41: Tarrats | G41: Ruben | H41: 7 | I41: 41464 | J41: Southside Academy Charter School | K41: 45915 | M41: 0.95 | N41: No Good | O41: ST states: student enrolled at Southside Academy Charter School 10/15/2025 - current. Entry date 3> day discrepancy. Need charter attendance record to change in ST. | P41: Gen Ed
A42: Southside 291462 | B42: 46174 | C42: southside_291462_unified-roster.xlsx | D42: 1348451822 | E42: 210022690 | F42: Moore | G42: Samya | H42: 4 | I42: 42401 | J42: Southside Academy Charter School | K42: 45905 | M42: 0.975 | N42: No Good | O42: ST states: Enrolled at Southside Academy Charter School 10/27/25-current. Entry date 3> day discrepancy. Need charter school attendance record to change in ST. | P42: Gen Ed
A43: Southside 291462 | B43: 46174 | C43: southside_291462_unified-roster.xlsx | D43: 6885359396 | F43: Thurman | G43: Xavier | H43: 1 | I43: 43656 | J43: Southside Academy Charter School | K43: 45903 | L43: 45981 | M43: 0.275 | N43: No Good | O43: No charter enrollment for current year 25-26 in ST. Only Projected Enrollment for Southside Academy for 7/1/26. Need charter attendance record to change in ST. | P43: Gen Ed
A44: Southside 291462 | B44: 46174 | C44: southside_291462_unified-roster.xlsx | D44: 9391717043 | E44: 210022224 | F44: Tarrats | G44: Zailashay | H44: 6 | I44: 41897 | J44: Southside Academy Charter School | K44: 45930 | M44: 0.9 | N44: No Good | O44: ST states: student enrolled at Southside Academy Charter School 10/15/2025 - current. Entry date 3> day discrepancy. Need charter attendance record to change in ST. | P44: Gen Ed
A45: Southside 291462 | B45: 46174 | C45: southside_291462_unified-roster.xlsx | D45: 3015231426 | E45: 210023269 | F45: Walker | G45: Zayvian | H45: K | I45: 43861 | J45: Southside Academy Charter School | K45: 45903 | M45: 1 | N45: No Good | O45: ST states: student enrolled at Southside Academy on 4/9/26- current. 3> day discrepancy. Need charter attendance record to change in ST. | P45: Gen Ed
A46: Southside 291462 | B46: 46174 | C46: southside_291462_unified-roster.xlsx | D46: 5714663321 | E46: 200036826 | F46: Parrilla | G46: Aaminah | H46: 6 | I46: 41964 | J46: Southside Academy Charter School | K46: 45903 | M46: 1 | N46: Good | O46: 0 | P46: SPED
A47: Southside 291462 | B47: 46174 | C47: southside_291462_unified-roster.xlsx | D47: 9977865516 | E47: 210018968 | F47: Lynch | G47: Aaron | H47: 1 | I47: 43557 | J47: Southside Academy Charter School | K47: 45915 | M47: 0.95 | N47: Good | O47: 0 | P47: Gen Ed
A48: Southside 291462 | B48: 46174 | C48: southside_291462_unified-roster.xlsx | D48: 4986713632 | E48: 210003070 | F48: Smith | G48: Aaron | H48: 5 | I48: 41842 | J48: Southside Academy Charter School | K48: 45903 | M48: 1 | N48: Good | O48: 0 | P48: Gen Ed
A49: Southside 291462 | B49: 46174 | C49: southside_291462_unified-roster.xlsx | D49: 9323458081 | E49: 210014696 | F49: Anderson | G49: Aayden | H49: 1 | I49: 43550 | J49: Southside Academy Charter School | K49: 45903 | L49: 46085 | M49: 0.625 | N49: Good | O49: 0 | P49: SPED
A50: Southside 291462 | B50: 46174 | C50: southside_291462_unified-roster.xlsx | D50: 1983806742 | E50: 210018426 | F50: Durham | G50: Adam | H50: 1 | I50: 43605 | J50: Southside Academy Charter School | K50: 45903 | M50: 1 | N50: Good | O50: 0 | P50: Gen Ed
A51: Southside 291462 | B51: 46174 | C51: southside_291462_unified-roster.xlsx | D51: 9265754471 | E51: 200031166 | F51: Perdomo | G51: Adelina | H51: 7 | I51: 41281 | J51: Southside Academy Charter School | K51: 45903 | M51: 1 | N51: Good | O51: 0 | P51: Gen Ed
A52: Southside 291462 | B52: 46174 | C52: southside_291462_unified-roster.xlsx | D52: 2349311626 | E52: 200026850 | F52: Mann | G52: Adonis | H52: 8 | I52: 40622 | J52: Southside Academy Charter School | K52: 45903 | M52: 1 | N52: Good | O52: 0 | P52: SPED
A53: Southside 291462 | B53: 46174 | C53: southside_291462_unified-roster.xlsx | D53: 6920438320 | E53: 210005255 | F53: Smith | G53: Adoriannah | H53: 6 | I53: 41864 | J53: Southside Academy Charter School | K53: 45908 | M53: 0.975 | N53: Good | O53: 0 | P53: Gen Ed
A54: Southside 291462 | B54: 46174 | C54: southside_291462_unified-roster.xlsx | D54: 2859324671 | E54: 200030533 | F54: Harris | G54: Adrayla | H54: 8 | I54: 41151 | J54: Southside Academy Charter School | K54: 45903 | M54: 1 | N54: Good | O54: 0 | P54: Gen Ed
A55: Southside 291462 | B55: 46174 | C55: southside_291462_unified-roster.xlsx | D55: 9004836816 | E55: 210007545 | F55: Rowland | G55: Adrianna | H55: 8 | I55: 40934 | J55: Southside Academy Charter School | K55: 45903 | M55: 1 | N55: Good | O55: 0 | P55: Gen Ed
A56: Southside 291462 | B56: 46174 | C56: southside_291462_unified-roster.xlsx | D56: 4798198643 | E56: 210011819 | F56: Davis | G56: A-Drianna | H56: 1 | I56: 43589 | J56: Southside Academy Charter School | K56: 45903 | M56: 1 | N56: Good | O56: 0 | P56: Gen Ed
A57: Southside 291462 | B57: 46174 | C57: southside_291462_unified-roster.xlsx | D57: 5716749290 | E57: 200038876 | F57: Green-Hayward | G57: AdriElla | H57: 6 | I57: 41861 | J57: Southside Academy Charter School | K57: 45903 | M57: 1 | N57: Good | O57: 0 | P57: Gen Ed
A58: Southside 291462 | B58: 46174 | C58: southside_291462_unified-roster.xlsx | D58: 9816245530 | E58: 210016421 | F58: Timori | G58: Ahmad | H58: 5 | I58: 41917 | J58: Southside Academy Charter School | K58: 45903 | M58: 1 | N58: Good | O58: 0 | P58: Gen Ed
A59: Southside 291462 | B59: 46174 | C59: southside_291462_unified-roster.xlsx | D59: 9112250374 | E59: 210004384 | F59: Capers | G59: Aiden | H59: 4 | I59: 42418 | J59: Southside Academy Charter School | K59: 45903 | M59: 1 | N59: Good | O59: 0 | P59: Gen Ed
A60: Southside 291462 | B60: 46174 | C60: southside_291462_unified-roster.xlsx | D60: 5308675136 | E60: 210017359 | F60: Akot | G60: Akot | H60: K | I60: 44049 | J60: Southside Academy Charter School | K60: 45903 | L60: 46052 | M60: 0.5 | N60: Good | O60: 0 | P60: Gen Ed
A61: Southside 291462 | B61: 46174 | C61: southside_291462_unified-roster.xlsx | D61: 6862971750 | E61: 200030599 | F61: Kodet | G61: Alana | H61: 7 | I61: 41500 | J61: Southside Academy Charter School | K61: 45903 | M61: 1 | N61: Good | O61: 0 | P61: Gen Ed
A62: Southside 291462 | B62: 46174 | C62: southside_291462_unified-roster.xlsx | D62: 1012369440 | E62: 210004998 | F62: Salem | G62: Alanna | H62: 4 | I62: 42475 | J62: Southside Academy Charter School | K62: 45903 | M62: 1 | N62: Good | O62: 0 | P62: Gen Ed
A63: Southside 291462 | B63: 46174 | C63: southside_291462_unified-roster.xlsx | D63: 4003684191 | E63: 200038430 | F63: Tillie | G63: Alayiah | H63: 4 | I63: 42281 | J63: Southside Academy Charter School | K63: 45903 | M63: 1 | N63: Good | O63: 0 | P63: SPED
A64: Southside 291462 | B64: 46174 | C64: southside_291462_unified-roster.xlsx | D64: 8037443260 | E64: 210012357 | F64: Allan Jr | G64: Alexander | H64: 3 | I64: 42781 | J64: Southside Academy Charter School | K64: 45918 | M64: 0.925 | N64: Good | O64: 0 | P64: SPED
A65: Southside 291462 | B65: 46174 | C65: southside_291462_unified-roster.xlsx | D65: 1757340380 | E65: 210005851 | F65: May | G65: Alina | H65: 2 | I65: 43109 | J65: Southside Academy Charter School | K65: 45903 | M65: 1 | N65: Good | O65: 0 | P65: SPED
A66: Southside 291462 | B66: 46174 | C66: southside_291462_unified-roster.xlsx | D66: 9247943203 | E66: 200032807 | F66: Aiken | G66: Aliya | H66: 8 | I66: 41174 | J66: Southside Academy Charter School | K66: 45903 | M66: 1 | N66: Good | O66: 0 | P66: Gen Ed
A67: Southside 291462 | B67: 46174 | C67: southside_291462_unified-roster.xlsx | D67: 2018797941 | E67: 200037650 | F67: Blunt | G67: Aliyah | H67: 5 | I67: 42094 | J67: Southside Academy Charter School | K67: 45903 | M67: 1 | N67: Good | O67: 0 | P67: Gen Ed
A68: Southside 291462 | B68: 46174 | C68: southside_291462_unified-roster.xlsx | D68: 7271659280 | E68: 200038218 | F68: Smith | G68: Allanna | H68: 6 | I68: 41726 | J68: Southside Academy Charter School | K68: 45903 | L68: 46059 | M68: 0.525 | N68: Good | O68: 0 | P68: Gen Ed
A69: Southside 291462 | B69: 46174 | C69: southside_291462_unified-roster.xlsx | D69: 200029382 | E69: 200029382 | F69: Colon | G69: Alyani | H69: 8 | I69: 40559 | J69: Southside Academy Charter School | K69: 45903 | M69: 1 | N69: Good | O69: 0 | P69: Gen Ed
A70: Southside 291462 | B70: 46174 | C70: southside_291462_unified-roster.xlsx | D70: 2799458756 | E70: 210004202 | F70: Jacobs | G70: Amara | H70: 3 | I70: 42788 | J70: Southside Academy Charter School | K70: 45909 | M70: 0.975 | N70: Good | O70: 0 | P70: Gen Ed
A71: Southside 291462 | B71: 46174 | C71: southside_291462_unified-roster.xlsx | D71: 3948567923 | E71: 200029630 | F71: Coston | G71: Amare | H71: 6 | I71: 41522 | J71: Southside Academy Charter School | K71: 45903 | M71: 1 | N71: Good | O71: 0 | P71: Gen Ed
A72: Southside 291462 | B72: 46174 | C72: southside_291462_unified-roster.xlsx | D72: 2365285906 | E72: 210004781 | F72: McFadden | G72: Amari | H72: 2 | I72: 43026 | J72: Southside Academy Charter School | K72: 45903 | M72: 1 | N72: Good | O72: 0 | P72: SPED
A73: Southside 291462 | B73: 46174 | C73: southside_291462_unified-roster.xlsx | D73: 5003227753 | E73: 200037678 | F73: Vega Davila | G73: Amarilys | H73: 5 | I73: 41985 | J73: Southside Academy Charter School | K73: 45903 | M73: 1 | N73: Good | O73: 0 | P73: Gen Ed
A74: Southside 291462 | B74: 46174 | C74: southside_291462_unified-roster.xlsx | D74: 1647851873 | E74: 210004236 | F74: Morales | G74: Amaya | H74: 5 | I74: 41740 | J74: Southside Academy Charter School | K74: 45903 | M74: 1 | N74: Good | O74: 0 | P74: Gen Ed
A75: Southside 291462 | B75: 46174 | C75: southside_291462_unified-roster.xlsx | D75: 1635879015 | E75: 210004000 | F75: Ruiz-Mclain | G75: Ameliah | H75: 4 | I75: 42388 | J75: Southside Academy Charter School | K75: 45903 | M75: 1 | N75: Good | O75: 0 | P75: Gen Ed
A76: Southside 291462 | B76: 46174 | C76: southside_291462_unified-roster.xlsx | D76: 2567760593 | E76: 200030543 | F76: Chandler | G76: Amerie | H76: 7 | I76: 41095 | J76: Southside Academy Charter School | K76: 45903 | M76: 1 | N76: Good | O76: 0 | P76: Gen Ed
A77: Southside 291462 | B77: 46174 | C77: southside_291462_unified-roster.xlsx | D77: 8535798744 | E77: 210017318 | F77: Clifton | G77: Amias | H77: K | I77: 43817 | J77: Southside Academy Charter School | K77: 45903 | M77: 1 | N77: Good | O77: 0 | P77: Gen Ed
A78: Southside 291462 | B78: 46174 | C78: southside_291462_unified-roster.xlsx | D78: 6124086535 | E78: 210007964 | F78: Cirino | G78: Amir | H78: 3 | I78: 42940 | J78: Southside Academy Charter School | K78: 45904 | M78: 0.975 | N78: Good | O78: 0 | P78: Gen Ed
A79: Southside 291462 | B79: 46174 | C79: southside_291462_unified-roster.xlsx | D79: 2741058673 | E79: 210011629 | F79: Johnson | G79: Amir | H79: 2 | I79: 43132 | J79: Southside Academy Charter School | K79: 45904 | M79: 0.975 | N79: Good | O79: 0 | P79: Gen Ed
A80: Southside 291462 | B80: 46174 | C80: southside_291462_unified-roster.xlsx | D80: 3898545173 | E80: 200037239 | F80: Aiken | G80: Amira | H80: 6 | I80: 41632 | J80: Southside Academy Charter School | K80: 45903 | M80: 1 | N80: Good | O80: 0 | P80: Gen Ed
... A96: Southside 291462 | B96: 46174 | C96: southside_291462_unified-roster.xlsx | D96: 8775651313 | E96: 210013145 | F96: Stroman | G96: Anthony | H96: 3 | I96: 42916 | J96: Southside Academy Charter School | K96: 45903 | M96: 1 | N96: Good | O96: 0 | P96: Gen Ed
A97: Southside 291462 | B97: 46174 | C97: southside_291462_unified-roster.xlsx | D97: 9394640522 | E97: 210010093 | F97: Davis-El | G97: Anubis | H97: 2 | I97: 43011 | J97: Southside Academy Charter School | K97: 45903 | L97: 45940 | M97: 0.15 | N97: Good | O97: 0 | P97: Gen Ed
A98: Southside 291462 | B98: 46174 | C98: southside_291462_unified-roster.xlsx | D98: 9394640522 | E98: 210010093 | F98: Davis-El | G98: Anubis | H98: 2 | I98: 43011 | J98: Southside Academy Charter School | K98: 46042 | M98: 0.55 | N98: Good | O98: 0 | P98: Gen Ed
